Workbook
Name Pagamento: Set!$F$2:$F$3
Name Compra: Set!$B$2:$B$3
Name Avaliados: Set!$D$2:$D$3

Sheet Calcular
B1: Tipo de Compra | E1: Pagamento | F1: Total | K1: z | M1: 1775679826593 | N1: 1782854443666 | O1: Olá isadora! *Avaliação Mania* 1782854443666 2. macaquinho 3. vestido 4. blazer 5. blazer 6. blusa modal 7. macaquinho 8. vestido 9. calça 10. calça 11. calça 12. calça 13. cinta 14. blusa 15. blusa 16. blusa 17. blusa 18. blusa 19. blusa 20. blusa 21. casaco 22. vestido 23. short 24. short 25. short 26. short 27. short 28. short 29. short 30. short 31. academia b 32. short 33. short 34. saia 35. saia 36. saia 37. saia 38. saia 39. blusa 40. blusa 41. blusa 42. blusa 43. blusa 44. blusa 45. blusa 46. blusa 47. blusa 48. blusa 49. top 50. body 51. academia 52. academia 53. academia 54. academia 55. academia 56. academia 57. academia 58. camiseta 59. camiseta 60. camiseta 61. camiseta 62. melissa possession 63. botero sandalia Total em Dinheiro: ou *Em Créditos na Loja: *R$407,50* - Assumimos o frete para envio cliente ➡loja. - Essa avaliação é baseada no valor das melissas em perfeitas condições e sem avarias ou detalhes. - A recepção e conferência da chegada é sempre filmada e disponibilizada para o cliente.
A2: isadora | B2: Avaliados | E2: Em Dinheiro | F2: =IF(AND(B2="Direta", B4="N/A"),SUM(I7:I72)+N4,IF(AND(B2="Avaliados",B4="Do Clube"),"Clube: só em Creditos", IF(AND(B2="Avaliados",B4="Fora do Clube"),(SUM(N8:N72))-(SUM(N8:N72)*60%)-N4,"-")) ) -> 0 | K2: Altura | L2: =(Set!J2+((E5-1)*0.8)) -> 11.2
B3: Tipo de Fornecedor | E3: Em Credito | F3: =IF(AND(B2="Direta" , B4="N/A"),"Direta: só Em Dinheiro",IF(AND(B2="Avaliados",B4="Do Clube"),(SUM(N8:N72))-(SUM(N8:N72)*20%)-N4, IF(AND(B2="Avaliados",B4="Fora do Clube"),(SUM(N8:N72))-(SUM(N8:N72)*40%)-N4,"-")) ) -> 0 | H3: Valor da Venda(na Compra Direta) | K3: Largura | L3: =(Set!J3+((E5-1)*1)) -> 20.8
B4: Fora do Clube | K4: Comprimento | L4: =(Set!J4+((E5-1)*1.3)) -> 30.2
E5: =COUNTIF(N8:N72,">0") -> 0 | F5: Valor de Compra | K5: Peso | L5: =Set!J5+(($E$5-1)*0.5) -> 0
D6: Min | E6: Fabricação | F6: Em Dinheiro | G6: Em Credito
G7: =IF(N8="","-",IF(AND($B$2="Direta" , $B$4="N/A"),"Só Em Dinheiro",IF(AND($B$2="Avaliados",$B$4="Do Clube"),N8-(N8*20%)-($N$4/$E$5),IF(AND($B$2="Avaliados",$B$4="Fora do Clube"),N8-(N8*40%)-($N$4/$E$5),"-")) )) -> - | H7: =$N$4/$E$5 -> #DIV/0! | I7: =IF($B$2="Avaliados",H7-H7,N8*'Precificação'!$C$38) -> #DIV/0! | J7: =IF(I7>0,H7+I7,0) -> #DIV/0!
A8: macaquinho | C8: 35 | G8: =IF(N9="","-",IF(AND($B$2="Direta" , $B$4="N/A"),"Só Em Dinheiro",IF(AND($B$2="Avaliados",$B$4="Do Clube"),N9-(N9*20%)-($N$4/$E$5),IF(AND($B$2="Avaliados",$B$4="Fora do Clube"),N9-(N9*40%)-($N$4/$E$5),"-")) )) -> - | H8: =$N$4/$E$5 -> #DIV/0! | I8: =IF($B$2="Avaliados",H8-H8,N9*'Precificação'!$C$38) -> #DIV/0! | J8: =IF(I8>0,H8+I8,0) -> #DIV/0!
A9: vestido | C9: 35 | D9: 0 | G9: =IF(N10="","-",IF(AND($B$2="Direta" , $B$4="N/A"),"Só Em Dinheiro",IF(AND($B$2="Avaliados",$B$4="Do Clube"),N10-(N10*20%)-($N$4/$E$5),IF(AND($B$2="Avaliados",$B$4="Fora do Clube"),N10-(N10*40%)-($N$4/$E$5),"-")) )) -> - | H9: =$N$4/$E$5 -> #DIV/0! | I9: =IF($B$2="Avaliados",H9-H9,N10*'Precificação'!$C$38) -> #DIV/0! | J9: =IF(I9>0,H9+I9,0) -> #DIV/0!
A10: blazer | C10: 35 | D10: 0 | G10: =IF(N11="","-",IF(AND($B$2="Direta" , $B$4="N/A"),"Só Em Dinheiro",IF(AND($B$2="Avaliados",$B$4="Do Clube"),N11-(N11*20%)-($N$4/$E$5),IF(AND($B$2="Avaliados",$B$4="Fora do Clube"),N11-(N11*40%)-($N$4/$E$5),"-")) )) -> - | H10: =$N$4/$E$5 -> #DIV/0! | I10: =IF($B$2="Avaliados",H10-H10,N11*'Precificação'!$C$38) -> #DIV/0! | J10: =IF(I10>0,H10+I10,0) -> #DIV/0!
A11: blazer | C11: 35 | D11: 0 | G11: =IF(#REF!="","-",IF(AND($B$2="Direta" , $B$4="N/A"),"Só Em Dinheiro",IF(AND($B$2="Avaliados",$B$4="Do Clube"),#REF!-(#REF!*20%)-($N$4/$E$5),IF(AND($B$2="Avaliados",$B$4="Fora do Clube"),#REF!-(#REF!*40%)-($N$4/$E$5),"-")) )) -> #REF! | H11: =$N$4/$E$5 -> #DIV/0! | I11: =IF($B$2="Avaliados",H11-H11,#REF!*'Precificação'!$C$38) -> #DIV/0! | J11: =IF(I11>0,H11+I11,0) -> #DIV/0!
A12: blusa modal | C12: 30 | D12: =MINIFS('Variação'!I:I,'Variação'!B:B,B12) -> 0 | G12: =IF(N12="","-",IF(AND($B$2="Direta" , $B$4="N/A"),"Só Em Dinheiro",IF(AND($B$2="Avaliados",$B$4="Do Clube"),N12-(N12*20%)-($N$4/$E$5),IF(AND($B$2="Avaliados",$B$4="Fora do Clube"),N12-(N12*40%)-($N$4/$E$5),"-")) )) -> - | H12: =$N$4/$E$5 -> #DIV/0! | I12: =IF($B$2="Avaliados",H12-H12,N12*'Precificação'!$C$38) -> #DIV/0! | J12: =IF(I12>0,H12+I12,0) -> #DIV/0!
A13: macaquinho | C13: 30 | D13: =MINIFS('Variação'!I:I,'Variação'!B:B,B13) -> 0 | G13: =IF(N13="","-",IF(AND($B$2="Direta" , $B$4="N/A"),"Só Em Dinheiro",IF(AND($B$2="Avaliados",$B$4="Do Clube"),N13-(N13*20%)-($N$4/$E$5),IF(AND($B$2="Avaliados",$B$4="Fora do Clube"),N13-(N13*40%)-($N$4/$E$5),"-")) )) -> - | H13: =$N$4/$E$5 -> #DIV/0! | I13: =IF($B$2="Avaliados",H13-H13,N13*'Precificação'!$C$38) -> #DIV/0! | J13: =IF(I13>0,H13+I13,0) -> #DIV/0!
A14: vestido | C14: 25 | D14: =MINIFS('Variação'!I:I,'Variação'!B:B,B14) -> 0 | G14: =IF(N14="","-",IF(AND($B$2="Direta" , $B$4="N/A"),"Só Em Dinheiro",IF(AND($B$2="Avaliados",$B$4="Do Clube"),N14-(N14*20%)-($N$4/$E$5),IF(AND($B$2="Avaliados",$B$4="Fora do Clube"),N14-(N14*40%)-($N$4/$E$5),"-")) )) -> - | H14: =$N$4/$E$5 -> #DIV/0! | I14: =IF($B$2="Avaliados",H14-H14,N14*'Precificação'!$C$38) -> #DIV/0! | J14: =IF(I14>0,H14+I14,0) -> #DIV/0!
A15: calça | C15: 25 | D15: =MINIFS('Variação'!I:I,'Variação'!B:B,B15) -> 0 | G15: =IF(N15="","-",IF(AND($B$2="Direta" , $B$4="N/A"),"Só Em Dinheiro",IF(AND($B$2="Avaliados",$B$4="Do Clube"),N15-(N15*20%)-($N$4/$E$5),IF(AND($B$2="Avaliados",$B$4="Fora do Clube"),N15-(N15*40%)-($N$4/$E$5),"-")) )) -> - | H15: =$N$4/$E$5 -> #DIV/0! | I15: =IF($B$2="Avaliados",H15-H15,N15*'Precificação'!$C$38) -> #DIV/0! | J15: =IF(I15>0,H15+I15,0) -> #DIV/0!
A16: calça | C16: 25 | D16: =MINIFS('Variação'!I:I,'Variação'!B:B,B16) -> 0 | G16: =IF(N16="","-",IF(AND($B$2="Direta" , $B$4="N/A"),"Só Em Dinheiro",IF(AND($B$2="Avaliados",$B$4="Do Clube"),N16-(N16*20%)-($N$4/$E$5),IF(AND($B$2="Avaliados",$B$4="Fora do Clube"),N16-(N16*40%)-($N$4/$E$5),"-")) )) -> - | H16: =$N$4/$E$5 -> #DIV/0! | I16: =IF($B$2="Avaliados",H16-H16,N16*'Precificação'!$C$38) -> #DIV/0! | J16: =IF(I16>0,H16+I16,0) -> #DIV/0!
A17: calça | C17: 25 | D17: =MINIFS('Variação'!I:I,'Variação'!B:B,B17) -> 0 | G17: =IF(N17="","-",IF(AND($B$2="Direta" , $B$4="N/A"),"Só Em Dinheiro",IF(AND($B$2="Avaliados",$B$4="Do Clube"),N17-(N17*20%)-($N$4/$E$5),IF(AND($B$2="Avaliados",$B$4="Fora do Clube"),N17-(N17*40%)-($N$4/$E$5),"-")) )) -> - | H17: =$N$4/$E$5 -> #DIV/0! | I17: =IF($B$2="Avaliados",H17-H17,N17*'Precificação'!$C$38) -> #DIV/0! | J17: =IF(I17>0,H17+I17,0) -> #DIV/0!
A18: calça | C18: 25 | D18: =MINIFS('Variação'!I:I,'Variação'!B:B,B18) -> 0 | G18: =IF(N18="","-",IF(AND($B$2="Direta" , $B$4="N/A"),"Só Em Dinheiro",IF(AND($B$2="Avaliados",$B$4="Do Clube"),N18-(N18*20%)-($N$4/$E$5),IF(AND($B$2="Avaliados",$B$4="Fora do Clube"),N18-(N18*40%)-($N$4/$E$5),"-")) )) -> - | H18: =$N$4/$E$5 -> #DIV/0! | I18: =IF($B$2="Avaliados",H18-H18,N18*'Precificação'!$C$38) -> #DIV/0! | J18: =IF(I18>0,H18+I18,0) -> #DIV/0!
A19: cinta | C19: 25 | D19: =MINIFS('Variação'!I:I,'Variação'!B:B,B19) -> 0 | G19: =IF(N19="","-",IF(AND($B$2="Direta" , $B$4="N/A"),"Só Em Dinheiro",IF(AND($B$2="Avaliados",$B$4="Do Clube"),N19-(N19*20%)-($N$4/$E$5),IF(AND($B$2="Avaliados",$B$4="Fora do Clube"),N19-(N19*40%)-($N$4/$E$5),"-")) )) -> - | H19: =$N$4/$E$5 -> #DIV/0! | I19: =IF($B$2="Avaliados",H19-H19,N19*'Precificação'!$C$38) -> #DIV/0! | J19: =IF(I19>0,H19+I19,0) -> #DIV/0!
A20: blusa | C20: 25 | D20: =MINIFS('Variação'!I:I,'Variação'!B:B,B20) -> 0 | G20: =IF(N20="","-",IF(AND($B$2="Direta" , $B$4="N/A"),"Só Em Dinheiro",IF(AND($B$2="Avaliados",$B$4="Do Clube"),N20-(N20*20%)-($N$4/$E$5),IF(AND($B$2="Avaliados",$B$4="Fora do Clube"),N20-(N20*40%)-($N$4/$E$5),"-")) )) -> - | H20: =$N$4/$E$5 -> #DIV/0! | I20: =IF($B$2="Avaliados",H20-H20,N20*'Precificação'!$C$38) -> #DIV/0! | J20: =IF(I20>0,H20+I20,0) -> #DIV/0!
A21: blusa | C21: 25 | D21: =MINIFS('Variação'!I:I,'Variação'!B:B,B21) -> 0 | G21: =IF(N21="","-",IF(AND($B$2="Direta" , $B$4="N/A"),"Só Em Dinheiro",IF(AND($B$2="Avaliados",$B$4="Do Clube"),N21-(N21*20%)-($N$4/$E$5),IF(AND($B$2="Avaliados",$B$4="Fora do Clube"),N21-(N21*40%)-($N$4/$E$5),"-")) )) -> - | H21: =$N$4/$E$5 -> #DIV/0! | I21: =IF($B$2="Avaliados",H21-H21,N21*'Precificação'!$C$38) -> #DIV/0! | J21: =IF(I21>0,H21+I21,0) -> #DIV/0!
A22: blusa | C22: 25 | G22: =IF(N22="","-",IF(AND($B$2="Direta" , $B$4="N/A"),"Só Em Dinheiro",IF(AND($B$2="Avaliados",$B$4="Do Clube"),N22-(N22*20%)-($N$4/$E$5),IF(AND($B$2="Avaliados",$B$4="Fora do Clube"),N22-(N22*40%)-($N$4/$E$5),"-")) )) -> - | H22: =$N$4/$E$5 -> #DIV/0! | I22: =IF($B$2="Avaliados",H22-H22,N22*'Precificação'!$C$38) -> #DIV/0! | J22: =IF(I22>0,H22+I22,0) -> #DIV/0!
A23: blusa | C23: 25 | D23: =MINIFS('Variação'!I:I,'Variação'!B:B,B23) -> 0 | G23: =IF(N23="","-",IF(AND($B$2="Direta" , $B$4="N/A"),"Só Em Dinheiro",IF(AND($B$2="Avaliados",$B$4="Do Clube"),N23-(N23*20%)-($N$4/$E$5),IF(AND($B$2="Avaliados",$B$4="Fora do Clube"),N23-(N23*40%)-($N$4/$E$5),"-")) )) -> - | H23: =$N$4/$E$5 -> #DIV/0! | I23: =IF($B$2="Avaliados",H23-H23,N23*'Precificação'!$C$38) -> #DIV/0! | J23: =IF(I23>0,H23+I23,0) -> #DIV/0!
A24: blusa | C24: 25 | D24: =MINIFS('Variação'!I:I,'Variação'!B:B,B24) -> 0 | G24: =IF(N24="","-",IF(AND($B$2="Direta" , $B$4="N/A"),"Só Em Dinheiro",IF(AND($B$2="Avaliados",$B$4="Do Clube"),N24-(N24*20%)-($N$4/$E$5),IF(AND($B$2="Avaliados",$B$4="Fora do Clube"),N24-(N24*40%)-($N$4/$E$5),"-")) )) -> - | H24: =$N$4/$E$5 -> #DIV/0! | I24: =IF($B$2="Avaliados",H24-H24,N24*'Precificação'!$C$38) -> #DIV/0! | J24: =IF(I24>0,H24+I24,0) -> #DIV/0!
A25: blusa | C25: 25 | D25: =MINIFS('Variação'!I:I,'Variação'!B:B,B25) -> 0 | G25: =IF(N25="","-",IF(AND($B$2="Direta" , $B$4="N/A"),"Só Em Dinheiro",IF(AND($B$2="Avaliados",$B$4="Do Clube"),N25-(N25*20%)-($N$4/$E$5),IF(AND($B$2="Avaliados",$B$4="Fora do Clube"),N25-(N25*40%)-($N$4/$E$5),"-")) )) -> - | H25: =$N$4/$E$5 -> #DIV/0! | I25: =IF($B$2="Avaliados",H25-H25,N25*'Precificação'!$C$38) -> #DIV/0! | J25: =IF(I25>0,H25+I25,0) -> #DIV/0!
A26: blusa | C26: 25 | D26: =MINIFS('Variação'!I:I,'Variação'!B:B,B26) -> 0 | G26: =IF(N26="","-",IF(AND($B$2="Direta" , $B$4="N/A"),"Só Em Dinheiro",IF(AND($B$2="Avaliados",$B$4="Do Clube"),N26-(N26*20%)-($N$4/$E$5),IF(AND($B$2="Avaliados",$B$4="Fora do Clube"),N26-(N26*40%)-($N$4/$E$5),"-")) )) -> - | H26: =$N$4/$E$5 -> #DIV/0! | I26: =IF($B$2="Avaliados",H26-H26,N26*'Precificação'!$C$38) -> #DIV/0! | J26: =IF(I26>0,H26+I26,0) -> #DIV/0!
A27: casaco | C27: 25 | D27: =MINIFS('Variação'!I:I,'Variação'!B:B,B27) -> 0 | G27: =IF(N27="","-",IF(AND($B$2="Direta" , $B$4="N/A"),"Só Em Dinheiro",IF(AND($B$2="Avaliados",$B$4="Do Clube"),N27-(N27*20%)-($N$4/$E$5),IF(AND($B$2="Avaliados",$B$4="Fora do Clube"),N27-(N27*40%)-($N$4/$E$5),"-")) )) -> - | H27: =$N$4/$E$5 -> #DIV/0! | I27: =IF($B$2="Avaliados",H27-H27,N27*'Precificação'!$C$38) -> #DIV/0! | J27: =IF(I27>0,H27+I27,0) -> #DIV/0!
A28: vestido | C28: 25 | D28: =MINIFS('Variação'!I:I,'Variação'!B:B,B28) -> 0 | G28: =IF(N28="","-",IF(AND($B$2="Direta" , $B$4="N/A"),"Só Em Dinheiro",IF(AND($B$2="Avaliados",$B$4="Do Clube"),N28-(N28*20%)-($N$4/$E$5),IF(AND($B$2="Avaliados",$B$4="Fora do Clube"),N28-(N28*40%)-($N$4/$E$5),"-")) )) -> - | H28: =$N$4/$E$5 -> #DIV/0! | I28: =IF($B$2="Avaliados",H28-H28,N28*'Precificação'!$C$38) -> #DIV/0! | J28: =IF(I28>0,H28+I28,0) -> #DIV/0!
A29: short | C29: 25 | D29: =MINIFS('Variação'!I:I,'Variação'!B:B,B29) -> 0 | G29: =IF(N29="","-",IF(AND($B$2="Direta" , $B$4="N/A"),"Só Em Dinheiro",IF(AND($B$2="Avaliados",$B$4="Do Clube"),N29-(N29*20%)-($N$4/$E$5),IF(AND($B$2="Avaliados",$B$4="Fora do Clube"),N29-(N29*40%)-($N$4/$E$5),"-")) )) -> - | H29: =$N$4/$E$5 -> #DIV/0! | I29: =IF($B$2="Avaliados",H29-H29,N29*'Precificação'!$C$38) -> #DIV/0! | J29: =IF(I29>0,H29+I29,0) -> #DIV/0!
A30: short | C30: 25 | D30: =MINIFS('Variação'!I:I,'Variação'!B:B,B30) -> 0 | G30: =IF(N30="","-",IF(AND($B$2="Direta" , $B$4="N/A"),"Só Em Dinheiro",IF(AND($B$2="Avaliados",$B$4="Do Clube"),N30-(N30*20%)-($N$4/$E$5),IF(AND($B$2="Avaliados",$B$4="Fora do Clube"),N30-(N30*40%)-($N$4/$E$5),"-")) )) -> - | H30: =$N$4/$E$5 -> #DIV/0! | I30: =IF($B$2="Avaliados",H30-H30,N30*'Precificação'!$C$38) -> #DIV/0! | J30: =IF(I30>0,H30+I30,0) -> #DIV/0!
A31: short | C31: 25 | D31: =MINIFS('Variação'!I:I,'Variação'!B:B,B31) -> 0 | G31: =IF(N31="","-",IF(AND($B$2="Direta" , $B$4="N/A"),"Só Em Dinheiro",IF(AND($B$2="Avaliados",$B$4="Do Clube"),N31-(N31*20%)-($N$4/$E$5),IF(AND($B$2="Avaliados",$B$4="Fora do Clube"),N31-(N31*40%)-($N$4/$E$5),"-")) )) -> - | H31: =$N$4/$E$5 -> #DIV/0! | I31: =IF($B$2="Avaliados",H31-H31,N31*'Precificação'!$C$38) -> #DIV/0!
A32: short | C32: 25 | G32: =IF(N32="","-",IF(AND($B$2="Direta" , $B$4="N/A"),"Só Em Dinheiro",IF(AND($B$2="Avaliados",$B$4="Do Clube"),N32-(N32*20%)-($N$4/$E$5),IF(AND($B$2="Avaliados",$B$4="Fora do Clube"),N32-(N32*40%)-($N$4/$E$5),"-")) )) -> - | H32: =$N$4/$E$5 -> #DIV/0! | I32: =IF($B$2="Avaliados",H32-H32,N32*'Precificação'!$C$38) -> #DIV/0! | J32: =IF(I32>0,H32+I32,0) -> #DIV/0!
A33: short | C33: 25 | D33: =MINIFS('Variação'!I:I,'Variação'!B:B,B33) -> 0 | G33: =IF(N33="","-",IF(AND($B$2="Direta" , $B$4="N/A"),"Só Em Dinheiro",IF(AND($B$2="Avaliados",$B$4="Do Clube"),N33-(N33*20%)-($N$4/$E$5),IF(AND($B$2="Avaliados",$B$4="Fora do Clube"),N33-(N33*40%)-($N$4/$E$5),"-")) )) -> - | H33: =$N$4/$E$5 -> #DIV/0! | I33: =IF($B$2="Avaliados",H33-H33,N33*'Precificação'!$C$38) -> #DIV/0!
A34: short | C34: 25 | D34: =MINIFS('Variação'!I:I,'Variação'!B:B,B34) -> 0 | G34: =IF(N34="","-",IF(AND($B$2="Direta" , $B$4="N/A"),"Só Em Dinheiro",IF(AND($B$2="Avaliados",$B$4="Do Clube"),N34-(N34*20%)-($N$4/$E$5),IF(AND($B$2="Avaliados",$B$4="Fora do Clube"),N34-(N34*40%)-($N$4/$E$5),"-")) )) -> - | H34: =$N$4/$E$5 -> #DIV/0! | I34: =IF($B$2="Avaliados",H34-H34,N34*'Precificação'!$C$38) -> #DIV/0! | J34: =IF(I34>0,H34+I34,0) -> #DIV/0!
A35: short | C35: 25
A36: short | C36: 25 | D36: =MINIFS('Variação'!I:I,'Variação'!B:B,B36) -> 0 | G36: =IF(N36="","-",IF(AND($B$2="Direta" , $B$4="N/A"),"Só Em Dinheiro",IF(AND($B$2="Avaliados",$B$4="Do Clube"),N36-(N36*20%)-($N$4/$E$5),IF(AND($B$2="Avaliados",$B$4="Fora do Clube"),N36-(N36*40%)-($N$4/$E$5),"-")) )) -> - | H36: =$N$4/$E$5 -> #DIV/0! | I36: =IF($B$2="Avaliados",H36-H36,N36*'Precificação'!$C$38) -> #DIV/0! | J36: =IF(I36>0,H36+I36,0) -> #DIV/0!
A37: academia b | C37: 25 | D37: =MINIFS('Variação'!I:I,'Variação'!B:B,B37) -> 0 | G37: =IF(N37="","-",IF(AND($B$2="Direta" , $B$4="N/A"),"Só Em Dinheiro",IF(AND($B$2="Avaliados",$B$4="Do Clube"),N37-(N37*20%)-($N$4/$E$5),IF(AND($B$2="Avaliados",$B$4="Fora do Clube"),N37-(N37*40%)-($N$4/$E$5),"-")) )) -> - | H37: =$N$4/$E$5 -> #DIV/0! | I37: =IF($B$2="Avaliados",H37-H37,N37*'Precificação'!$C$38) -> #DIV/0! | J37: =IF(I37>0,H37+I37,0) -> #DIV/0!
A38: short | C38: 20 | D38: =MINIFS('Variação'!I:I,'Variação'!B:B,B38) -> 0 | G38: =IF(N38="","-",IF(AND($B$2="Direta" , $B$4="N/A"),"Só Em Dinheiro",IF(AND($B$2="Avaliados",$B$4="Do Clube"),N38-(N38*20%)-($N$4/$E$5),IF(AND($B$2="Avaliados",$B$4="Fora do Clube"),N38-(N38*40%)-($N$4/$E$5),"-")) )) -> - | H38: =$N$4/$E$5 -> #DIV/0! | I38: =IF($B$2="Avaliados",H38-H38,N38*'Precificação'!$C$38) -> #DIV/0! | J38: =IF(I38>0,H38+I38,0) -> #DIV/0!
A39: short | C39: 20 | D39: =MINIFS('Variação'!I:I,'Variação'!B:B,B39) -> 0 | G39: =IF(N39="","-",IF(AND($B$2="Direta" , $B$4="N/A"),"Só Em Dinheiro",IF(AND($B$2="Avaliados",$B$4="Do Clube"),N39-(N39*20%)-($N$4/$E$5),IF(AND($B$2="Avaliados",$B$4="Fora do Clube"),N39-(N39*40%)-($N$4/$E$5),"-")) )) -> - | H39: =$N$4/$E$5 -> #DIV/0! | I39: =IF($B$2="Avaliados",H39-H39,N39*'Precificação'!$C$38) -> #DIV/0! | J39: =IF(I39>0,H39+I39,0) -> #DIV/0!
A40: saia | C40: 20 | D40: =MINIFS('Variação'!I:I,'Variação'!B:B,B40) -> 0 | G40: =IF(N40="","-",IF(AND($B$2="Direta" , $B$4="N/A"),"Só Em Dinheiro",IF(AND($B$2="Avaliados",$B$4="Do Clube"),N40-(N40*20%)-($N$4/$E$5),IF(AND($B$2="Avaliados",$B$4="Fora do Clube"),N40-(N40*40%)-($N$4/$E$5),"-")) )) -> - | H40: =$N$4/$E$5 -> #DIV/0! | I40: =IF($B$2="Avaliados",H40-H40,N40*'Precificação'!$C$38) -> #DIV/0! | J40: =IF(I40>0,H40+I40,0) -> #DIV/0!
A41: saia | C41: 20 | D41: =MINIFS('Variação'!I:I,'Variação'!B:B,B41) -> 0 | G41: =IF(N41="","-",IF(AND($B$2="Direta" , $B$4="N/A"),"Só Em Dinheiro",IF(AND($B$2="Avaliados",$B$4="Do Clube"),N41-(N41*20%)-($N$4/$E$5),IF(AND($B$2="Avaliados",$B$4="Fora do Clube"),N41-(N41*40%)-($N$4/$E$5),"-")) )) -> - | H41: =$N$4/$E$5 -> #DIV/0! | I41: =IF($B$2="Avaliados",H41-H41,N41*'Precificação'!$C$38) -> #DIV/0! | J41: =IF(I41>0,H41+I41,0) -> #DIV/0!
A42: saia | C42: 20 | D42: =MINIFS('Variação'!I:I,'Variação'!B:B,B42) -> 0 | G42: =IF(N42="","-",IF(AND($B$2="Direta" , $B$4="N/A"),"Só Em Dinheiro",IF(AND($B$2="Avaliados",$B$4="Do Clube"),N42-(N42*20%)-($N$4/$E$5),IF(AND($B$2="Avaliados",$B$4="Fora do Clube"),N42-(N42*40%)-($N$4/$E$5),"-")) )) -> - | H42: =$N$4/$E$5 -> #DIV/0! | I42: =IF($B$2="Avaliados",H42-H42,N42*'Precificação'!$C$38) -> #DIV/0! | J42: =IF(I42>0,H42+I42,0) -> #DIV/0!
A43: saia | C43: 20 | D43: =MINIFS('Variação'!I:I,'Variação'!B:B,B43) -> 0 | G43: =IF(N43="","-",IF(AND($B$2="Direta" , $B$4="N/A"),"Só Em Dinheiro",IF(AND($B$2="Avaliados",$B$4="Do Clube"),N43-(N43*20%)-($N$4/$E$5),IF(AND($B$2="Avaliados",$B$4="Fora do Clube"),N43-(N43*40%)-($N$4/$E$5),"-")) )) -> - | H43: =$N$4/$E$5 -> #DIV/0! | I43: =IF($B$2="Avaliados",H43-H43,N43*'Precificação'!$C$38) -> #DIV/0! | J43: =IF(I43>0,H43+I43,0) -> #DIV/0!
A44: saia | C44: 20 | D44: =MINIFS('Variação'!I:I,'Variação'!B:B,B44) -> 0 | G44: =IF(N44="","-",IF(AND($B$2="Direta" , $B$4="N/A"),"Só Em Dinheiro",IF(AND($B$2="Avaliados",$B$4="Do Clube"),N44-(N44*20%)-($N$4/$E$5),IF(AND($B$2="Avaliados",$B$4="Fora do Clube"),N44-(N44*40%)-($N$4/$E$5),"-")) )) -> - | H44: =$N$4/$E$5 -> #DIV/0! | I44: =IF($B$2="Avaliados",H44-H44,N44*'Precificação'!$C$38) -> #DIV/0! | J44: =IF(I44>0,H44+I44,0) -> #DIV/0!
A45: blusa | C45: 20 | D45: =MINIFS('Variação'!I:I,'Variação'!B:B,B45) -> 0 | G45: =IF(N45="","-",IF(AND($B$2="Direta" , $B$4="N/A"),"Só Em Dinheiro",IF(AND($B$2="Avaliados",$B$4="Do Clube"),N45-(N45*20%)-($N$4/$E$5),IF(AND($B$2="Avaliados",$B$4="Fora do Clube"),N45-(N45*40%)-($N$4/$E$5),"-")) )) -> - | H45: =$N$4/$E$5 -> #DIV/0! | I45: =IF($B$2="Avaliados",H45-H45,N45*'Precificação'!$C$38) -> #DIV/0! | J45: =IF(I45>0,H45+I45,0) -> #DIV/0!
A46: blusa | C46: 20 | D46: =MINIFS('Variação'!I:I,'Variação'!B:B,B46) -> 0 | G46: =IF(N46="","-",IF(AND($B$2="Direta" , $B$4="N/A"),"Só Em Dinheiro",IF(AND($B$2="Avaliados",$B$4="Do Clube"),N46-(N46*20%)-($N$4/$E$5),IF(AND($B$2="Avaliados",$B$4="Fora do Clube"),N46-(N46*40%)-($N$4/$E$5),"-")) )) -> - | H46: =$N$4/$E$5 -> #DIV/0! | I46: =IF($B$2="Avaliados",H46-H46,N46*'Precificação'!$C$38) -> #DIV/0! | J46: =IF(I46>0,H46+I46,0) -> #DIV/0!
A47: blusa | C47: 20 | D47: =MINIFS('Variação'!I:I,'Variação'!B:B,B47) -> 0 | G47: =IF(N47="","-",IF(AND($B$2="Direta" , $B$4="N/A"),"Só Em Dinheiro",IF(AND($B$2="Avaliados",$B$4="Do Clube"),N47-(N47*20%)-($N$4/$E$5),IF(AND($B$2="Avaliados",$B$4="Fora do Clube"),N47-(N47*40%)-($N$4/$E$5),"-")) )) -> - | H47: =$N$4/$E$5 -> #DIV/0! | I47: =IF($B$2="Avaliados",H47-H47,N47*'Precificação'!$C$38) -> #DIV/0! | J47: =IF(I47>0,H47+I47,0) -> #DIV/0!
... A69: boterro sandalia | C69: 45 | D69: =MINIFS('Variação'!I:I,'Variação'!B:B,B69) -> 0 | G69: =IF(N69="","-",IF(AND($B$2="Direta" , $B$4="N/A"),"Só Em Dinheiro",IF(AND($B$2="Avaliados",$B$4="Do Clube"),N69-(N69*20%)-($N$4/$E$5),IF(AND($B$2="Avaliados",$B$4="Fora do Clube"),N69-(N69*40%)-($N$4/$E$5),"-")) )) -> - | H69: =$N$4/$E$5 -> #DIV/0! | I69: =IF($B$2="Avaliados",H69-H69,N69*'Precificação'!$C$38) -> #DIV/0! | J69: =IF(I69>0,H69+I69,0) -> #DIV/0!
D70: =MINIFS('Variação'!I:I,'Variação'!B:B,B70) -> 0 | G70: =IF(N70="","-",IF(AND($B$2="Direta" , $B$4="N/A"),"Só Em Dinheiro",IF(AND($B$2="Avaliados",$B$4="Do Clube"),N70-(N70*20%)-($N$4/$E$5),IF(AND($B$2="Avaliados",$B$4="Fora do Clube"),N70-(N70*40%)-($N$4/$E$5),"-")) )) -> - | H70: =$N$4/$E$5 -> #DIV/0! | I70: =IF($B$2="Avaliados",H70-H70,N70*'Precificação'!$C$38) -> #DIV/0! | J70: =IF(I70>0,H70+I70,0) -> #DIV/0!
D71: =MINIFS('Variação'!I:I,'Variação'!B:B,B71) -> 0 | G71: =IF(N71="","-",IF(AND($B$2="Direta" , $B$4="N/A"),"Só Em Dinheiro",IF(AND($B$2="Avaliados",$B$4="Do Clube"),N71-(N71*20%)-($N$4/$E$5),IF(AND($B$2="Avaliados",$B$4="Fora do Clube"),N71-(N71*40%)-($N$4/$E$5),"-")) )) -> - | H71: =$N$4/$E$5 -> #DIV/0! | I71: =IF($B$2="Avaliados",H71-H71,N71*'Precificação'!$C$38) -> #DIV/0! | J71: =IF(I71>0,H71+I71,0) -> #DIV/0!
D72: =MINIFS('Variação'!I:I,'Variação'!B:B,B72) -> 0 | G72: =IF(N72="","-",IF(AND($B$2="Direta" , $B$4="N/A"),"Só Em Dinheiro",IF(AND($B$2="Avaliados",$B$4="Do Clube"),N72-(N72*20%)-($N$4/$E$5),IF(AND($B$2="Avaliados",$B$4="Fora do Clube"),N72-(N72*40%)-($N$4/$E$5),"-")) )) -> - | H72: =$N$4/$E$5 -> #DIV/0! | I72: =IF($B$2="Avaliados",H72-H72,N72*'Precificação'!$C$38) -> #DIV/0! | J72: =IF(I72>0,H72+I72,0) -> #DIV/0!
D73: =MINIFS('Variação'!I:I,'Variação'!B:B,B73) -> 0 | G73: =IF(N73="","-",IF(AND($B$2="Direta" , $B$4="N/A"),"Só Em Dinheiro",IF(AND($B$2="Avaliados",$B$4="Do Clube"),N73-(N73*20%)-($N$4/$E$5),IF(AND($B$2="Avaliados",$B$4="Fora do Clube"),N73-(N73*40%)-($N$4/$E$5),"-")) )) -> - | H73: =$N$4/$E$5 -> #DIV/0! | I73: =IF($B$2="Avaliados",H73-H73,N73*'Precificação'!$C$38) -> #DIV/0! | J73: =IF(I73>0,H73+I73,0) -> #DIV/0!
D74: =MINIFS('Variação'!I:I,'Variação'!B:B,B74) -> 0 | G74: =IF(N74="","-",IF(AND($B$2="Direta" , $B$4="N/A"),"Só Em Dinheiro",IF(AND($B$2="Avaliados",$B$4="Do Clube"),N74-(N74*20%)-($N$4/$E$5),IF(AND($B$2="Avaliados",$B$4="Fora do Clube"),N74-(N74*40%)-($N$4/$E$5),"-")) )) -> - | H74: =$N$4/$E$5 -> #DIV/0! | I74: =IF($B$2="Avaliados",H74-H74,N74*'Precificação'!$C$38) -> #DIV/0! | J74: =IF(I74>0,H74+I74,0) -> #DIV/0!
D75: =MINIFS('Variação'!I:I,'Variação'!B:B,B75) -> 0 | G75: =IF(N75="","-",IF(AND($B$2="Direta" , $B$4="N/A"),"Só Em Dinheiro",IF(AND($B$2="Avaliados",$B$4="Do Clube"),N75-(N75*20%)-($N$4/$E$5),IF(AND($B$2="Avaliados",$B$4="Fora do Clube"),N75-(N75*40%)-($N$4/$E$5),"-")) )) -> - | H75: =$N$4/$E$5 -> #DIV/0! | I75: =IF($B$2="Avaliados",H75-H75,N75*'Precificação'!$C$38) -> #DIV/0! | J75: =IF(I75>0,H75+I75,0) -> #DIV/0!
D76: =MINIFS('Variação'!I:I,'Variação'!B:B,B76) -> 0 | G76: =IF(N76="","-",IF(AND($B$2="Direta" , $B$4="N/A"),"Só Em Dinheiro",IF(AND($B$2="Avaliados",$B$4="Do Clube"),N76-(N76*20%)-($N$4/$E$5),IF(AND($B$2="Avaliados",$B$4="Fora do Clube"),N76-(N76*40%)-($N$4/$E$5),"-")) )) -> - | H76: =$N$4/$E$5 -> #DIV/0! | I76: =IF($B$2="Avaliados",H76-H76,N76*'Precificação'!$C$38) -> #DIV/0! | J76: =IF(I76>0,H76+I76,0) -> #DIV/0!
D77: =MINIFS('Variação'!I:I,'Variação'!B:B,B77) -> 0 | G77: =IF(N77="","-",IF(AND($B$2="Direta" , $B$4="N/A"),"Só Em Dinheiro",IF(AND($B$2="Avaliados",$B$4="Do Clube"),N77-(N77*20%)-($N$4/$E$5),IF(AND($B$2="Avaliados",$B$4="Fora do Clube"),N77-(N77*40%)-($N$4/$E$5),"-")) )) -> - | H77: =$N$4/$E$5 -> #DIV/0! | I77: =IF($B$2="Avaliados",H77-H77,N77*'Precificação'!$C$38) -> #DIV/0! | J77: =IF(I77>0,H77+I77,0) -> #DIV/0!
G78: =IF(N78="","-",IF(AND($B$2="Direta" , $B$4="N/A"),"Só Em Dinheiro",IF(AND($B$2="Avaliados",$B$4="Do Clube"),N78-(N78*20%)-($N$4/$E$5),IF(AND($B$2="Avaliados",$B$4="Fora do Clube"),N78-(N78*40%)-($N$4/$E$5),"-")) )) -> - | H78: =$N$4/$E$5 -> #DIV/0! | I78: =IF($B$2="Avaliados",H78-H78,N78*'Precificação'!$C$38) -> #DIV/0! | J78: =IF(I78>0,H78+I78,0) -> #DIV/0!
G79: =IF(N79="","-",IF(AND($B$2="Direta" , $B$4="N/A"),"Só Em Dinheiro",IF(AND($B$2="Avaliados",$B$4="Do Clube"),N79-(N79*20%)-($N$4/$E$5),IF(AND($B$2="Avaliados",$B$4="Fora do Clube"),N79-(N79*40%)-($N$4/$E$5),"-")) )) -> - | H79: =$N$4/$E$5 -> #DIV/0! | I79: =IF($B$2="Avaliados",H79-H79,N79*'Precificação'!$C$38) -> #DIV/0! | J79: =IF(I79>0,H79+I79,0) -> #DIV/0!
G80: =IF(N80="","-",IF(AND($B$2="Direta" , $B$4="N/A"),"Só Em Dinheiro",IF(AND($B$2="Avaliados",$B$4="Do Clube"),N80-(N80*20%)-($N$4/$E$5),IF(AND($B$2="Avaliados",$B$4="Fora do Clube"),N80-(N80*40%)-($N$4/$E$5),"-")) )) -> - | H80: =$N$4/$E$5 -> #DIV/0! | I80: =IF($B$2="Avaliados",H80-H80,N80*'Precificação'!$C$38) -> #DIV/0! | J80: =IF(I80>0,H80+I80,0) -> #DIV/0!
F81: =IF(N81="","-",IF(AND($B$2="Direta", $B$4="N/A"),J81,IF(AND($B$2="Avaliados",$B$4="Do Clube"),"Só em Creditos",IF(AND($B$2="Avaliados",$B$4="Fora do Clube"),N81-(N81*60%)-($N$4/$E$5),"-")) )) -> - | G81: =IF(N81="","-",IF(AND($B$2="Direta" , $B$4="N/A"),"Só Em Dinheiro",IF(AND($B$2="Avaliados",$B$4="Do Clube"),N81-(N81*20%)-($N$4/$E$5),IF(AND($B$2="Avaliados",$B$4="Fora do Clube"),N81-(N81*40%)-($N$4/$E$5),"-")) )) -> - | H81: =$N$4/$E$5 -> #DIV/0! | I81: =IF($B$2="Avaliados",H81-H81,N81*'Precificação'!$C$38) -> #DIV/0! | J81: =IF(I81>0,H81+I81,0) -> #DIV/0!
F82: =IF(N82="","-",IF(AND($B$2="Direta", $B$4="N/A"),J82,IF(AND($B$2="Avaliados",$B$4="Do Clube"),"Só em Creditos",IF(AND($B$2="Avaliados",$B$4="Fora do Clube"),N82-(N82*60%)-($N$4/$E$5),"-")) )) -> - | G82: =IF(N82="","-",IF(AND($B$2="Direta" , $B$4="N/A"),"Só Em Dinheiro",IF(AND($B$2="Avaliados",$B$4="Do Clube"),N82-(N82*20%)-($N$4/$E$5),IF(AND($B$2="Avaliados",$B$4="Fora do Clube"),N82-(N82*40%)-($N$4/$E$5),"-")) )) -> - | H82: =$N$4/$E$5 -> #DIV/0! | I82: =IF($B$2="Avaliados",H82-H82,N82*'Precificação'!$C$38) -> #DIV/0! | J82: =IF(I82>0,H82+I82,0) -> #DIV/0!
F83: =IF(N83="","-",IF(AND($B$2="Direta", $B$4="N/A"),J83,IF(AND($B$2="Avaliados",$B$4="Do Clube"),"Só em Creditos",IF(AND($B$2="Avaliados",$B$4="Fora do Clube"),N83-(N83*60%)-($N$4/$E$5),"-")) )) -> - | G83: =IF(N83="","-",IF(AND($B$2="Direta" , $B$4="N/A"),"Só Em Dinheiro",IF(AND($B$2="Avaliados",$B$4="Do Clube"),N83-(N83*20%)-($N$4/$E$5),IF(AND($B$2="Avaliados",$B$4="Fora do Clube"),N83-(N83*40%)-($N$4/$E$5),"-")) )) -> - | H83: =$N$4/$E$5 -> #DIV/0! | I83: =IF($B$2="Avaliados",H83-H83,N83*'Precificação'!$C$38) -> #DIV/0! | J83: =IF(I83>0,H83+I83,0) -> #DIV/0!
F84: =IF(N84="","-",IF(AND($B$2="Direta", $B$4="N/A"),J84,IF(AND($B$2="Avaliados",$B$4="Do Clube"),"Só em Creditos",IF(AND($B$2="Avaliados",$B$4="Fora do Clube"),N84-(N84*60%)-($N$4/$E$5),"-")) )) -> - | G84: =IF(N84="","-",IF(AND($B$2="Direta" , $B$4="N/A"),"Só Em Dinheiro",IF(AND($B$2="Avaliados",$B$4="Do Clube"),N84-(N84*20%)-($N$4/$E$5),IF(AND($B$2="Avaliados",$B$4="Fora do Clube"),N84-(N84*40%)-($N$4/$E$5),"-")) )) -> - | H84: =$N$4/$E$5 -> #DIV/0! | I84: =IF($B$2="Avaliados",H84-H84,N84*'Precificação'!$C$38) -> #DIV/0! | J84: =IF(I84>0,H84+I84,0) -> #DIV/0!
F85: =IF(N85="","-",IF(AND($B$2="Direta", $B$4="N/A"),J85,IF(AND($B$2="Avaliados",$B$4="Do Clube"),"Só em Creditos",IF(AND($B$2="Avaliados",$B$4="Fora do Clube"),N85-(N85*60%)-($N$4/$E$5),"-")) )) -> - | G85: =IF(N85="","-",IF(AND($B$2="Direta" , $B$4="N/A"),"Só Em Dinheiro",IF(AND($B$2="Avaliados",$B$4="Do Clube"),N85-(N85*20%)-($N$4/$E$5),IF(AND($B$2="Avaliados",$B$4="Fora do Clube"),N85-(N85*40%)-($N$4/$E$5),"-")) )) -> - | H85: =$N$4/$E$5 -> #DIV/0! | I85: =IF($B$2="Avaliados",H85-H85,N85*'Precificação'!$C$38) -> #DIV/0! | J85: =IF(I85>0,H85+I85,0) -> #DIV/0!
F86: =IF(N86="","-",IF(AND($B$2="Direta", $B$4="N/A"),J86,IF(AND($B$2="Avaliados",$B$4="Do Clube"),"Só em Creditos",IF(AND($B$2="Avaliados",$B$4="Fora do Clube"),N86-(N86*60%)-($N$4/$E$5),"-")) )) -> - | G86: =IF(N86="","-",IF(AND($B$2="Direta" , $B$4="N/A"),"Só Em Dinheiro",IF(AND($B$2="Avaliados",$B$4="Do Clube"),N86-(N86*20%)-($N$4/$E$5),IF(AND($B$2="Avaliados",$B$4="Fora do Clube"),N86-(N86*40%)-($N$4/$E$5),"-")) )) -> - | H86: =$N$4/$E$5 -> #DIV/0! | I86: =IF($B$2="Avaliados",H86-H86,N86*'Precificação'!$C$38) -> #DIV/0! | J86: =IF(I86>0,H86+I86,0) -> #DIV/0!
F87: =IF(N87="","-",IF(AND($B$2="Direta", $B$4="N/A"),J87,IF(AND($B$2="Avaliados",$B$4="Do Clube"),"Só em Creditos",IF(AND($B$2="Avaliados",$B$4="Fora do Clube"),N87-(N87*60%)-($N$4/$E$5),"-")) )) -> - | G87: =IF(N87="","-",IF(AND($B$2="Direta" , $B$4="N/A"),"Só Em Dinheiro",IF(AND($B$2="Avaliados",$B$4="Do Clube"),N87-(N87*20%)-($N$4/$E$5),IF(AND($B$2="Avaliados",$B$4="Fora do Clube"),N87-(N87*40%)-($N$4/$E$5),"-")) )) -> - | H87: =$N$4/$E$5 -> #DIV/0! | I87: =IF($B$2="Avaliados",H87-H87,N87*'Precificação'!$C$38) -> #DIV/0! | J87: =IF(I87>0,H87+I87,0) -> #DIV/0!
F88: =IF(N88="","-",IF(AND($B$2="Direta", $B$4="N/A"),J88,IF(AND($B$2="Avaliados",$B$4="Do Clube"),"Só em Creditos",IF(AND($B$2="Avaliados",$B$4="Fora do Clube"),N88-(N88*60%)-($N$4/$E$5),"-")) )) -> - | G88: =IF(N88="","-",IF(AND($B$2="Direta" , $B$4="N/A"),"Só Em Dinheiro",IF(AND($B$2="Avaliados",$B$4="Do Clube"),N88-(N88*20%)-($N$4/$E$5),IF(AND($B$2="Avaliados",$B$4="Fora do Clube"),N88-(N88*40%)-($N$4/$E$5),"-")) )) -> - | H88: =$N$4/$E$5 -> #DIV/0! | I88: =IF($B$2="Avaliados",H88-H88,N88*'Precificação'!$C$38) -> #DIV/0! | J88: =IF(I88>0,H88+I88,0) -> #DIV/0!
F89: =IF(N89="","-",IF(AND($B$2="Direta", $B$4="N/A"),J89,IF(AND($B$2="Avaliados",$B$4="Do Clube"),"Só em Creditos",IF(AND($B$2="Avaliados",$B$4="Fora do Clube"),N89-(N89*60%)-($N$4/$E$5),"-")) )) -> - | G89: =IF(N89="","-",IF(AND($B$2="Direta" , $B$4="N/A"),"Só Em Dinheiro",IF(AND($B$2="Avaliados",$B$4="Do Clube"),N89-(N89*20%)-($N$4/$E$5),IF(AND($B$2="Avaliados",$B$4="Fora do Clube"),N89-(N89*40%)-($N$4/$E$5),"-")) )) -> - | H89: =$N$4/$E$5 -> #DIV/0! | I89: =IF($B$2="Avaliados",H89-H89,N89*'Precificação'!$C$38) -> #DIV/0! | J89: =IF(I89>0,H89+I89,0) -> #DIV/0!
F90: =IF(N90="","-",IF(AND($B$2="Direta", $B$4="N/A"),J90,IF(AND($B$2="Avaliados",$B$4="Do Clube"),"Só em Creditos",IF(AND($B$2="Avaliados",$B$4="Fora do Clube"),N90-(N90*60%)-($N$4/$E$5),"-")) )) -> - | G90: =IF(N90="","-",IF(AND($B$2="Direta" , $B$4="N/A"),"Só Em Dinheiro",IF(AND($B$2="Avaliados",$B$4="Do Clube"),N90-(N90*20%)-($N$4/$E$5),IF(AND($B$2="Avaliados",$B$4="Fora do Clube"),N90-(N90*40%)-($N$4/$E$5),"-")) )) -> - | H90: =$N$4/$E$5 -> #DIV/0! | I90: =IF($B$2="Avaliados",H90-H90,N90*'Precificação'!$C$38) -> #DIV/0! | J90: =IF(I90>0,H90+I90,0) -> #DIV/0!
F91: =IF(N91="","-",IF(AND($B$2="Direta", $B$4="N/A"),J91,IF(AND($B$2="Avaliados",$B$4="Do Clube"),"Só em Creditos",IF(AND($B$2="Avaliados",$B$4="Fora do Clube"),N91-(N91*60%)-($N$4/$E$5),"-")) )) -> - | G91: =IF(N91="","-",IF(AND($B$2="Direta" , $B$4="N/A"),"Só Em Dinheiro",IF(AND($B$2="Avaliados",$B$4="Do Clube"),N91-(N91*20%)-($N$4/$E$5),IF(AND($B$2="Avaliados",$B$4="Fora do Clube"),N91-(N91*40%)-($N$4/$E$5),"-")) )) -> - | H91: =$N$4/$E$5 -> #DIV/0! | I91: =IF($B$2="Avaliados",H91-H91,N91*'Precificação'!$C$38) -> #DIV/0! | J91: =IF(I91>0,H91+I91,0) -> #DIV/0!
F92: =IF(N92="","-",IF(AND($B$2="Direta", $B$4="N/A"),J92,IF(AND($B$2="Avaliados",$B$4="Do Clube"),"Só em Creditos",IF(AND($B$2="Avaliados",$B$4="Fora do Clube"),N92-(N92*60%)-($N$4/$E$5),"-")) )) -> - | G92: =IF(N92="","-",IF(AND($B$2="Direta" , $B$4="N/A"),"Só Em Dinheiro",IF(AND($B$2="Avaliados",$B$4="Do Clube"),N92-(N92*20%)-($N$4/$E$5),IF(AND($B$2="Avaliados",$B$4="Fora do Clube"),N92-(N92*40%)-($N$4/$E$5),"-")) )) -> - | H92: =$N$4/$E$5 -> #DIV/0! | I92: =IF($B$2="Avaliados",H92-H92,N92*'Precificação'!$C$38) -> #DIV/0! | J92: =IF(I92>0,H92+I92,0) -> #DIV/0!
... F107: =IF(N107="","-",IF(AND($B$2="Direta", $B$4="N/A"),J107,IF(AND($B$2="Avaliados",$B$4="Do Clube"),"Só em Creditos",IF(AND($B$2="Avaliados",$B$4="Fora do Clube"),N107-(N107*60%)-($N$4/$E$5),"-")) )) -> - | G107: =IF(N107="","-",IF(AND($B$2="Direta" , $B$4="N/A"),"Só Em Dinheiro",IF(AND($B$2="Avaliados",$B$4="Do Clube"),N107-(N107*20%)-($N$4/$E$5),IF(AND($B$2="Avaliados",$B$4="Fora do Clube"),N107-(N107*40%)-($N$4/$E$5),"-")) )) -> - | H107: =$N$4/$E$5 -> #DIV/0! | I107: =IF($B$2="Avaliados",H107-H107,N107*'Precificação'!$C$38) -> #DIV/0! | J107: =IF(I107>0,H107+I107,0) -> #DIV/0!

Sheet Página20

Sheet Página19
A2: Código loja
A3: Código categoria
A4: Data cadastro
A5: Nome produto
A6: Código produto
A7: Imagem principal
A8: Imagem 2
A9: Imagem 3
A10: Imagem 4
A11: Preço venda
A12: Peso
A13: Frete
... A47: Nome categoria

Sheet Variação
A1: Código variação | B1: Código produto | C1: EAN | D1: Variação principal | E1: Valor variação principal | F1: Variação 2 | G1: Valor variação 2 | H1: Peso | I1: Preço venda | J1: Estoque | K1: Quantidade vendida | L1: Preço custo | M1: Inicio promoção | N1: Fim promoção | O1: Preço promoção | P1: Referência | Q1: Imagem | R1: Comprimento | S1: Largura | T1: Altura | U1: Imagens adicionais
A2: 9 | B2: 69 | C2: 7894443800029 | D2: COR | E2: Preto | F2: Tamanho | G2: 28 | H2: 500 | I2: 50 | J2: 0 | K2: 4 | L2: 35 | O2: 0 | P2: § | Q2: https://images.tcdn.com.br/img/img_prod/995386/melissa_mel_flox_69_variacao_9_2_d672c57421724e7aa4a142a0bc03133a.jpeg | U2: https://images.tcdn.com.br/img/img_prod/995386/melissa_mel_flox_69_variacao_9_2_d672c57421724e7aa4a142a0bc03133a.jpeg, https://images.tcdn.com.br/img/img_prod/995386/melissa_mel_flox_69_variacao_9_3_a51455984a0c38fca57fc915b246f156.jpeg, https://images.tcdn.com.br/img/img_prod/995386/melissa_mel_flox_69_variacao_9_4_952058f6bf4468804982d67b2ee98313.jpeg, https://images.tcdn.com.br/img/img_prod/995386/melissa_mel_flox_69_variacao_9_5_e24d430bf7b36da07458d2742b8485a5.jpeg, https://images.tcdn.com.br/img/img_prod/995386/melissa_mel_flox_69_variacao_9_6_040594a10798bdcf5b792526bdd8a677.jpeg
A3: 25 | B3: 125 | C3: 7894443800036 | D3: COR | E3: Preto | F3: Tamanho | G3: 19 | H3: 100 | I3: 70 | J3: 0 | K3: 1 | L3: 33.34 | O3: 0 | P3: § | Q3: https://images.tcdn.com.br/img/img_prod/995386/mini_melissa_papete_rider_125_variacao_25_3_40df20e587a9f77cb3ea0a7bfb0ee0b1.jpeg | R3: 25 | S3: 15 | T3: 10 | U3: https://images.tcdn.com.br/img/img_prod/995386/mini_melissa_papete_rider_125_variacao_25_3_40df20e587a9f77cb3ea0a7bfb0ee0b1.jpeg, https://images.tcdn.com.br/img/img_prod/995386/mini_melissa_papete_rider_125_variacao_25_4_e754b9fb81c3ca7399f5f58a1572f7f4.jpeg, https://images.tcdn.com.br/img/img_prod/995386/mini_melissa_papete_rider_125_variacao_25_5_51800343d5e3645a64b9ec0c6cb078c6.jpeg
A4: 43 | B4: 37 | C4: 7894443800043 | D4: COR | E4: Amarelo | H4: 500 | I4: 65 | J4: 0 | K4: 3 | L4: 45 | O4: 0 | P4: § | Q4: https://images.tcdn.com.br/img/img_prod/995386/my_first_mini_melissa_tricot_37_variacao_43_2_cbe154edf208981e12f8f0fb550fffce.jpeg | R4: 20 | S4: 12 | T4: 10 | U4: https://images.tcdn.com.br/img/img_prod/995386/my_first_mini_melissa_tricot_37_variacao_43_2_cbe154edf208981e12f8f0fb550fffce.jpeg, https://images.tcdn.com.br/img/img_prod/995386/my_first_mini_melissa_tricot_37_variacao_43_3_0e574f337355636a1f474f5752e9e64d.jpeg, https://images.tcdn.com.br/img/img_prod/995386/my_first_mini_melissa_tricot_37_variacao_43_4_64685628f9a28222e9ecaae6ba2d2705.jpeg, https://images.tcdn.com.br/img/img_prod/995386/my_first_mini_melissa_tricot_37_variacao_43_5_d539577edbd694096925efd565d11b29.jpeg
A5: 45 | B5: 37 | C5: 7894443800050 | D5: COR | E5: Vermelho | H5: 300 | I5: 65 | J5: 0 | K5: 4 | L5: 45 | O5: 0 | P5: § | Q5: https://images.tcdn.com.br/img/img_prod/995386/my_first_mini_melissa_tricot_37_variacao_45_2_680e063cfb915f645c15dd789cf88d8e.jpeg | R5: 25 | S5: 15 | T5: 10 | U5: https://images.tcdn.com.br/img/img_prod/995386/my_first_mini_melissa_tricot_37_variacao_45_2_680e063cfb915f645c15dd789cf88d8e.jpeg, https://images.tcdn.com.br/img/img_prod/995386/my_first_mini_melissa_tricot_37_variacao_45_3_224bb99bfd4a482cd44f168f5a230fbb.jpeg, https://images.tcdn.com.br/img/img_prod/995386/my_first_mini_melissa_tricot_37_variacao_45_4_64777c8aee15258778f83d312762434f.jpeg, https://images.tcdn.com.br/img/img_prod/995386/my_first_mini_melissa_tricot_37_variacao_45_5_341f2469cb2e710af8d10591dbd24ab1.jpeg
A6: 55 | B6: 139 | C6: 7894443800067 | D6: COR | E6: Rosa | F6: Tamanho | G6: 26/27 | H6: 100 | I6: 65 | J6: 0 | K6: 2 | L6: 40 | O6: 0 | P6: § | Q6: https://images.tcdn.com.br/img/img_prod/995386/mini_melissa_maggie_bear_139_variacao_55_2_765ad78f34c8a9fac3a09e7c9ea036bd.jpeg | R6: 25 | S6: 15 | T6: 10 | U6: https://images.tcdn.com.br/img/img_prod/995386/mini_melissa_maggie_bear_139_variacao_55_2_765ad78f34c8a9fac3a09e7c9ea036bd.jpeg, https://images.tcdn.com.br/img/img_prod/995386/mini_melissa_maggie_bear_139_variacao_55_3_946be4b1137d4accfbaccc6235172a12.jpeg, https://images.tcdn.com.br/img/img_prod/995386/mini_melissa_maggie_bear_139_variacao_55_4_e5f5580575dd2e37ce3749a2591af7f4.jpeg, https://images.tcdn.com.br/img/img_prod/995386/mini_melissa_maggie_bear_139_variacao_55_5_2bd3503a2fed9e00fb829462c85d0c5c.jpeg
A7: 73 | B7: 121 | C7: 7894443800074 | D7: COR | E7: Rosa Choque | F7: Tamanho | G7: 20/21 | I7: 60 | J7: 0 | K7: 4 | L7: 0 | O7: 0 | P7: § | Q7: https://images.tcdn.com.br/img/img_prod/995386/mini_melissa_sneaker_love_system_121_variacao_73_2_226c85d7ce35081e9dbc54ca41e000b3.jpeg | U7: https://images.tcdn.com.br/img/img_prod/995386/mini_melissa_sneaker_love_system_121_variacao_73_2_226c85d7ce35081e9dbc54ca41e000b3.jpeg, https://images.tcdn.com.br/img/img_prod/995386/mini_melissa_sneaker_love_system_121_variacao_73_3_efcd0f0f58dfd81b5f7e03f0e969c31c.jpeg, https://images.tcdn.com.br/img/img_prod/995386/mini_melissa_sneaker_love_system_121_variacao_73_4_eeb8f6669286502adf267fcccfb04154.jpeg, https://images.tcdn.com.br/img/img_prod/995386/mini_melissa_sneaker_love_system_121_variacao_73_5_fa28ac0672914a0e6d6c542f0eca580e.jpeg
A8: 79 | B8: 87 | C8: 7894443800081 | D8: COR | E8: Rosa Glitter | F8: Tamanho | G8: 20/21 | H8: 500 | I8: 85 | J8: 0 | K8: 3 | L8: 42.58 | M8: 44489 | N8: 44500 | O8: 60 | P8: § | Q8: https://images.tcdn.com.br/img/img_prod/995386/mini_melissa_possession_87_variacao_79_3_586ce9c9c3abcc517e70169393f47057.jpeg | R8: 25 | S8: 15 | T8: 10 | U8: https://images.tcdn.com.br/img/img_prod/995386/mini_melissa_possession_87_variacao_79_3_586ce9c9c3abcc517e70169393f47057.jpeg, https://images.tcdn.com.br/img/img_prod/995386/mini_melissa_possession_87_variacao_79_4_d32725398b013caab5a5efbd495c7b9a.jpeg, https://images.tcdn.com.br/img/img_prod/995386/mini_melissa_possession_87_variacao_79_5_e37704c83eeacea6be6d6061495663a1.jpeg
A9: 87 | B9: 159 | C9: 7894443800098 | D9: COR | E9: Preto | F9: Tamanho | G9: 17/18 | H9: 500 | I9: 50 | J9: 0 | K9: 1 | L9: 22.98 | O9: 0 | P9: 5 seminova | Q9: https://images.tcdn.com.br/img/img_prod/995386/mini_melissa_ultragirl_a_bela_e_a_fera_159_variacao_87_2_dcae212f43e2df1293844b720c2391d4.jpg | R9: 25 | S9: 15 | T9: 10 | U9: https://images.tcdn.com.br/img/img_prod/995386/mini_melissa_ultragirl_a_bela_e_a_fera_159_variacao_87_2_dcae212f43e2df1293844b720c2391d4.jpg, https://images.tcdn.com.br/img/img_prod/995386/mini_melissa_ultragirl_a_bela_e_a_fera_159_variacao_87_3_12a04e1c663c330aa2a6602a272b2282.jpg, https://images.tcdn.com.br/img/img_prod/995386/mini_melissa_ultragirl_a_bela_e_a_fera_159_variacao_87_4_a9132fc73b908172af2419faa611f325.jpg, https://images.tcdn.com.br/img/img_prod/995386/mini_melissa_ultragirl_a_bela_e_a_fera_159_variacao_87_5_09aafaf03e05c7428bd8bfd3d518e3eb.jpg, https://images.tcdn.com.br/img/img_prod/995386/mini_melissa_ultragirl_a_bela_e_a_fera_159_variacao_87_6_1f69b723a79c4711ceb6d7da40edc980.jpg
A10: 93 | B10: 121 | C10: 7894443800104 | D10: COR | E10: Azul escuro | F10: Tamanho | G10: 17/18 | H10: 500 | I10: 50 | J10: 0 | K10: 1 | L10: 22.98 | O10: 0 | P10: § | Q10: https://images.tcdn.com.br/img/img_prod/995386/mini_melissa_sneaker_love_system_121_variacao_93_2_12cc4e7df6f5f92fad327694340f5114.jpeg | R10: 25 | S10: 15 | T10: 10 | U10: https://images.tcdn.com.br/img/img_prod/995386/mini_melissa_sneaker_love_system_121_variacao_93_2_12cc4e7df6f5f92fad327694340f5114.jpeg, https://images.tcdn.com.br/img/img_prod/995386/mini_melissa_sneaker_love_system_121_variacao_93_3_95f94cbd1d724fe453571618f57011a9.jpeg, https://images.tcdn.com.br/img/img_prod/995386/mini_melissa_sneaker_love_system_121_variacao_93_4_93bcffdb9c0e99b38432a01bf85a78c2.jpeg, https://images.tcdn.com.br/img/img_prod/995386/mini_melissa_sneaker_love_system_121_variacao_93_5_0af925c3a68dff4c9e4e78694d1c100b.jpeg
A11: 95 | B11: 163 | C11: 7894443800111 | D11: COR | E11: Rosa | F11: Tamanho | G11: 23/24 | H11: 500 | I11: 55 | J11: 0 | K11: 4 | L11: 40.34 | O11: 0 | P11: § | Q11: https://images.tcdn.com.br/img/img_prod/995386/mini_melissa_mar_sandal_swett_dreams_163_variacao_95_2_7cec0f6a93b10c1d6f3fb0e577e84a74.jpeg | R11: 20 | S11: 15 | T11: 10 | U11: https://images.tcdn.com.br/img/img_prod/995386/mini_melissa_mar_sandal_swett_dreams_163_variacao_95_2_7cec0f6a93b10c1d6f3fb0e577e84a74.jpeg, https://images.tcdn.com.br/img/img_prod/995386/mini_melissa_mar_sandal_swett_dreams_163_variacao_95_3_a88942bd0602ff893417d01b2feeaa67.jpeg, https://images.tcdn.com.br/img/img_prod/995386/mini_melissa_mar_sandal_swett_dreams_163_variacao_95_4_128d5816ae2873547ca8428f5c6bcb4d.jpeg, https://images.tcdn.com.br/img/img_prod/995386/mini_melissa_mar_sandal_swett_dreams_163_variacao_95_5_53e8d938f79dead48859dc0a413d3a46.jpeg
A12: 101 | B12: 83 | C12: 7894443800128 | D12: COR | E12: Rosa Glitter | F12: Tamanho | G12: 22 | H12: 500 | I12: 55 | J12: 0 | K12: 2 | L12: 40.54 | O12: 0 | P12: § | Q12: https://images.tcdn.com.br/img/img_prod/995386/mini_melissa_ultragirl_pequena_sereia_83_variacao_101_2_554319e2700d4b5e16793d85df44e3b7.jpeg | R12: 25 | S12: 15 | T12: 10 | U12: https://images.tcdn.com.br/img/img_prod/995386/mini_melissa_ultragirl_pequena_sereia_83_variacao_101_2_554319e2700d4b5e16793d85df44e3b7.jpeg, https://images.tcdn.com.br/img/img_prod/995386/mini_melissa_ultragirl_pequena_sereia_83_variacao_101_3_aa37a0e2f05fa9e86234d50af17efe16.jpeg, https://images.tcdn.com.br/img/img_prod/995386/mini_melissa_ultragirl_pequena_sereia_83_variacao_101_4_aa37a0e2f05fa9e86234d50af17efe16.jpeg, https://images.tcdn.com.br/img/img_prod/995386/mini_melissa_ultragirl_pequena_sereia_83_variacao_101_5_64487e7bb05e57d1ada24cf24d474912.jpeg, https://images.tcdn.com.br/img/img_prod/995386/mini_melissa_ultragirl_pequena_sereia_83_variacao_101_6_d47e0963675769f75e198f7da15efe57.jpeg
A13: 105 | B13: 55 | C13: 7894443800135 | D13: COR | E13: Preto | F13: Tamanho | G13: 28 | H13: 100 | I13: 58 | J13: 0 | K13: 1 | L13: 30.23 | O13: 0 | P13: § | Q13: https://images.tcdn.com.br/img/img_prod/995386/mini_melissa_ultragirl_swett_iii_55_variacao_105_2_ab1271c7de339b77847f66edac8f60ac.jpeg | R13: 25 | S13: 15 | T13: 10 | U13: https://images.tcdn.com.br/img/img_prod/995386/mini_melissa_ultragirl_swett_iii_55_variacao_105_2_ab1271c7de339b77847f66edac8f60ac.jpeg, https://images.tcdn.com.br/img/img_prod/995386/mini_melissa_ultragirl_swett_iii_55_variacao_105_3_c93367d7994cd9888cb1c5deabbeaa8d.jpeg, https://images.tcdn.com.br/img/img_prod/995386/mini_melissa_ultragirl_swett_iii_55_variacao_105_4_9ad5c690189eaf4b28769ee212da8644.jpeg, https://images.tcdn.com.br/img/img_prod/995386/mini_melissa_ultragirl_swett_iii_55_variacao_105_5_8a0ce303b026d9ffe2fda4ecf8ea830b.jpeg, https://images.tcdn.com.br/img/img_prod/995386/mini_melissa_ultragirl_swett_iii_55_variacao_105_6_cf35ce7eb81866b00f14aa66a2486d1c.jpeg
A14: 107 | B14: 55 | C14: 7894443800142 | D14: COR | E14: Colorido Glitter | F14: Tamanho | G14: 19 | H14: 500 | I14: 55 | J14: 0 | K14: 1 | L14: 30.23 | O14: 0 | P14: § | Q14: https://images.tcdn.com.br/img/img_prod/995386/mini_melissa_ultragirl_swett_iii_55_variacao_107_2_6c77a42f29a84232f2a5f3ef17c27fcf.jpeg | R14: 25 | S14: 15 | T14: 10 | U14: https://images.tcdn.com.br/img/img_prod/995386/mini_melissa_ultragirl_swett_iii_55_variacao_107_2_6c77a42f29a84232f2a5f3ef17c27fcf.jpeg, https://images.tcdn.com.br/img/img_prod/995386/mini_melissa_ultragirl_swett_iii_55_variacao_107_3_4cf289f8855a42ee72fc76f7e0113651.jpeg, https://images.tcdn.com.br/img/img_prod/995386/mini_melissa_ultragirl_swett_iii_55_variacao_107_4_65e984e5eafb52fc5922d1ac51b53c1c.jpeg, https://images.tcdn.com.br/img/img_prod/995386/mini_melissa_ultragirl_swett_iii_55_variacao_107_5_9774e56e3fb4585a24f1e0a7f2e10d4a.jpeg, https://images.tcdn.com.br/img/img_prod/995386/mini_melissa_ultragirl_swett_iii_55_variacao_107_6_65e984e5eafb52fc5922d1ac51b53c1c.jpeg
A15: 119 | B15: 53 | C15: 7894443800159 | D15: COR | E15: Preto | F15: Tamanho | G15: 20/21 | H15: 300 | I15: 40 | J15: 0 | K15: 3 | L15: 38.53 | O15: 0 | P15: § | Q15: https://images.tcdn.com.br/img/img_prod/995386/mini_melissa_campana_zig_zag_53_variacao_119_2_b68e4acfe05c9b5cb195805b3c47ca7d.jpeg | R15: 25 | S15: 15 | T15: 10 | U15: https://images.tcdn.com.br/img/img_prod/995386/mini_melissa_campana_zig_zag_53_variacao_119_2_b68e4acfe05c9b5cb195805b3c47ca7d.jpeg, https://images.tcdn.com.br/img/img_prod/995386/mini_melissa_campana_zig_zag_53_variacao_119_3_5fe10dd790e004e6db299f273896c8ee.jpeg, https://images.tcdn.com.br/img/img_prod/995386/mini_melissa_campana_zig_zag_53_variacao_119_4_68cab83609eada1ee918b0fef591e806.jpeg, https://images.tcdn.com.br/img/img_prod/995386/mini_melissa_campana_zig_zag_53_variacao_119_5_4762e7a3f884e263d15b1e26ddce7c46.jpeg
A16: 125 | B16: 171 | C16: 7894443800166 | D16: COR | E16: Colorido Glitter | F16: Tamanho | G16: 28 | H16: 500 | I16: 80 | J16: 0 | K16: 2 | L16: 31.3 | O16: 0 | P16: § | Q16: https://images.tcdn.com.br/img/img_prod/995386/mini_melissa_street_sneaker_171_variacao_125_2_1049a1a4d1a45e92a12cd770e82ce767.jpeg | R16: 25 | S16: 15 | T16: 10 | U16: https://images.tcdn.com.br/img/img_prod/995386/mini_melissa_street_sneaker_171_variacao_125_2_1049a1a4d1a45e92a12cd770e82ce767.jpeg, https://images.tcdn.com.br/img/img_prod/995386/mini_melissa_street_sneaker_171_variacao_125_3_73bf74f56d793772c7d1238f0281afe9.jpeg, https://images.tcdn.com.br/img/img_prod/995386/mini_melissa_street_sneaker_171_variacao_125_4_5ba7628ae610e301c060298a49255997.jpeg
A17: 129 | B17: 113 | C17: 7894443800173 | D17: COR | E17: Vidro Azul | F17: Tamanho | G17: 23/24 | H17: 500 | I17: 55 | J17: 0 | K17: 1 | L17: 24.27 | O17: 0 | P17: § | Q17: https://images.tcdn.com.br/img/img_prod/995386/mini_melissa_possession_unicornio_113_variacao_129_2_90c73ebc3e25ee04a18394519beac97e.jpeg | R17: 25 | S17: 15 | T17: 10 | U17: https://images.tcdn.com.br/img/img_prod/995386/mini_melissa_possession_unicornio_113_variacao_129_2_90c73ebc3e25ee04a18394519beac97e.jpeg, https://images.tcdn.com.br/img/img_prod/995386/mini_melissa_possession_unicornio_113_variacao_129_3_f43195ecff8404dc39863c84641642c6.jpeg
A18: 139 | B18: 65 | C18: 7894443800180 | D18: COR | E18: Rosa | F18: Tamanho | G18: 28 | H18: 500 | I18: 80 | J18: 0 | K18: 2 | L18: 134 | O18: 0 | P18: § | Q18: https://images.tcdn.com.br/img/img_prod/995386/mini_melissa_street_mickey_and_friends_65_variacao_139_2_c351d7399374d45b7d00113cd4131731.jpeg | R18: 25 | S18: 15 | T18: 10 | U18: https://images.tcdn.com.br/img/img_prod/995386/mini_melissa_street_mickey_and_friends_65_variacao_139_2_c351d7399374d45b7d00113cd4131731.jpeg, https://images.tcdn.com.br/img/img_prod/995386/mini_melissa_street_mickey_and_friends_65_variacao_139_3_ec6cb2ba891c4b0843fcfcabc94be601.jpeg, https://images.tcdn.com.br/img/img_prod/995386/mini_melissa_street_mickey_and_friends_65_variacao_139_4_23095fccf603266fb629cc37061a4338.jpeg, https://images.tcdn.com.br/img/img_prod/995386/mini_melissa_street_mickey_and_friends_65_variacao_139_5_e732814a80cf82a0e992c8f2f652fca6.jpeg
A19: 147 | B19: 65 | C19: 7894443800197 | D19: COR | E19: Branco | F19: Tamanho | G19: 26/27 | H19: 500 | I19: 80 | J19: 0 | K19: 2 | L19: 134 | O19: 0 | P19: § | Q19: https://images.tcdn.com.br/img/img_prod/995386/mini_melissa_street_mickey_and_friends_65_variacao_147_2_a703e6bd62237ac874dea96c580b0b10.jpeg | R19: 25 | S19: 15 | T19: 10 | U19: https://images.tcdn.com.br/img/img_prod/995386/mini_melissa_street_mickey_and_friends_65_variacao_147_2_a703e6bd62237ac874dea96c580b0b10.jpeg, https://images.tcdn.com.br/img/img_prod/995386/mini_melissa_street_mickey_and_friends_65_variacao_147_3_4e866f06f4e4bc4cb154753d3325f840.jpeg, https://images.tcdn.com.br/img/img_prod/995386/mini_melissa_street_mickey_and_friends_65_variacao_147_4_313a04e1d203cb9e73ebc42892ec0d01.jpeg, https://images.tcdn.com.br/img/img_prod/995386/mini_melissa_street_mickey_and_friends_65_variacao_147_5_b110645ebcdf1649c0f66cda3270f772.jpeg
A20: 149 | B20: 173 | C20: 7894443800203 | D20: COR | E20: Azul escuro | F20: Tamanho | G20: 17/18 | H20: 500 | I20: 55 | J20: 0 | K20: 1 | L20: 32.49 | O20: 0 | P20: § | Q20: https://images.tcdn.com.br/img/img_prod/995386/mini_melissa_ultragirl_swett_dreams_173_variacao_149_2_c4af13482e780d2e1333dfbd13517468.jpeg | R20: 25 | S20: 15 | T20: 10 | U20: https://images.tcdn.com.br/img/img_prod/995386/mini_melissa_ultragirl_swett_dreams_173_variacao_149_2_c4af13482e780d2e1333dfbd13517468.jpeg, https://images.tcdn.com.br/img/img_prod/995386/mini_melissa_ultragirl_swett_dreams_173_variacao_149_3_6c16ae1dbe1697d8c1e5805bcffaa694.jpeg, https://images.tcdn.com.br/img/img_prod/995386/mini_melissa_ultragirl_swett_dreams_173_variacao_149_4_786051f481d076df80aff9906db85d6f.jpeg, https://images.tcdn.com.br/img/img_prod/995386/mini_melissa_ultragirl_swett_dreams_173_variacao_149_5_59c93d81a8212aaf7c3ad7adfd6d28f4.jpeg, https://images.tcdn.com.br/img/img_prod/995386/mini_melissa_ultragirl_swett_dreams_173_variacao_149_6_db3d734e9e753631dc59cc68ae066f48.jpeg
A21: 165 | B21: 183 | C21: 7894443800227 | D21: COR | E21: Azul | F21: Tamanho | G21: 26/27 | I21: 50 | J21: -1 | K21: 3 | L21: 25 | O21: 0 | P21: § | Q21: https://images.tcdn.com.br/img/img_prod/995386/mini_melissa_aranha_vivienne_westwood_183_variacao_165_2_efb883915eb0278877d3eb220a514e98.jpeg | U21: https://images.tcdn.com.br/img/img_prod/995386/mini_melissa_aranha_vivienne_westwood_183_variacao_165_2_efb883915eb0278877d3eb220a514e98.jpeg, https://images.tcdn.com.br/img/img_prod/995386/mini_melissa_aranha_vivienne_westwood_183_variacao_165_3_4bc2c977e75a1bcff4e1f20030ac83e7.jpeg, https://images.tcdn.com.br/img/img_prod/995386/mini_melissa_aranha_vivienne_westwood_183_variacao_165_4_785ee7b78a54089bc49ba7427bff188d.jpeg, https://images.tcdn.com.br/img/img_prod/995386/mini_melissa_aranha_vivienne_westwood_183_variacao_165_5_a0af77d3b9d016fca69ba45011c42f04.jpeg, https://images.tcdn.com.br/img/img_prod/995386/mini_melissa_aranha_vivienne_westwood_183_variacao_165_6_3f05f767294b3deef5e1818fcc024eba.jpeg
A22: 169 | B22: 185 | C22: 7894443800234 | D22: COR | E22: Preto | F22: Tamanho | G22: 33/34 | H22: 200 | I22: 50 | J22: 0 | K22: 1 | L22: 25 | O22: 0 | P22: § | Q22: https://images.tcdn.com.br/img/img_prod/995386/melissa_color_pop_malevola_185_variacao_169_2_70b0ef3483e383620088f9e7ffc71223.jpeg | R22: 25 | S22: 15 | T22: 10 | U22: https://images.tcdn.com.br/img/img_prod/995386/melissa_color_pop_malevola_185_variacao_169_2_70b0ef3483e383620088f9e7ffc71223.jpeg, https://images.tcdn.com.br/img/img_prod/995386/melissa_color_pop_malevola_185_variacao_169_3_fbc013e20aca5b1c608910d9e0a40def.jpeg, https://images.tcdn.com.br/img/img_prod/995386/melissa_color_pop_malevola_185_variacao_169_4_655f1e065a9f5c26e05d9f1fd8c08c98.jpeg, https://images.tcdn.com.br/img/img_prod/995386/melissa_color_pop_malevola_185_variacao_169_5_d640d745040ae9e2623d1f844630f3a3.jpeg
A23: 171 | B23: 69 | C23: 7894443800241 | D23: COR | E23: Preto | F23: Tamanho | G23: 29 | H23: 300 | I23: 75 | J23: 0 | K23: 4 | L23: 30.5 | O23: 0 | P23: § | Q23: https://images.tcdn.com.br/img/img_prod/995386/melissa_mel_flox_69_variacao_171_2_a24832e9de741b7d1424d66140eafd74.jpg | R23: 25 | S23: 15 | T23: 10 | U23: https://images.tcdn.com.br/img/img_prod/995386/melissa_mel_flox_69_variacao_171_2_a24832e9de741b7d1424d66140eafd74.jpg, https://images.tcdn.com.br/img/img_prod/995386/melissa_mel_flox_69_variacao_171_3_8526257a5f3117af9c1b67b3f21e27ca.jpg, https://images.tcdn.com.br/img/img_prod/995386/melissa_mel_flox_69_variacao_171_4_4646551be1bf893fb49ab1dcebc7303c.jpg, https://images.tcdn.com.br/img/img_prod/995386/melissa_mel_flox_69_variacao_171_5_2b86065e4cb8d2dbbac214c0597bd40a.jpg, https://images.tcdn.com.br/img/img_prod/995386/melissa_mel_flox_69_variacao_171_6_b25c1348360929c425822018ec30a5bb.jpg
A24: 175 | B24: 187 | C24: 7894443800258 | D24: COR | E24: Rosa Choque | F24: Tamanho | G24: 17/18 | I24: 60 | J24: 0 | K24: 2 | L24: 40 | O24: 0 | P24: § | Q24: https://images.tcdn.com.br/img/img_prod/995386/mini_melissa_sneaker_be_187_variacao_175_2_a7e9c2b7e7e7653a39d9c2ec476a7431.jpeg | U24: https://images.tcdn.com.br/img/img_prod/995386/mini_melissa_sneaker_be_187_variacao_175_2_a7e9c2b7e7e7653a39d9c2ec476a7431.jpeg, https://images.tcdn.com.br/img/img_prod/995386/mini_melissa_sneaker_be_187_variacao_175_3_b507ae6f4708aa2f54a1d257fbd9c717.jpeg, https://images.tcdn.com.br/img/img_prod/995386/mini_melissa_sneaker_be_187_variacao_175_4_bd68beeaec7a92314541a2dff2785f49.jpeg, https://images.tcdn.com.br/img/img_prod/995386/mini_melissa_sneaker_be_187_variacao_175_5_f4933c408161f4519c96e58bc167c0b5.jpeg, https://images.tcdn.com.br/img/img_prod/995386/mini_melissa_sneaker_be_187_variacao_175_6_408dda468aff008027d5c68c4ed1e4f6.jpeg
A25: 179 | B25: 189 | C25: 7894443800265 | D25: COR | E25: Perola | F25: Tamanho | G25: 22 | H25: 500 | I25: 55 | J25: 0 | K25: 1 | L25: 31.71 | O25: 0 | P25: § | Q25: https://images.tcdn.com.br/img/img_prod/995386/mini_melissa_mar_sandal_189_variacao_179_2_a201e556bc1f10be314e4ef4c528856a.jpeg | R25: 25 | S25: 15 | T25: 10 | U25: https://images.tcdn.com.br/img/img_prod/995386/mini_melissa_mar_sandal_189_variacao_179_2_a201e556bc1f10be314e4ef4c528856a.jpeg, https://images.tcdn.com.br/img/img_prod/995386/mini_melissa_mar_sandal_189_variacao_179_3_55b156bcb265220ff709467845d3da91.jpeg, https://images.tcdn.com.br/img/img_prod/995386/mini_melissa_mar_sandal_189_variacao_179_4_55b156bcb265220ff709467845d3da91.jpeg, https://images.tcdn.com.br/img/img_prod/995386/mini_melissa_mar_sandal_189_variacao_179_5_658af3a88d48dc213ab546803bf894c7.jpeg, https://images.tcdn.com.br/img/img_prod/995386/mini_melissa_mar_sandal_189_variacao_179_6_49ea6faa4468fbac4fb9a7d543f3600b.jpeg
A26: 205 | B26: 125 | C26: 7894443800272 | D26: COR | E26: Rosa Glitter | F26: Tamanho | G26: 17/18 | H26: 500 | I26: 60 | J26: 0 | K26: 3 | L26: 70 | O26: 0 | P26: usada | Q26: https://images.tcdn.com.br/img/img_prod/995386/mini_melissa_papete_rider_125_variacao_205_3_7d8cf5f5b956c5c9d7b36396b1b0aad8.jpg | R26: 25 | S26: 15 | T26: 10 | U26: https://images.tcdn.com.br/img/img_prod/995386/mini_melissa_papete_rider_125_variacao_205_3_7d8cf5f5b956c5c9d7b36396b1b0aad8.jpg, https://images.tcdn.com.br/img/img_prod/995386/mini_melissa_papete_rider_125_variacao_205_4_271237aac9484b0cbe6d4b73f5ff6c19.jpg
A27: 207 | B27: 193 | C27: 7894443800289 | D27: COR | E27: Rosa Glitter | F27: Tamanho | G27: 19 | H27: 500 | I27: 55 | J27: 0 | K27: 2 | L27: 70 | O27: 0 | P27: § | Q27: https://images.tcdn.com.br/img/img_prod/995386/mini_melissa_wide_sandal_193_variacao_207_2_4a1322d697a4dfe7524bb91a626c616e.jpeg | R27: 25 | S27: 15 | T27: 10 | U27: https://images.tcdn.com.br/img/img_prod/995386/mini_melissa_wide_sandal_193_variacao_207_2_4a1322d697a4dfe7524bb91a626c616e.jpeg, https://images.tcdn.com.br/img/img_prod/995386/mini_melissa_wide_sandal_193_variacao_207_3_35c0937911f7634ce351e7f64dfd7c81.jpeg, https://images.tcdn.com.br/img/img_prod/995386/mini_melissa_wide_sandal_193_variacao_207_4_1204e09e4b5f2c128f2361b77605bfbf.jpeg, https://images.tcdn.com.br/img/img_prod/995386/mini_melissa_wide_sandal_193_variacao_207_5_50afbc3933234dd081b1fb107a11ea74.jpeg
A28: 209 | B28: 171 | C28: 7894443800296 | D28: COR | E28: Rosa Glitter | F28: Tamanho | G28: 20/21 | H28: 500 | I28: 70 | J28: 0 | K28: 1 | L28: 45 | O28: 0 | P28: § | Q28: https://images.tcdn.com.br/img/img_prod/995386/mini_melissa_street_sneaker_171_variacao_209_2_6cddadefdba8b63b573d4575f1eaa8e3.jpeg | R28: 25 | S28: 15 | T28: 10 | U28: https://images.tcdn.com.br/img/img_prod/995386/mini_melissa_street_sneaker_171_variacao_209_2_6cddadefdba8b63b573d4575f1eaa8e3.jpeg, https://images.tcdn.com.br/img/img_prod/995386/mini_melissa_street_sneaker_171_variacao_209_3_08e1bcd2a133a962196462823e908ad7.jpeg
A29: 225 | B29: 118 | C29: 7894443800302 | D29: COR | E29: Preto | F29: Tamanho | G29: 22 | H29: 500 | I29: 50 | J29: 0 | K29: 1 | L29: 34 | O29: 0 | P29: § | Q29: https://images.tcdn.com.br/img/img_prod/995386/mini_melissa_ultragirl_bamby_118_variacao_225_2_8643077d7874dec5f839f9e68edd2e50.jpeg | R29: 25 | S29: 15 | T29: 10 | U29: https://images.tcdn.com.br/img/img_prod/995386/mini_melissa_ultragirl_bamby_118_variacao_225_2_8643077d7874dec5f839f9e68edd2e50.jpeg, https://images.tcdn.com.br/img/img_prod/995386/mini_melissa_ultragirl_bamby_118_variacao_225_3_97e6e5dda2284e0cc70938afa8d74393.jpeg, https://images.tcdn.com.br/img/img_prod/995386/mini_melissa_ultragirl_bamby_118_variacao_225_4_fac28105f9bdb117f635fca407b9d77e.jpeg, https://images.tcdn.com.br/img/img_prod/995386/mini_melissa_ultragirl_bamby_118_variacao_225_5_c2ca91c47a5d1cad5c34d17fca10f692.jpeg, https://images.tcdn.com.br/img/img_prod/995386/mini_melissa_ultragirl_bamby_118_variacao_225_6_aa1dde6aceb8ef5b61fc6876306e7e94.jpeg
A30: 233 | B30: 53 | C30: 7894443800319 | D30: COR | E30: Prata | F30: Tamanho | G30: 25 | I30: 50 | J30: 0 | K30: 2 | L30: 30 | O30: 0 | P30: 54 usada | Q30: https://images.tcdn.com.br/img/img_prod/995386/mini_melissa_campana_zig_zag_53_variacao_233_2_26db1f9188a74b6e5ebe1e37bd697be5.jpg | U30: https://images.tcdn.com.br/img/img_prod/995386/mini_melissa_campana_zig_zag_53_variacao_233_2_26db1f9188a74b6e5ebe1e37bd697be5.jpg, https://images.tcdn.com.br/img/img_prod/995386/mini_melissa_campana_zig_zag_53_variacao_233_3_ab50d2bac446fb028d5d208715a4cbb9.jpg, https://images.tcdn.com.br/img/img_prod/995386/mini_melissa_campana_zig_zag_53_variacao_233_4_5c995583d697e3725a3ca5e4c4c42561.jpg, https://images.tcdn.com.br/img/img_prod/995386/mini_melissa_campana_zig_zag_53_variacao_233_5_5614a89124f5f4e47846add10cded541.jpg, https://images.tcdn.com.br/img/img_prod/995386/mini_melissa_campana_zig_zag_53_variacao_233_6_add23ed693585043652da7af67abf806.jpg
A31: 237 | B31: 103 | C31: 7894443800326 | D31: COR | E31: Amarelo | F31: Tamanho | G31: 22 | I31: 65 | J31: 0 | K31: 6 | L31: 29.9 | O31: 0 | P31: § | Q31: https://images.tcdn.com.br/img/img_prod/995386/mini_melissa_jump_frutland_abacaxi_morango_melancia_abacate_103_variacao_237_2_3453d47d431eb92dd83380b732df1b80.jpeg | U31: https://images.tcdn.com.br/img/img_prod/995386/mini_melissa_jump_frutland_abacaxi_morango_melancia_abacate_103_variacao_237_2_3453d47d431eb92dd83380b732df1b80.jpeg, https://images.tcdn.com.br/img/img_prod/995386/mini_melissa_jump_frutland_abacaxi_morango_melancia_abacate_103_variacao_237_3_5be27f555817f45f6d22d048668839c7.jpeg, https://images.tcdn.com.br/img/img_prod/995386/mini_melissa_jump_frutland_abacaxi_morango_melancia_abacate_103_variacao_237_4_a7bebf3b160c9e8d42d2cb86625d574c.jpeg, https://images.tcdn.com.br/img/img_prod/995386/mini_melissa_jump_frutland_abacaxi_morango_melancia_abacate_103_variacao_237_5_b8263fed31f254c149c46e45139b3c53.jpeg, https://images.tcdn.com.br/img/img_prod/995386/mini_melissa_jump_frutland_abacaxi_morango_melancia_abacate_103_variacao_237_6_30863841591c48515ab2121a615a8d23.jpeg
A32: 239 | B32: 189 | C32: 7894443800333 | D32: COR | E32: Dourado Glitter | F32: Tamanho | G32: 17/18 | I32: 55 | J32: 0 | K32: 5 | L32: 30 | O32: 0 | P32: nova | Q32: https://images.tcdn.com.br/img/img_prod/995386/mini_melissa_mar_sandal_189_variacao_239_2_5427b36d70ed527e298065c978d46b49.jpeg | U32: https://images.tcdn.com.br/img/img_prod/995386/mini_melissa_mar_sandal_189_variacao_239_2_5427b36d70ed527e298065c978d46b49.jpeg, https://images.tcdn.com.br/img/img_prod/995386/mini_melissa_mar_sandal_189_variacao_239_3_875e2c000d2273add3618e839ca4ae66.jpeg, https://images.tcdn.com.br/img/img_prod/995386/mini_melissa_mar_sandal_189_variacao_239_4_151ded783ea94d5ab25ae337e460d850.jpeg, https://images.tcdn.com.br/img/img_prod/995386/mini_melissa_mar_sandal_189_variacao_239_5_5e7d0b34bf9d2954acb6f66882d8f2f1.jpeg, https://images.tcdn.com.br/img/img_prod/995386/mini_melissa_mar_sandal_189_variacao_239_6_3fa9e4e395c71360d5e2ec0171caef3b.jpg
A33: 245 | B33: 72 | C33: 7894443800340 | D33: COR | E33: Preto | F33: Tamanho | G33: 17/18 | I33: 55 | J33: 0 | K33: 1 | L33: 25 | O33: 0 | P33: § | Q33: https://images.tcdn.com.br/img/img_prod/995386/mini_melissa_possession_turma_do_pudim_72_variacao_245_3_dcc0a58a4367c7a73c3ac13ac208241d.jpeg | U33: https://images.tcdn.com.br/img/img_prod/995386/mini_melissa_possession_turma_do_pudim_72_variacao_245_3_dcc0a58a4367c7a73c3ac13ac208241d.jpeg
A34: 255 | B34: 201 | C34: 7894443800357 | D34: COR | E34: Vermelho | F34: Tamanho | G34: 17/18 | H34: 300 | I34: 65 | J34: 0 | K34: 2 | L34: 40 | O34: 0 | P34: § | Q34: https://images.tcdn.com.br/img/img_prod/995386/mini_melissa_snacker_be_ad_hello_kitty_201_variacao_255_2_fe1186951c2bfa8d79d1d7c98023eb79.jpeg | R34: 25 | S34: 15 | T34: 10 | U34: https://images.tcdn.com.br/img/img_prod/995386/mini_melissa_snacker_be_ad_hello_kitty_201_variacao_255_2_fe1186951c2bfa8d79d1d7c98023eb79.jpeg, https://images.tcdn.com.br/img/img_prod/995386/mini_melissa_snacker_be_ad_hello_kitty_201_variacao_255_3_ad199165a50591f8ef0bd35e0b08877e.jpeg, https://images.tcdn.com.br/img/img_prod/995386/mini_melissa_snacker_be_ad_hello_kitty_201_variacao_255_4_59f4f3be726d989291cbae7c4c27db52.jpeg, https://images.tcdn.com.br/img/img_prod/995386/mini_melissa_snacker_be_ad_hello_kitty_201_variacao_255_5_23cc6419185071459bea4a7e910b4762.jpeg, https://images.tcdn.com.br/img/img_prod/995386/mini_melissa_snacker_be_ad_hello_kitty_201_variacao_255_6_63ca377c0eae09fc7289a8e97eded738.jpeg, https://images.tcdn.com.br/img/img_prod/995386/mini_melissa_snacker_be_ad_hello_kitty_201_variacao_255_7_efe14ce9a2b1b5f83b8bfe90f4ab0330.jpeg
A35: 267 | B35: 39 | C35: 7894443800364 | D35: COR | E35: Amarelo | F35: Tamanho | G35: 17/18 | H35: 100 | I35: 60 | J35: 0 | K35: 1 | L35: 50 | O35: 0 | P35: § | Q35: https://images.tcdn.com.br/img/img_prod/995386/galocha_mini_melissa_sugar_rain_fabula_39_variacao_267_2_63dfdb05a719ae22de0cb26488aaafd4.jpeg | R35: 25 | S35: 15 | T35: 10 | U35: https://images.tcdn.com.br/img/img_prod/995386/galocha_mini_melissa_sugar_rain_fabula_39_variacao_267_2_63dfdb05a719ae22de0cb26488aaafd4.jpeg, https://images.tcdn.com.br/img/img_prod/995386/galocha_mini_melissa_sugar_rain_fabula_39_variacao_267_3_c61bf270f966673d2481535d2ba40e65.jpeg, https://images.tcdn.com.br/img/img_prod/995386/galocha_mini_melissa_sugar_rain_fabula_39_variacao_267_4_01462d8b875dcef981ec42d40f7079fe.jpeg, https://images.tcdn.com.br/img/img_prod/995386/galocha_mini_melissa_sugar_rain_fabula_39_variacao_267_5_40122db97ee280b12dfd358375270aac.jpeg, https://images.tcdn.com.br/img/img_prod/995386/galocha_mini_melissa_sugar_rain_fabula_39_variacao_267_6_2698a9d13be63402f87061a3e832e3f2.jpeg
A36: 269 | B36: 58 | C36: 7894443800371 | D36: COR | E36: Caramelo | F36: Tamanho | G36: 17/18 | H36: 500 | I36: 80 | J36: 0 | K36: 1 | L36: 44.71 | O36: 0 | P36: § | Q36: https://images.tcdn.com.br/img/img_prod/995386/mini_melissa_sugar_boot_winter_58_variacao_269_2_e6c92ebd223a7c62bfe817c46da13914.jpeg | R36: 25 | S36: 15 | T36: 10 | U36: https://images.tcdn.com.br/img/img_prod/995386/mini_melissa_sugar_boot_winter_58_variacao_269_2_e6c92ebd223a7c62bfe817c46da13914.jpeg, https://images.tcdn.com.br/img/img_prod/995386/mini_melissa_sugar_boot_winter_58_variacao_269_3_6f833007a020a198509aeed554f55584.jpeg, https://images.tcdn.com.br/img/img_prod/995386/mini_melissa_sugar_boot_winter_58_variacao_269_4_e72fe7a11c2805ab3733ecfcfa385021.jpeg, https://images.tcdn.com.br/img/img_prod/995386/mini_melissa_sugar_boot_winter_58_variacao_269_5_0591d879013a77dfbcfc9000a488cf89.jpeg
A37: 271 | B37: 203 | C37: 7894443800388 | D37: COR | E37: Lilás | F37: Tamanho | G37: 20/21 | H37: 500 | I37: 60 | J37: 0 | K37: 3 | L37: 44.71 | O37: 0 | P37: § | Q37: https://images.tcdn.com.br/img/img_prod/995386/mini_melissa_sneaker_be_ad_raibow_203_variacao_271_2_b35b6a9f4a078f319c43bc18e256e33c.jpeg | R37: 25 | S37: 15 | T37: 10 | U37: https://images.tcdn.com.br/img/img_prod/995386/mini_melissa_sneaker_be_ad_raibow_203_variacao_271_2_b35b6a9f4a078f319c43bc18e256e33c.jpeg, https://images.tcdn.com.br/img/img_prod/995386/mini_melissa_sneaker_be_ad_raibow_203_variacao_271_3_a62d7c94b74b4d6d99aca025177c228e.jpeg, https://images.tcdn.com.br/img/img_prod/995386/mini_melissa_sneaker_be_ad_raibow_203_variacao_271_4_50151578646175a010c907bb40b4a371.jpeg, https://images.tcdn.com.br/img/img_prod/995386/mini_melissa_sneaker_be_ad_raibow_203_variacao_271_5_4f6d1cb34b89201aa13b6e11e5a2907c.jpeg
A38: 277 | B38: 205 | C38: 7894443800395 | D38: COR | E38: Cinza | F38: Tamanho | G38: 17/18 | H38: 500 | I38: 60 | J38: 0 | K38: 1 | L38: 0 | O38: 0 | P38: § | Q38: https://images.tcdn.com.br/img/img_prod/995386/mini_melissa_ultragirl_animal_lovers_gata_205_variacao_277_2_6c318377510309443ece3177711ae075.jpeg | R38: 25 | S38: 15 | T38: 10 | U38: https://images.tcdn.com.br/img/img_prod/995386/mini_melissa_ultragirl_animal_lovers_gata_205_variacao_277_2_6c318377510309443ece3177711ae075.jpeg
A39: 281 | B39: 207 | C39: 7894443800401 | D39: COR | E39: marrom | F39: Tamanho | G39: 20/21 | H39: 100 | I39: 55 | J39: 0 | K39: 1 | L39: 21.08 | O39: 0 | P39: § | Q39: https://images.tcdn.com.br/img/img_prod/995386/mini_melissa_triple_bowl_207_variacao_281_2_e08f226ed3e9ceff0f2033f617fcadb2.jpeg | R39: 25 | S39: 15 | T39: 10 | U39: https://images.tcdn.com.br/img/img_prod/995386/mini_melissa_triple_bowl_207_variacao_281_2_e08f226ed3e9ceff0f2033f617fcadb2.jpeg, https://images.tcdn.com.br/img/img_prod/995386/mini_melissa_triple_bowl_207_variacao_281_3_bf294254a3262713d0dd1420c83a08ad.jpeg, https://images.tcdn.com.br/img/img_prod/995386/mini_melissa_triple_bowl_207_variacao_281_4_6cbf202219b7f943a7bdf05f571ca69f.jpeg, https://images.tcdn.com.br/img/img_prod/995386/mini_melissa_triple_bowl_207_variacao_281_5_0da9c5a2033ae6ce6e6f1786d5b9a8ae.jpeg
A40: 291 | B40: 111 | C40: 7894443800418 | D40: COR | E40: Rosa Glitter | F40: Tamanho | G40: 19 | I40: 55 | J40: 0 | K40: 0 | L40: 27.1 | O40: 0 | P40: § | Q40: https://images.tcdn.com.br/img/img_prod/995386/mini_melissa_ultragirl_unicornio_111_variacao_291_2_e640afd02d596b45543d3582ef955c77.jpeg | U40: https://images.tcdn.com.br/img/img_prod/995386/mini_melissa_ultragirl_unicornio_111_variacao_291_2_e640afd02d596b45543d3582ef955c77.jpeg, https://images.tcdn.com.br/img/img_prod/995386/mini_melissa_ultragirl_unicornio_111_variacao_291_3_705bfc3ca4cc38b8f52d765dc4e13f9a.jpeg, https://images.tcdn.com.br/img/img_prod/995386/mini_melissa_ultragirl_unicornio_111_variacao_291_4_1b87962f8098152baf906ae2110e2510.jpeg, https://images.tcdn.com.br/img/img_prod/995386/mini_melissa_ultragirl_unicornio_111_variacao_291_5_fb8daa6722c01cf0d1f1538a529d2efa.jpeg
A41: 295 | B41: 209 | C41: 7894443800425 | D41: COR | E41: Rosa | F41: Tamanho | G41: 19 | I41: 55 | J41: 0 | K41: 2 | L41: 27.08 | O41: 0 | P41: § | Q41: https://images.tcdn.com.br/img/img_prod/995386/mini_melissa_beach_slide_mickey_e_minnie_209_variacao_295_2_fb782e9029a435f58efc8466b686f7f3.jpeg | U41: https://images.tcdn.com.br/img/img_prod/995386/mini_melissa_beach_slide_mickey_e_minnie_209_variacao_295_2_fb782e9029a435f58efc8466b686f7f3.jpeg, https://images.tcdn.com.br/img/img_prod/995386/mini_melissa_beach_slide_mickey_e_minnie_209_variacao_295_3_845f950f4e7205aad086f8e41cb7c8f0.jpeg, https://images.tcdn.com.br/img/img_prod/995386/mini_melissa_beach_slide_mickey_e_minnie_209_variacao_295_4_541bcb0462ada2199d503b694e98dd0c.jpeg, https://images.tcdn.com.br/img/img_prod/995386/mini_melissa_beach_slide_mickey_e_minnie_209_variacao_295_5_e803df6edc5b2c5b35f23ffb1a2c1481.jpeg
A42: 297 | B42: 53 | C42: 7894443800432 | D42: COR | E42: Prata | F42: Tamanho | G42: 19 | H42: 100 | I42: 40 | J42: 0 | K42: 2 | L42: 27.08 | O42: 0 | P42: § | Q42: https://images.tcdn.com.br/img/img_prod/995386/mini_melissa_campana_zig_zag_53_variacao_297_2_19a65aa5532daa180d13fe0fec6095a2.jpeg | R42: 25 | S42: 15 | T42: 10 | U42: https://images.tcdn.com.br/img/img_prod/995386/mini_melissa_campana_zig_zag_53_variacao_297_2_19a65aa5532daa180d13fe0fec6095a2.jpeg, https://images.tcdn.com.br/img/img_prod/995386/mini_melissa_campana_zig_zag_53_variacao_297_3_7919be89729e45c77f0139989919adba.jpeg, https://images.tcdn.com.br/img/img_prod/995386/mini_melissa_campana_zig_zag_53_variacao_297_4_bc95815e78c8f56cea4f446c65fb09d2.jpeg, https://images.tcdn.com.br/img/img_prod/995386/mini_melissa_campana_zig_zag_53_variacao_297_5_b7e4eb5bed1f2e5563070676ecf60e9e.jpeg, https://images.tcdn.com.br/img/img_prod/995386/mini_melissa_campana_zig_zag_53_variacao_297_6_a8bd6caf558ac7ae75a15235162f62dd.jpeg
A43: 309 | B43: 51 | C43: 7894443800449 | D43: COR | E43: Rosa Chiclete | F43: Tamanho | G43: 17/18 | I43: 65 | J43: 0 | K43: 4 | L43: 27.08 | O43: 0 | P43: § | Q43: https://images.tcdn.com.br/img/img_prod/995386/mini_melissa_sneaker_ulitsa_51_variacao_309_2_253d9dd55f3b6b0c963a87288c44d806.jpeg | U43: https://images.tcdn.com.br/img/img_prod/995386/mini_melissa_sneaker_ulitsa_51_variacao_309_2_253d9dd55f3b6b0c963a87288c44d806.jpeg, https://images.tcdn.com.br/img/img_prod/995386/mini_melissa_sneaker_ulitsa_51_variacao_309_3_ce4fe301a4cf54d9ecbe3b6771fdb719.jpeg, https://images.tcdn.com.br/img/img_prod/995386/mini_melissa_sneaker_ulitsa_51_variacao_309_4_a3cf15086a08a6e8618cb3d94ef4cd9e.jpeg, https://images.tcdn.com.br/img/img_prod/995386/mini_melissa_sneaker_ulitsa_51_variacao_309_5_9debc934aaf78cd5ddf446f582e9324b.jpeg, https://images.tcdn.com.br/img/img_prod/995386/mini_melissa_sneaker_ulitsa_51_variacao_309_6_e2a4b88baee0f16188b896193ad2db9c.jpeg
A44: 311 | B44: 93 | C44: 7894443800456 | D44: Tamanho | E44: 17/18 | F44: COR | G44: Rosa | H44: 100 | I44: 55 | J44: 0 | K44: 3 | L44: 27.08 | O44: 0 | P44: § | Q44: https://images.tcdn.com.br/img/img_prod/995386/mini_melissa_beach_sandal_93_variacao_311_2_0f4b9d8684a59ee79cee4faaf7a5d52e.jpeg | R44: 25 | S44: 15 | T44: 10 | U44: https://images.tcdn.com.br/img/img_prod/995386/mini_melissa_beach_sandal_93_variacao_311_2_0f4b9d8684a59ee79cee4faaf7a5d52e.jpeg, https://images.tcdn.com.br/img/img_prod/995386/mini_melissa_beach_sandal_93_variacao_311_3_f90e8de2169feed38a8f09fe7eb091b8.jpeg, https://images.tcdn.com.br/img/img_prod/995386/mini_melissa_beach_sandal_93_variacao_311_4_ab23db5c41a40f384897aa646e8b1e8f.jpeg, https://images.tcdn.com.br/img/img_prod/995386/mini_melissa_beach_sandal_93_variacao_311_5_fd4129307ef366f5979c2ca8d8bd2921.jpeg
A45: 313 | B45: 128 | C45: 7894443800463 | D45: COR | E45: Rosa Choque | F45: Tamanho | G45: 19 | I45: 40 | J45: 0 | K45: 1 | L45: 27.08 | O45: 0 | P45: § | Q45: https://images.tcdn.com.br/img/img_prod/995386/mini_melissa_furadinha_pic_nic_128_variacao_313_2_f87773873fe4a1dfddaf9db4d24e5ca4.jpeg | U45: https://images.tcdn.com.br/img/img_prod/995386/mini_melissa_furadinha_pic_nic_128_variacao_313_2_f87773873fe4a1dfddaf9db4d24e5ca4.jpeg, https://images.tcdn.com.br/img/img_prod/995386/mini_melissa_furadinha_pic_nic_128_variacao_313_3_9e62b9d501cf16e3438cdae21dab19fa.jpeg, https://images.tcdn.com.br/img/img_prod/995386/mini_melissa_furadinha_pic_nic_128_variacao_313_4_77271b227113a68727fce64bc920934b.jpeg, https://images.tcdn.com.br/img/img_prod/995386/mini_melissa_furadinha_pic_nic_128_variacao_313_5_4f88e41b32780951f461c60e48699290.jpeg, https://images.tcdn.com.br/img/img_prod/995386/mini_melissa_furadinha_pic_nic_128_variacao_313_6_0a587cdb6bf69b210dfee9565d05fdb6.jpeg
A46: 315 | B46: 47 | C46: 7894443800470 | D46: COR | E46: Rosa | F46: Tamanho | G46: 19 | H46: 100 | I46: 40 | J46: 0 | K46: 1 | L46: 27.08 | O46: 0 | P46: usada | Q46: https://images.tcdn.com.br/img/img_prod/995386/mini_melissa_furadinha_frutas_47_variacao_315_2_9ce328f8fbb4f8ad5b8b34fdd7c87fd0.jpg | R46: 25 | S46: 15 | T46: 10 | U46: https://images.tcdn.com.br/img/img_prod/995386/mini_melissa_furadinha_frutas_47_variacao_315_2_9ce328f8fbb4f8ad5b8b34fdd7c87fd0.jpg, https://images.tcdn.com.br/img/img_prod/995386/mini_melissa_furadinha_frutas_47_variacao_315_3_b6d8f5629d283e7f2e5aedf039d91e2d.jpg, https://images.tcdn.com.br/img/img_prod/995386/mini_melissa_furadinha_frutas_47_variacao_315_4_c35e7f30bea3c1322a204f37e9f1856a.jpg, https://images.tcdn.com.br/img/img_prod/995386/mini_melissa_furadinha_frutas_47_variacao_315_5_be9c2532a0fa4e49ba68cdd5e050fa22.jpg, https://images.tcdn.com.br/img/img_prod/995386/mini_melissa_furadinha_frutas_47_variacao_315_6_593959f818a248e98a7c49122adc41e2.jpg
A47: 319 | B47: 151 | C47: 7894443800487 | D47: COR | E47: Rosa | F47: Tamanho | G47: 25 | H47: 100 | I47: 50 | J47: 0 | K47: 1 | L47: 27.08 | O47: 0 | P47: § | Q47: https://images.tcdn.com.br/img/img_prod/995386/mini_melissa_swett_minnie_151_variacao_319_2_60e7d878362f5b2afecd7ce2d6df68fc.jpeg | U47: https://images.tcdn.com.br/img/img_prod/995386/mini_melissa_swett_minnie_151_variacao_319_2_60e7d878362f5b2afecd7ce2d6df68fc.jpeg, https://images.tcdn.com.br/img/img_prod/995386/mini_melissa_swett_minnie_151_variacao_319_3_c7be66636373aa180624030fd8337844.jpg
A48: 323 | B48: 53 | C48: 7894443800494 | D48: COR | E48: Dourado Glitter | F48: Tamanho | G48: 19 | I48: 40 | J48: 0 | K48: 0 | L48: 27.78 | O48: 0 | P48: § | Q48: https://images.tcdn.com.br/img/img_prod/995386/mini_melissa_campana_zig_zag_53_variacao_323_2_b68e4acfe05c9b5cb195805b3c47ca7d.jpeg | U48: https://images.tcdn.com.br/img/img_prod/995386/mini_melissa_campana_zig_zag_53_variacao_323_2_b68e4acfe05c9b5cb195805b3c47ca7d.jpeg, https://images.tcdn.com.br/img/img_prod/995386/mini_melissa_campana_zig_zag_53_variacao_323_3_68cab83609eada1ee918b0fef591e806.jpeg, https://images.tcdn.com.br/img/img_prod/995386/mini_melissa_campana_zig_zag_53_variacao_323_4_5fe10dd790e004e6db299f273896c8ee.jpeg, https://images.tcdn.com.br/img/img_prod/995386/mini_melissa_campana_zig_zag_53_variacao_323_5_4762e7a3f884e263d15b1e26ddce7c46.jpeg
A49: 329 | B49: 145 | C49: 7894443800500 | D49: COR | E49: Vidro | F49: Tamanho | G49: 17/18 | I49: 45 | J49: 0 | K49: 1 | L49: 27.78 | O49: 0 | P49: § | Q49: https://images.tcdn.com.br/img/img_prod/995386/mini_melissa_aranha_picole_145_variacao_329_2_836779e297fc1addd64a3398ec09f594.jpeg | U49: https://images.tcdn.com.br/img/img_prod/995386/mini_melissa_aranha_picole_145_variacao_329_2_836779e297fc1addd64a3398ec09f594.jpeg, https://images.tcdn.com.br/img/img_prod/995386/mini_melissa_aranha_picole_145_variacao_329_3_e8c380aa72df0f06a2ae4d5d2b141e20.jpeg, https://images.tcdn.com.br/img/img_prod/995386/mini_melissa_aranha_picole_145_variacao_329_4_3d26b97b36dfd12583351ea90dd39794.jpeg, https://images.tcdn.com.br/img/img_prod/995386/mini_melissa_aranha_picole_145_variacao_329_5_e246ee97144c6e4885e3826bf2299335.jpeg
A50: 333 | B50: 213 | C50: 7894443800517 | D50: COR | E50: Bege | F50: Tamanho | G50: 17/18 | I50: 55 | J50: 0 | K50: 0 | L50: 37 | O50: 0 | P50: §
A51: 335 | B51: 145 | C51: 7894443800524 | D51: COR | E51: Vidro | F51: Tamanho | G51: 19 | I51: 45 | J51: 0 | K51: 1 | L51: 37 | O51: 0 | P51: § | Q51: https://images.tcdn.com.br/img/img_prod/995386/mini_melissa_aranha_picole_145_variacao_335_2_836779e297fc1addd64a3398ec09f594.jpeg | U51: https://images.tcdn.com.br/img/img_prod/995386/mini_melissa_aranha_picole_145_variacao_335_2_836779e297fc1addd64a3398ec09f594.jpeg, https://images.tcdn.com.br/img/img_prod/995386/mini_melissa_aranha_picole_145_variacao_335_3_776772e88d51f6deddf51f0faac06909.jpeg, https://images.tcdn.com.br/img/img_prod/995386/mini_melissa_aranha_picole_145_variacao_335_4_e8c380aa72df0f06a2ae4d5d2b141e20.jpeg, https://images.tcdn.com.br/img/img_prod/995386/mini_melissa_aranha_picole_145_variacao_335_5_e246ee97144c6e4885e3826bf2299335.jpeg
A52: 339 | B52: 121 | C52: 7894443800531 | D52: COR | E52: Colorido Glitter | F52: Tamanho | G52: 25 | I52: 65 | J52: 0 | K52: 3 | L52: 37 | O52: 0 | P52: § | Q52: https://images.tcdn.com.br/img/img_prod/995386/mini_melissa_sneaker_love_system_121_variacao_339_2_a7d6c67366dd8654e262462022f214e8.jpeg | U52: https://images.tcdn.com.br/img/img_prod/995386/mini_melissa_sneaker_love_system_121_variacao_339_2_a7d6c67366dd8654e262462022f214e8.jpeg, https://images.tcdn.com.br/img/img_prod/995386/mini_melissa_sneaker_love_system_121_variacao_339_3_ee4a77024b60537d2c3cc55b64b23772.jpeg, https://images.tcdn.com.br/img/img_prod/995386/mini_melissa_sneaker_love_system_121_variacao_339_4_b984acc0cda6f8c06da1e1a95d77bb74.jpeg, https://images.tcdn.com.br/img/img_prod/995386/mini_melissa_sneaker_love_system_121_variacao_339_5_59d2900fa0915bc8e87ab0e5b5ee26b4.jpeg
A53: 343 | B53: 62 | C53: 7894443800548 | D53: COR | E53: Caramelo | F53: Tamanho | G53: 25 | I53: 65 | J53: 0 | K53: 2 | L53: 50 | O53: 0 | P53: § | Q53: https://images.tcdn.com.br/img/img_prod/995386/mini_melissa_beach_line_friends_cachorro_62_variacao_343_2_309aca7e87229dbc14c033222dd43a0a.jpeg | U53: https://images.tcdn.com.br/img/img_prod/995386/mini_melissa_beach_line_friends_cachorro_62_variacao_343_2_309aca7e87229dbc14c033222dd43a0a.jpeg, https://images.tcdn.com.br/img/img_prod/995386/mini_melissa_beach_line_friends_cachorro_62_variacao_343_3_09cc135add0a97e7e97d11911bb7c6e8.jpeg, https://images.tcdn.com.br/img/img_prod/995386/mini_melissa_beach_line_friends_cachorro_62_variacao_343_4_02392e46240824f1ca61e765c5077ce0.jpeg, https://images.tcdn.com.br/img/img_prod/995386/mini_melissa_beach_line_friends_cachorro_62_variacao_343_5_f5ba27eb2851e87392b54d331409e911.jpeg
A54: 347 | B54: 217 | C54: 7894443800555 | D54: COR | E54: VERDE AGUA | F54: Tamanho | G54: 31 | I54: 55 | J54: 0 | K54: 2 | L54: 37 | O54: 0 | P54: § | Q54: https://images.tcdn.com.br/img/img_prod/995386/melissa_mel_aranha1976_vi_217_variacao_347_2_6efae61783cf2c19197112c1e661582b.jpg | U54: https://images.tcdn.com.br/img/img_prod/995386/melissa_mel_aranha1976_vi_217_variacao_347_2_6efae61783cf2c19197112c1e661582b.jpg, https://images.tcdn.com.br/img/img_prod/995386/melissa_mel_aranha1976_vi_217_variacao_347_3_7fbfbcf43cc22f2d83349fded8e90a6f.jpg, https://images.tcdn.com.br/img/img_prod/995386/melissa_mel_aranha1976_vi_217_variacao_347_4_e756847f7b9dc2999e2430a9b894e789.jpg, https://images.tcdn.com.br/img/img_prod/995386/melissa_mel_aranha1976_vi_217_variacao_347_5_3f14b5851c1c12622b1b75ffbbedb559.jpg, https://images.tcdn.com.br/img/img_prod/995386/melissa_mel_aranha1976_vi_217_variacao_347_6_d32e31b6ce08a90d55420726414bd3d1.jpg
A55: 365 | B55: 143 | C55: 7894443800562 | D55: COR | E55: Amarelo | F55: Tamanho | G55: 19/20 | I55: 60 | J55: 0 | K55: 0 | L55: 35.46 | O55: 0 | P55: § | Q55: https://images.tcdn.com.br/img/img_prod/995386/mini_melissa_boot_baby_143_variacao_365_2_c5fc736d193670df27730e1b4f931365.png | U55: https://images.tcdn.com.br/img/img_prod/995386/mini_melissa_boot_baby_143_variacao_365_2_c5fc736d193670df27730e1b4f931365.png
A56: 367 | B56: 143 | C56: 7894443800579 | D56: COR | E56: Rosa Choque | F56: Tamanho | G56: 19/20 | I56: 60 | J56: 0 | K56: 1 | L56: 43.2 | O56: 0 | P56: § | Q56: https://images.tcdn.com.br/img/img_prod/995386/mini_melissa_boot_baby_143_variacao_367_2_17b986edede3c5e32e97a10da9aed81f.jpeg | U56: https://images.tcdn.com.br/img/img_prod/995386/mini_melissa_boot_baby_143_variacao_367_2_17b986edede3c5e32e97a10da9aed81f.jpeg, https://images.tcdn.com.br/img/img_prod/995386/mini_melissa_boot_baby_143_variacao_367_3_de39dd0b675c01ab19cd1eca786b5dbe.jpg, https://images.tcdn.com.br/img/img_prod/995386/mini_melissa_boot_baby_143_variacao_367_4_c6c8aa0fc58ec5d458ba05e5e33557ef.jpeg, https://images.tcdn.com.br/img/img_prod/995386/mini_melissa_boot_baby_143_variacao_367_5_fad615aa7b23cfc7cec9dde7c7c9e28a.jpg
A57: 371 | B57: 87 | C57: 7894443800586 | D57: COR | E57: Vidro | F57: Tamanho | G57: 19 | I57: 55 | J57: 0 | K57: 6 | L57: 35.13 | O57: 0 | P57: § | Q57: https://images.tcdn.com.br/img/img_prod/995386/mini_melissa_possession_87_variacao_371_3_1ad9f54e954b311c20dbbb0b74983757.jpg | R57: 25 | S57: 15 | T57: 10 | U57: https://images.tcdn.com.br/img/img_prod/995386/mini_melissa_possession_87_variacao_371_3_1ad9f54e954b311c20dbbb0b74983757.jpg, https://images.tcdn.com.br/img/img_prod/995386/mini_melissa_possession_87_variacao_371_4_21c3193ad1d53b3bfbb8e4b5fec60209.jpg, https://images.tcdn.com.br/img/img_prod/995386/mini_melissa_possession_87_variacao_371_5_ee5a5836dce92eba41d85a2e97899b91.jpg, https://images.tcdn.com.br/img/img_prod/995386/mini_melissa_possession_87_variacao_371_6_6a9e22d4f1130b441558474d805eb646.jpg
A58: 379 | B58: 53 | C58: 7894443800593 | D58: COR | E58: Gliter Bronse | F58: Tamanho | G58: 23/24 | I58: 40 | J58: 0 | K58: 1 | L58: 28.21 | O58: 0 | P58: § | Q58: https://images.tcdn.com.br/img/img_prod/995386/mini_melissa_campana_zig_zag_53_variacao_379_2_42c91065089d8d940d60a426b550c999.jpeg | U58: https://images.tcdn.com.br/img/img_prod/995386/mini_melissa_campana_zig_zag_53_variacao_379_2_42c91065089d8d940d60a426b550c999.jpeg, https://images.tcdn.com.br/img/img_prod/995386/mini_melissa_campana_zig_zag_53_variacao_379_3_a23a9e0cbf2ee2445151088c610b4027.jpeg, https://images.tcdn.com.br/img/img_prod/995386/mini_melissa_campana_zig_zag_53_variacao_379_4_50696ef913976c8a14778811105dafda.jpeg, https://images.tcdn.com.br/img/img_prod/995386/mini_melissa_campana_zig_zag_53_variacao_379_5_a2e711c7f638a08cc6ad3192a8901a68.jpeg
A59: 381 | B59: 147 | C59: 7894443800609 | D59: COR | E59: Vidro | F59: Tamanho | G59: 22 | I59: 50 | J59: 0 | K59: 0 | L59: 0 | O59: 0 | P59: 16 usada | Q59: https://images.tcdn.com.br/img/img_prod/995386/mini_melissa_ultragirl_minnie_laco_lateral_147_variacao_381_2_70959122f1cbd93faae5e5473f048a92.jpg | U59: https://images.tcdn.com.br/img/img_prod/995386/mini_melissa_ultragirl_minnie_laco_lateral_147_variacao_381_2_70959122f1cbd93faae5e5473f048a92.jpg, https://images.tcdn.com.br/img/img_prod/995386/mini_melissa_ultragirl_minnie_laco_lateral_147_variacao_381_3_ce26b79f93c0388a4887f93a89717e3c.jpg, https://images.tcdn.com.br/img/img_prod/995386/mini_melissa_ultragirl_minnie_laco_lateral_147_variacao_381_4_1d65254170f74abee439cd909b7824b4.jpg, https://images.tcdn.com.br/img/img_prod/995386/mini_melissa_ultragirl_minnie_laco_lateral_147_variacao_381_5_491535dce651c897a676cd0ae49504de.jpg
A60: 393 | B60: 53 | C60: 7894443800616 | D60: COR | E60: Gliter Bronse | F60: Tamanho | G60: 20/21 | I60: 40 | J60: 0 | K60: 1 | L60: 25 | O60: 0 | P60: § | Q60: https://images.tcdn.com.br/img/img_prod/995386/mini_melissa_campana_zig_zag_53_variacao_393_2_b28b67cc661ea286195852b9e2bbf1f3.jpeg | U60: https://images.tcdn.com.br/img/img_prod/995386/mini_melissa_campana_zig_zag_53_variacao_393_2_b28b67cc661ea286195852b9e2bbf1f3.jpeg, https://images.tcdn.com.br/img/img_prod/995386/mini_melissa_campana_zig_zag_53_variacao_393_3_46101f8a4d0da937ffaea33e32715cb8.jpg, https://images.tcdn.com.br/img/img_prod/995386/mini_melissa_campana_zig_zag_53_variacao_393_4_19df4c1eef4deebad31a921b0130157a.jpg, https://images.tcdn.com.br/img/img_prod/995386/mini_melissa_campana_zig_zag_53_variacao_393_5_a4240f3bebe37d95db3c608fcd7456cb.jpg
A61: 409 | B61: 235 | C61: 7894443800623 | D61: COR | E61: Amarelo | F61: Tamanho | G61: 28 | I61: 50 | J61: 0 | K61: 0 | L61: 42.19 | O61: 0 | P61: § | Q61: https://images.tcdn.com.br/img/img_prod/995386/melissa_mel_dreamed_235_variacao_409_2_612bfdf8765ea6b88614277cf5a09c09.png | U61: https://images.tcdn.com.br/img/img_prod/995386/melissa_mel_dreamed_235_variacao_409_2_612bfdf8765ea6b88614277cf5a09c09.png
A62: 417 | B62: 239 | C62: 7894443800630 | D62: COR | E62: Branco | F62: Tamanho | G62: 28 | H62: 100 | I62: 65 | J62: 0 | K62: 5 | L62: 30 | O62: 0 | P62: § | Q62: https://images.tcdn.com.br/img/img_prod/995386/mini_melissa_basic_baby_239_variacao_417_2_d9d8e48a5ed9811674ddb09a50f1bc04.jpg | R62: 25 | S62: 15 | T62: 10 | U62: https://images.tcdn.com.br/img/img_prod/995386/mini_melissa_basic_baby_239_variacao_417_2_d9d8e48a5ed9811674ddb09a50f1bc04.jpg, https://images.tcdn.com.br/img/img_prod/995386/mini_melissa_basic_baby_239_variacao_417_3_5f3282b399ee3bd4859b75bd11859e10.jpg, https://images.tcdn.com.br/img/img_prod/995386/mini_melissa_basic_baby_239_variacao_417_4_e7352495b8c14dd8c3801fc723759e5a.jpg, https://images.tcdn.com.br/img/img_prod/995386/mini_melissa_basic_baby_239_variacao_417_5_957de7df2fd147564a4a28395bfc7986.jpg, https://images.tcdn.com.br/img/img_prod/995386/mini_melissa_basic_baby_239_variacao_417_6_07864b32332e5876680574ed74b3403e.jpg
A63: 423 | B63: 189 | C63: 7894443800647 | D63: COR | E63: Bege | F63: Tamanho | G63: 25 | I63: 55 | J63: 0 | K63: 1 | L63: 25.48 | O63: 0 | P63: § | Q63: https://images.tcdn.com.br/img/img_prod/995386/mini_melissa_mar_sandal_189_variacao_423_2_7d04837a9af5e4466691880db04ca636.jpeg | U63: https://images.tcdn.com.br/img/img_prod/995386/mini_melissa_mar_sandal_189_variacao_423_2_7d04837a9af5e4466691880db04ca636.jpeg, https://images.tcdn.com.br/img/img_prod/995386/mini_melissa_mar_sandal_189_variacao_423_3_c86287d12fffaad96b6c0f0ede606519.jpeg, https://images.tcdn.com.br/img/img_prod/995386/mini_melissa_mar_sandal_189_variacao_423_4_62c1794dd02bba287103be89c69ec261.jpeg, https://images.tcdn.com.br/img/img_prod/995386/mini_melissa_mar_sandal_189_variacao_423_5_6bff19aea0d47eed3e4a0c91bf94ab4f.jpeg
A64: 427 | B64: 241 | C64: 7894443800654 | D64: COR | E64: Rosa Chiclete | F64: Tamanho | G64: 17/18 | I64: 55 | J64: 0 | K64: 2 | L64: 0 | O64: 0 | P64: § | Q64: https://images.tcdn.com.br/img/img_prod/995386/mini_melissa_alpha_play_241_variacao_427_2_11280a0176fe7ed594a63e0bdf7b2428.jpeg | U64: https://images.tcdn.com.br/img/img_prod/995386/mini_melissa_alpha_play_241_variacao_427_2_11280a0176fe7ed594a63e0bdf7b2428.jpeg, https://images.tcdn.com.br/img/img_prod/995386/mini_melissa_alpha_play_241_variacao_427_3_55a61541d1b7f66f2a2dcd20b2d9a886.jpeg, https://images.tcdn.com.br/img/img_prod/995386/mini_melissa_alpha_play_241_variacao_427_4_2ff8deff3e28fe7bd3405af893fbe73d.jpeg, https://images.tcdn.com.br/img/img_prod/995386/mini_melissa_alpha_play_241_variacao_427_5_f8afc984d528a4e96816932cea1a4c35.jpeg, https://images.tcdn.com.br/img/img_prod/995386/mini_melissa_alpha_play_241_variacao_427_6_4bc463aa3f38630536c07158bdf45450.jpeg
A65: 437 | B65: 245 | C65: 7894443800661 | D65: COR | E65: Azul escuro | F65: Tamanho | G65: 23/24 | H65: 300 | I65: 60 | J65: 0 | K65: 2 | L65: 30.71 | O65: 0 | P65: § | Q65: https://images.tcdn.com.br/img/img_prod/995386/mini_melissa_jump_245_variacao_437_2_b4d1bc0d6b02cb0b4c4d8f2bc1682b58.jpeg | R65: 25 | S65: 15 | T65: 10 | U65: https://images.tcdn.com.br/img/img_prod/995386/mini_melissa_jump_245_variacao_437_2_b4d1bc0d6b02cb0b4c4d8f2bc1682b58.jpeg, https://images.tcdn.com.br/img/img_prod/995386/mini_melissa_jump_245_variacao_437_3_c07f3290fde39ae921322d435a07dfce.png, https://images.tcdn.com.br/img/img_prod/995386/mini_melissa_jump_245_variacao_437_4_f07f47de866c7aee977f82817b1658b0.png, https://images.tcdn.com.br/img/img_prod/995386/mini_melissa_jump_245_variacao_437_5_dc5b58084e1dd2373ef29fe8dd6012a1.jpg, https://images.tcdn.com.br/img/img_prod/995386/mini_melissa_jump_245_variacao_437_6_eb8965ab91f3067c56d771238657b6b2.jpeg
A66: 449 | B66: 149 | C66: 7894443800678 | D66: COR | E66: Rosa | F66: Tamanho | G66: 19 | I66: 21 | J66: 0 | K66: 1 | L66: 30 | O66: 0 | P66: § | Q66: https://images.tcdn.com.br/img/img_prod/995386/mini_melissa_furadinha_fabula_149_variacao_449_2_9f2755e0646fde4c58028acabdafc95e.jpeg | U66: https://images.tcdn.com.br/img/img_prod/995386/mini_melissa_furadinha_fabula_149_variacao_449_2_9f2755e0646fde4c58028acabdafc95e.jpeg, https://images.tcdn.com.br/img/img_prod/995386/mini_melissa_furadinha_fabula_149_variacao_449_3_b5b665854fa03206410c6c51d480df3d.jpeg
A67: 455 | B67: 96 | C67: 7894443800685 | D67: COR | E67: Dourado Glitter | F67: Tamanho | G67: 17/18 | I67: 50 | J67: 0 | K67: 2 | L67: 35 | O67: 0 | P67: § | Q67: https://images.tcdn.com.br/img/img_prod/995386/mini_melissa_campana_crochet_96_variacao_455_2_0741252328b207ae5cd41d439a570869.jpeg | U67: https://images.tcdn.com.br/img/img_prod/995386/mini_melissa_campana_crochet_96_variacao_455_2_0741252328b207ae5cd41d439a570869.jpeg, https://images.tcdn.com.br/img/img_prod/995386/mini_melissa_campana_crochet_96_variacao_455_3_ddb26fe872f386d2acb79c5021d91911.jpeg, https://images.tcdn.com.br/img/img_prod/995386/mini_melissa_campana_crochet_96_variacao_455_4_b509feb12f8ee568a9ee9a651472394c.jpeg, https://images.tcdn.com.br/img/img_prod/995386/mini_melissa_campana_crochet_96_variacao_455_5_0676e13363e1d5091bcb4846475380f4.jpeg, https://images.tcdn.com.br/img/img_prod/995386/mini_melissa_campana_crochet_96_variacao_455_6_50d67ff33ea354177c0bc695fc58a0fb.jpeg
A68: 459 | B68: 64 | C68: 7894443800692 | D68: COR | E68: Azul | F68: Tamanho | G68: 17/18 | I68: 40 | J68: 0 | K68: 0 | L68: 25 | O68: 0 | P68: § | Q68: https://images.tcdn.com.br/img/img_prod/995386/mini_melissa_aranha_smurfs_64_variacao_459_2_003f447866b6f55b535ea36351ba405d.jpg | U68: https://images.tcdn.com.br/img/img_prod/995386/mini_melissa_aranha_smurfs_64_variacao_459_2_003f447866b6f55b535ea36351ba405d.jpg
A69: 461 | B69: 233 | C69: 7894443800708 | D69: COR | E69: Preto | F69: Tamanho | G69: 17/18 | I69: 35 | J69: 0 | K69: 1 | L69: 0 | O69: 0 | P69: § | Q69: https://images.tcdn.com.br/img/img_prod/995386/mini_melissa_ultragirl_animal_lovers_gato_233_variacao_461_2_d0f9e8fd9cb66f6f817154112dfb38f4.jpeg | U69: https://images.tcdn.com.br/img/img_prod/995386/mini_melissa_ultragirl_animal_lovers_gato_233_variacao_461_2_d0f9e8fd9cb66f6f817154112dfb38f4.jpeg, https://images.tcdn.com.br/img/img_prod/995386/mini_melissa_ultragirl_animal_lovers_gato_233_variacao_461_3_52252089cc7d7a965f656c4aadc50ffa.jpeg
A70: 467 | B70: 94 | C70: 7894443800715 | D70: COR | E70: Preto | F70: Tamanho | G70: 19 | I70: 60 | J70: 0 | K70: 4 | L70: 45 | O70: 0 | P70: § | Q70: https://images.tcdn.com.br/img/img_prod/995386/mini_melissa_sneaker_be_disney_94_variacao_467_2_0ac0bdc0cdbacbe06f99970dd207048d.jpeg | U70: https://images.tcdn.com.br/img/img_prod/995386/mini_melissa_sneaker_be_disney_94_variacao_467_2_0ac0bdc0cdbacbe06f99970dd207048d.jpeg, https://images.tcdn.com.br/img/img_prod/995386/mini_melissa_sneaker_be_disney_94_variacao_467_3_309fe1ed5e4dea7f8eb195e99cb3af21.jpeg, https://images.tcdn.com.br/img/img_prod/995386/mini_melissa_sneaker_be_disney_94_variacao_467_4_dde50f70cc88b4f1d2e48ae7a4292ed8.jpeg, https://images.tcdn.com.br/img/img_prod/995386/mini_melissa_sneaker_be_disney_94_variacao_467_5_94f70340949e7b0eb3ad859e66213da4.jpeg, https://images.tcdn.com.br/img/img_prod/995386/mini_melissa_sneaker_be_disney_94_variacao_467_6_22dda69a928f8f3bd8eba9dd7ef0f2b0.jpeg
A71: 485 | B71: 96 | C71: 7894443800722 | D71: COR | E71: marrom | F71: Tamanho | G71: 19 | I71: 40 | J71: 0 | K71: 2 | L71: 0 | O71: 0 | P71: § | Q71: https://images.tcdn.com.br/img/img_prod/995386/mini_melissa_campana_crochet_96_variacao_485_2_f906aee2e24aebebb0ecf29e98d95452.jpeg | U71: https://images.tcdn.com.br/img/img_prod/995386/mini_melissa_campana_crochet_96_variacao_485_2_f906aee2e24aebebb0ecf29e98d95452.jpeg, https://images.tcdn.com.br/img/img_prod/995386/mini_melissa_campana_crochet_96_variacao_485_3_4803df7f774638049a8553418f53adca.jpeg, https://images.tcdn.com.br/img/img_prod/995386/mini_melissa_campana_crochet_96_variacao_485_4_f13d2aaad94b904fe806ae80cf2d3ab2.jpeg, https://images.tcdn.com.br/img/img_prod/995386/mini_melissa_campana_crochet_96_variacao_485_5_72df2020893b2c177dc75003ec72b151.jpeg, https://images.tcdn.com.br/img/img_prod/995386/mini_melissa_campana_crochet_96_variacao_485_6_05aaad3fe6a0e61b5348860094767818.jpeg
A72: 495 | B72: 255 | C72: 7894443800739 | D72: COR | E72: Rosa | F72: Tamanho | G72: 19 | I72: 80 | J72: 0 | K72: 3 | L72: 134 | O72: 0 | P72: § | Q72: https://images.tcdn.com.br/img/img_prod/995386/mini_melissa_street_minnie_255_variacao_495_2_d02d79e317400c8c4d85dbd8acbecf71.jpeg | U72: https://images.tcdn.com.br/img/img_prod/995386/mini_melissa_street_minnie_255_variacao_495_2_d02d79e317400c8c4d85dbd8acbecf71.jpeg, https://images.tcdn.com.br/img/img_prod/995386/mini_melissa_street_minnie_255_variacao_495_3_f7808039a288dfca8f78f4f4d05e7357.jpeg, https://images.tcdn.com.br/img/img_prod/995386/mini_melissa_street_minnie_255_variacao_495_4_7bbc9aa61e6f78b617db31b0f045143f.jpeg, https://images.tcdn.com.br/img/img_prod/995386/mini_melissa_street_minnie_255_variacao_495_5_56d4684767a74fc33c42ff568bc5e927.jpeg, https://images.tcdn.com.br/img/img_prod/995386/mini_melissa_street_minnie_255_variacao_495_6_da52a70a40e2867014a7ebe7997fc701.jpeg
A73: 499 | B73: 255 | C73: 7894443800746 | D73: COR | E73: Rosa | F73: Tamanho | G73: 23/24 | H73: 500 | I73: 80 | J73: 0 | K73: 0 | L73: 134 | O73: 0 | P73: § | Q73: https://images.tcdn.com.br/img/img_prod/995386/mini_melissa_street_minnie_255_variacao_499_2_73c4fdc518fd8e89819a31aeb7d1aa00.jpeg | R73: 25 | S73: 15 | T73: 10 | U73: https://images.tcdn.com.br/img/img_prod/995386/mini_melissa_street_minnie_255_variacao_499_2_73c4fdc518fd8e89819a31aeb7d1aa00.jpeg, https://images.tcdn.com.br/img/img_prod/995386/mini_melissa_street_minnie_255_variacao_499_3_55def866082caacd0aa34b14771df60b.jpg
A74: 501 | B74: 255 | C74: 7894443800753 | D74: COR | E74: Rosa | F74: Tamanho | G74: 28 | H74: 500 | I74: 70 | J74: 0 | K74: 4 | L74: 40 | O74: 0 | P74: 44 seminova | Q74: https://images.tcdn.com.br/img/img_prod/995386/mini_melissa_street_minnie_255_variacao_501_2_2f4a181fdb28ab15626121339eaab628.jpg | R74: 25 | S74: 15 | T74: 10 | U74: https://images.tcdn.com.br/img/img_prod/995386/mini_melissa_street_minnie_255_variacao_501_2_2f4a181fdb28ab15626121339eaab628.jpg, https://images.tcdn.com.br/img/img_prod/995386/mini_melissa_street_minnie_255_variacao_501_3_ad3549005d63c6b4d9e4f1530f014f40.jpg, https://images.tcdn.com.br/img/img_prod/995386/mini_melissa_street_minnie_255_variacao_501_4_51fae94985ab8cbd38aebd03ea288e2d.jpg, https://images.tcdn.com.br/img/img_prod/995386/mini_melissa_street_minnie_255_variacao_501_5_658b289f49557b7d488cd43df0ac0501.jpg, https://images.tcdn.com.br/img/img_prod/995386/mini_melissa_street_minnie_255_variacao_501_6_0a92b0541213d88632383e29cc9dd1be.jpg
A75: 503 | B75: 255 | C75: 7894443800760 | D75: COR | E75: Rosa | F75: Tamanho | G75: 25 | H75: 100 | I75: 80 | J75: 0 | K75: 3 | L75: 134 | O75: 0 | P75: 6 usada | Q75: https://images.tcdn.com.br/img/img_prod/995386/mini_melissa_street_minnie_255_variacao_503_2_0ffad6f802c6248a39004135451958fd.jpg | R75: 25 | S75: 15 | T75: 10 | U75: https://images.tcdn.com.br/img/img_prod/995386/mini_melissa_street_minnie_255_variacao_503_2_0ffad6f802c6248a39004135451958fd.jpg, https://images.tcdn.com.br/img/img_prod/995386/mini_melissa_street_minnie_255_variacao_503_3_a7ae2116daa7b4de2cec4d87c467dfa0.jpg, https://images.tcdn.com.br/img/img_prod/995386/mini_melissa_street_minnie_255_variacao_503_4_119d39723bbfd0a3f4119742ad1bd820.jpg, https://images.tcdn.com.br/img/img_prod/995386/mini_melissa_street_minnie_255_variacao_503_5_f591d57a8b3611a06c288a9401b0003d.jpg, https://images.tcdn.com.br/img/img_prod/995386/mini_melissa_street_minnie_255_variacao_503_6_767162e92fefb2914d7d8c4f0b80d794.jpg
A76: 505 | B76: 255 | C76: 7894443800777 | D76: COR | E76: Rosa | F76: Tamanho | G76: 20/21 | H76: 500 | I76: 110 | J76: 0 | K76: 2 | L76: 60 | O76: 0 | P76: § | Q76: https://images.tcdn.com.br/img/img_prod/995386/mini_melissa_street_minnie_255_variacao_505_2_90ca9775353f14627e6fb7279f651de7.jpeg | R76: 25 | S76: 15 | T76: 10 | U76: https://images.tcdn.com.br/img/img_prod/995386/mini_melissa_street_minnie_255_variacao_505_2_90ca9775353f14627e6fb7279f651de7.jpeg, https://images.tcdn.com.br/img/img_prod/995386/mini_melissa_street_minnie_255_variacao_505_3_93caacadcf26c7985cb66c460dccfbe2.jpeg
A77: 507 | B77: 56 | C77: 7894443800784 | D77: COR | E77: Rosa Chiclete | F77: Tamanho | G77: 19 | I77: 80 | J77: 0 | K77: 2 | L77: 50 | O77: 0 | P77: § | Q77: https://images.tcdn.com.br/img/img_prod/995386/mini_melissa_rain_boot_56_variacao_507_2_87957b64d7b1e16d600955d2bd4d142c.jpeg | U77: https://images.tcdn.com.br/img/img_prod/995386/mini_melissa_rain_boot_56_variacao_507_2_87957b64d7b1e16d600955d2bd4d142c.jpeg, https://images.tcdn.com.br/img/img_prod/995386/mini_melissa_rain_boot_56_variacao_507_3_ccded4edcd3c20b450f7cf84218fc910.jpeg
A78: 511 | B78: 51 | C78: 7894443800791 | D78: COR | E78: Laranja | F78: Tamanho | G78: 19 | H78: 100 | I78: 60 | J78: 0 | K78: 1 | L78: 33.67 | O78: 0 | P78: § | Q78: https://images.tcdn.com.br/img/img_prod/995386/mini_melissa_sneaker_ulitsa_51_variacao_511_2_ffc8b53376c8b1bbc0a2642e3542246b.jpeg | R78: 25 | S78: 15 | T78: 10 | U78: https://images.tcdn.com.br/img/img_prod/995386/mini_melissa_sneaker_ulitsa_51_variacao_511_2_ffc8b53376c8b1bbc0a2642e3542246b.jpeg, https://images.tcdn.com.br/img/img_prod/995386/mini_melissa_sneaker_ulitsa_51_variacao_511_3_0a608a2e6e1f4038149f5f858257a274.jpeg, https://images.tcdn.com.br/img/img_prod/995386/mini_melissa_sneaker_ulitsa_51_variacao_511_4_565b1ec0b7f78db3c74580d5b6079c03.jpeg, https://images.tcdn.com.br/img/img_prod/995386/mini_melissa_sneaker_ulitsa_51_variacao_511_5_b568ab1f806a3b5ebac2ebd1e76d1be6.jpeg, https://images.tcdn.com.br/img/img_prod/995386/mini_melissa_sneaker_ulitsa_51_variacao_511_6_637b854d8f5c2ab3ee131cddd0ffa608.jpeg
A79: 535 | B79: 261 | C79: 7894443800807 | D79: COR | E79: Vermelho | F79: Tamanho | G79: 19 | H79: 500 | I79: 55 | J79: 0 | K79: 2 | L79: 37.33 | O79: 0 | P79: § | Q79: https://images.tcdn.com.br/img/img_prod/995386/mini_melissa_ultragirl_mickey_amp_minnie_mao_de_coracao_261_variacao_535_2_51bdae318ab3c835a96d8097d2c88f87.jpeg | R79: 25 | S79: 15 | T79: 10 | U79: https://images.tcdn.com.br/img/img_prod/995386/mini_melissa_ultragirl_mickey_amp_minnie_mao_de_coracao_261_variacao_535_2_51bdae318ab3c835a96d8097d2c88f87.jpeg, https://images.tcdn.com.br/img/img_prod/995386/mini_melissa_ultragirl_mickey_amp_minnie_mao_de_coracao_261_variacao_535_3_92e72db2f739fcf792345bfe950720b8.jpeg, https://images.tcdn.com.br/img/img_prod/995386/mini_melissa_ultragirl_mickey_amp_minnie_mao_de_coracao_261_variacao_535_4_b3bd4524681806f69852993e49f7a5e0.jpeg, https://images.tcdn.com.br/img/img_prod/995386/mini_melissa_ultragirl_mickey_amp_minnie_mao_de_coracao_261_variacao_535_5_d5f99be326d315014bf73b0feadd32e1.jpeg, https://images.tcdn.com.br/img/img_prod/995386/mini_melissa_ultragirl_mickey_amp_minnie_mao_de_coracao_261_variacao_535_6_9984cac035d1d022558e5bf026a45de9.jpeg
A80: 541 | B80: 233 | C80: 7894443800814 | D80: COR | E80: Dourado | F80: Tamanho | G80: 20/21 | I80: 40 | J80: 0 | K80: 1 | L80: 25 | O80: 0 | P80: *seminova | Q80: https://images.tcdn.com.br/img/img_prod/995386/mini_melissa_ultragirl_animal_lovers_gato_233_variacao_541_2_de9c95a886f4a75f697da4a220367c6a.jpg | U80: https://images.tcdn.com.br/img/img_prod/995386/mini_melissa_ultragirl_animal_lovers_gato_233_variacao_541_2_de9c95a886f4a75f697da4a220367c6a.jpg, https://images.tcdn.com.br/img/img_prod/995386/mini_melissa_ultragirl_animal_lovers_gato_233_variacao_541_3_578014a0176e61acb313510044aa58db.jpg, https://images.tcdn.com.br/img/img_prod/995386/mini_melissa_ultragirl_animal_lovers_gato_233_variacao_541_4_ddbd51c66f59fb3b3aa93812cf89ae81.jpg, https://images.tcdn.com.br/img/img_prod/995386/mini_melissa_ultragirl_animal_lovers_gato_233_variacao_541_5_ca66bb923e729296f387849f460946fb.jpg
A81: 543 | B81: 83 | C81: 7894443800821 | D81: COR | E81: Rosa Glitter | F81: Tamanho | G81: 19 | H81: 100 | I81: 50 | J81: 0 | K81: 1 | L81: 35 | O81: 0 | P81: 47 seminova | Q81: https://images.tcdn.com.br/img/img_prod/995386/mini_melissa_ultragirl_pequena_sereia_83_variacao_543_2_5da481de9531c835290cb94c87f0c520.jpg | R81: 25 | S81: 15 | T81: 10 | U81: https://images.tcdn.com.br/img/img_prod/995386/mini_melissa_ultragirl_pequena_sereia_83_variacao_543_2_5da481de9531c835290cb94c87f0c520.jpg, https://images.tcdn.com.br/img/img_prod/995386/mini_melissa_ultragirl_pequena_sereia_83_variacao_543_3_7cef5e429b01451b576a120ab8de0f89.jpg, https://images.tcdn.com.br/img/img_prod/995386/mini_melissa_ultragirl_pequena_sereia_83_variacao_543_4_1191c7f2708373ad968c67520a647b74.jpg, https://images.tcdn.com.br/img/img_prod/995386/mini_melissa_ultragirl_pequena_sereia_83_variacao_543_5_a8db5613e9b49fe2882a79f0ea11594d.jpg, https://images.tcdn.com.br/img/img_prod/995386/mini_melissa_ultragirl_pequena_sereia_83_variacao_543_6_d95cfc9ca4dbcc25b9da481b402e6af9.jpg, https://images.tcdn.com.br/img/img_prod/995386/mini_melissa_ultragirl_pequena_sereia_83_variacao_543_7_24a6ffb474bdad17b66ce12714bafecf.jpg
A82: 547 | B82: 72 | C82: 7894443800838 | D82: COR | E82: Preto | F82: Tamanho | G82: 23/24 | H82: 100 | I82: 50 | J82: 0 | K82: 4 | L82: 30 | O82: 0 | P82: § | Q82: https://images.tcdn.com.br/img/img_prod/995386/mini_melissa_possession_turma_do_pudim_72_variacao_547_3_7837ca2fc95db9f570e05387f1a2692f.jpg | R82: 25 | S82: 15 | T82: 10 | U82: https://images.tcdn.com.br/img/img_prod/995386/mini_melissa_possession_turma_do_pudim_72_variacao_547_3_7837ca2fc95db9f570e05387f1a2692f.jpg, https://images.tcdn.com.br/img/img_prod/995386/mini_melissa_possession_turma_do_pudim_72_variacao_547_4_61dafec81435ebf5f4d30ddde54b75a3.jpg, https://images.tcdn.com.br/img/img_prod/995386/mini_melissa_possession_turma_do_pudim_72_variacao_547_5_3ab6b4fa3776bebbdb31c6b77f2f1dca.jpg, https://images.tcdn.com.br/img/img_prod/995386/mini_melissa_possession_turma_do_pudim_72_variacao_547_6_ccf5353eaaf63a2b1d88268ad32d81c7.jpg
A83: 551 | B83: 263 | C83: 7894443800845 | D83: COR | E83: Vidro | F83: Tamanho | G83: 25 | H83: 100 | I83: 60 | J83: 0 | K83: 9 | L83: 40 | O83: 0 | P83: 48 usada | Q83: https://images.tcdn.com.br/img/img_prod/995386/mini_melissa_sneaker_polibolha_turma_do_pudim_263_variacao_551_2_8d6d3e8d92dbfdfca5500463d5f3009d.jpg | R83: 25 | S83: 15 | T83: 10 | U83: https://images.tcdn.com.br/img/img_prod/995386/mini_melissa_sneaker_polibolha_turma_do_pudim_263_variacao_551_2_8d6d3e8d92dbfdfca5500463d5f3009d.jpg, https://images.tcdn.com.br/img/img_prod/995386/mini_melissa_sneaker_polibolha_turma_do_pudim_263_variacao_551_3_9f8c21694c1d860cd8fe9b22bc557194.jpg, https://images.tcdn.com.br/img/img_prod/995386/mini_melissa_sneaker_polibolha_turma_do_pudim_263_variacao_551_4_ed7935490d6703f3cf32fe8ac6788d9c.jpg, https://images.tcdn.com.br/img/img_prod/995386/mini_melissa_sneaker_polibolha_turma_do_pudim_263_variacao_551_5_b252c6f746777710aba8fab04bb1c6da.jpg, https://images.tcdn.com.br/img/img_prod/995386/mini_melissa_sneaker_polibolha_turma_do_pudim_263_variacao_551_6_3c60b8f41c99e9027fe38fd2858362da.jpg
A84: 565 | B84: 87 | C84: 7894443800852 | D84: COR | E84: Colorido Glitter | F84: Tamanho | G84: 23/24 | H84: 100 | I84: 55 | J84: 0 | K84: 5 | L84: 45 | O84: 0 | P84: 6 seminova | Q84: https://images.tcdn.com.br/img/img_prod/995386/mini_melissa_possession_87_variacao_565_3_0617d451855397437e24a4d0e15e8138.jpg | R84: 25 | S84: 15 | T84: 10 | U84: https://images.tcdn.com.br/img/img_prod/995386/mini_melissa_possession_87_variacao_565_3_0617d451855397437e24a4d0e15e8138.jpg, https://images.tcdn.com.br/img/img_prod/995386/mini_melissa_possession_87_variacao_565_4_84eaf06a65b9edd8ba708f4aeb8f06e9.jpg, https://images.tcdn.com.br/img/img_prod/995386/mini_melissa_possession_87_variacao_565_5_34d0a63a8bcdec8cb3cfd29efc833b32.jpg, https://images.tcdn.com.br/img/img_prod/995386/mini_melissa_possession_87_variacao_565_6_04b21a113297c2752bef82fe5fccecb5.jpg
A85: 575 | B85: 189 | C85: 7894443800869 | D85: COR | E85: Rosa | F85: Tamanho | G85: 23/24 | I85: 50 | J85: 0 | K85: 4 | L85: 35 | O85: 0 | P85: § | Q85: https://images.tcdn.com.br/img/img_prod/995386/mini_melissa_mar_sandal_189_variacao_575_2_277507afc5405e3c86ee6affc081470b.jpg | U85: https://images.tcdn.com.br/img/img_prod/995386/mini_melissa_mar_sandal_189_variacao_575_2_277507afc5405e3c86ee6affc081470b.jpg, https://images.tcdn.com.br/img/img_prod/995386/mini_melissa_mar_sandal_189_variacao_575_3_6bcc3d519895de4cc7ed72eb411edbbe.jpeg, https://images.tcdn.com.br/img/img_prod/995386/mini_melissa_mar_sandal_189_variacao_575_4_0844049483658a88fd5470c7127acf5d.jpeg, https://images.tcdn.com.br/img/img_prod/995386/mini_melissa_mar_sandal_189_variacao_575_5_6baeb287e8e624fc0af61278ebb7d264.jpeg, https://images.tcdn.com.br/img/img_prod/995386/mini_melissa_mar_sandal_189_variacao_575_6_fd6a3d00712d979b9409bb3d0e1c7009.jpg, https://images.tcdn.com.br/img/img_prod/995386/mini_melissa_mar_sandal_189_variacao_575_7_09a6395bdaec49f5153a086992b6b688.jpg
A86: 595 | B86: 213 | C86: 7894443800876 | D86: COR | E86: Rosa Chiclete | F86: Tamanho | G86: 23/24 | I86: 55 | J86: 0 | K86: 1 | L86: 35 | O86: 0 | P86: § | Q86: https://images.tcdn.com.br/img/img_prod/995386/mini_melissa_ultragirl_x_213_variacao_595_2_af98b2543bd235043c4e35a7eb39e1e9.jpeg | U86: https://images.tcdn.com.br/img/img_prod/995386/mini_melissa_ultragirl_x_213_variacao_595_2_af98b2543bd235043c4e35a7eb39e1e9.jpeg, https://images.tcdn.com.br/img/img_prod/995386/mini_melissa_ultragirl_x_213_variacao_595_3_a26e34a48a705105322eefa530541f96.jpg
A87: 605 | B87: 124 | C87: 7894443800883 | D87: COR | E87: Prata | F87: Tamanho | G87: 23/24 | I87: 50 | J87: 0 | K87: 7 | L87: 30 | M87: 44643 | N87: 44651 | O87: 40 | P87: 12 usada | Q87: https://images.tcdn.com.br/img/img_prod/995386/mini_melissa_cosmic_sandal_124_variacao_605_2_5df4c3b16432d77ab90ccfbd0fb231ed.jpeg | U87: https://images.tcdn.com.br/img/img_prod/995386/mini_melissa_cosmic_sandal_124_variacao_605_2_5df4c3b16432d77ab90ccfbd0fb231ed.jpeg, https://images.tcdn.com.br/img/img_prod/995386/mini_melissa_cosmic_sandal_124_variacao_605_3_17f7e7dac141a53737b9fad307c55a11.jpeg, https://images.tcdn.com.br/img/img_prod/995386/mini_melissa_cosmic_sandal_124_variacao_605_4_32061e7934d20de869cd78656fa57a17.jpeg, https://images.tcdn.com.br/img/img_prod/995386/mini_melissa_cosmic_sandal_124_variacao_605_5_3e1cbd3f0150da211e558b1feb5cc8c6.jpeg, https://images.tcdn.com.br/img/img_prod/995386/mini_melissa_cosmic_sandal_124_variacao_605_6_00c2fdfbe924bc6986ba5b528860381f.jpeg
A88: 607 | B88: 155 | C88: 7894443800890 | D88: COR | E88: Amarelo | F88: Tamanho | G88: 23/24 | H88: 100 | I88: 60 | J88: 0 | K88: 5 | L88: 40 | O88: 0 | P88: 29 usada | Q88: https://images.tcdn.com.br/img/img_prod/995386/mini_melissa_jump_sunny_day_155_variacao_607_2_99ce12763c13613adf0ab0138dc8e5a5.jpg | R88: 25 | S88: 15 | T88: 10 | U88: https://images.tcdn.com.br/img/img_prod/995386/mini_melissa_jump_sunny_day_155_variacao_607_2_99ce12763c13613adf0ab0138dc8e5a5.jpg, https://images.tcdn.com.br/img/img_prod/995386/mini_melissa_jump_sunny_day_155_variacao_607_3_61d166212e35c02aa832875929b5ed7e.jpg, https://images.tcdn.com.br/img/img_prod/995386/mini_melissa_jump_sunny_day_155_variacao_607_4_c82a4d1074abf65dde2375202fe347e5.jpg, https://images.tcdn.com.br/img/img_prod/995386/mini_melissa_jump_sunny_day_155_variacao_607_5_d15cd0fa5c9792b949465c09cd998346.jpg, https://images.tcdn.com.br/img/img_prod/995386/mini_melissa_jump_sunny_day_155_variacao_607_6_e3b67c59d0670b887121e714bbfd488e.jpg
A89: 609 | B89: 251 | C89: 7894443800906 | D89: COR | E89: Rosa | F89: Tamanho | G89: 22 | I89: 100 | J89: 0 | K89: 3 | L89: 90 | O89: 0 | P89: § | Q89: https://images.tcdn.com.br/img/img_prod/995386/mini_melissa_sneaker_polibolha_dino_251_variacao_609_2_3c637c95933c959f6b241c9808da33bc.jpeg | U89: https://images.tcdn.com.br/img/img_prod/995386/mini_melissa_sneaker_polibolha_dino_251_variacao_609_2_3c637c95933c959f6b241c9808da33bc.jpeg, https://images.tcdn.com.br/img/img_prod/995386/mini_melissa_sneaker_polibolha_dino_251_variacao_609_3_c3ef31e29eae4d2c51c67f1a682efb62.jpeg, https://images.tcdn.com.br/img/img_prod/995386/mini_melissa_sneaker_polibolha_dino_251_variacao_609_4_c04efb42346d0e80d4258311e22c8e15.jpeg, https://images.tcdn.com.br/img/img_prod/995386/mini_melissa_sneaker_polibolha_dino_251_variacao_609_5_55a3a1e8570d45b21ac40c8a37a4ec58.jpeg
A90: 619 | B90: 125 | C90: 7894443800913 | D90: COR | E90: Preto | F90: Tamanho | G90: 22 | I90: 60 | J90: 0 | K90: 4 | L90: 50 | O90: 0 | P90: 36 usada | Q90: https://images.tcdn.com.br/img/img_prod/995386/mini_melissa_papete_rider_125_variacao_619_4_0668f2bad964cc5847548f9225b20c72.jpg | U90: https://images.tcdn.com.br/img/img_prod/995386/mini_melissa_papete_rider_125_variacao_619_4_0668f2bad964cc5847548f9225b20c72.jpg, https://images.tcdn.com.br/img/img_prod/995386/mini_melissa_papete_rider_125_variacao_619_5_d6efbc709ee35fc7d98bead0c7ec8ba3.jpg, https://images.tcdn.com.br/img/img_prod/995386/mini_melissa_papete_rider_125_variacao_619_6_f62d423c9a8210cac9f99d7e4a457c56.jpg
A91: 621 | B91: 126 | C91: 7894443800920 | D91: COR | E91: Rosa Choque | F91: Tamanho | G91: 22 | I91: 55 | J91: 0 | K91: 2 | L91: 35 | O91: 0 | P91: § | Q91: https://images.tcdn.com.br/img/img_prod/995386/mini_melissa_possession_estrela_126_variacao_621_2_3366440552ee572880d4046488c43c89.jpeg | U91: https://images.tcdn.com.br/img/img_prod/995386/mini_melissa_possession_estrela_126_variacao_621_2_3366440552ee572880d4046488c43c89.jpeg, https://images.tcdn.com.br/img/img_prod/995386/mini_melissa_possession_estrela_126_variacao_621_3_9d76f7c5a89d76926474fc58a2ddd702.jpeg, https://images.tcdn.com.br/img/img_prod/995386/mini_melissa_possession_estrela_126_variacao_621_4_970c4b7113cf91200245636ea9af7488.jpeg, https://images.tcdn.com.br/img/img_prod/995386/mini_melissa_possession_estrela_126_variacao_621_5_a45ebac0c6e08819907c953ddf7cdbe7.jpeg, https://images.tcdn.com.br/img/img_prod/995386/mini_melissa_possession_estrela_126_variacao_621_6_073518912c90fbda1652f7c293858366.jpeg
A92: 627 | B92: 255 | C92: 7894443800937 | D92: COR | E92: Rosa | F92: Tamanho | G92: 22 | I92: 80 | J92: 0 | K92: 3 | L92: 134 | O92: 0 | P92: § | Q92: https://images.tcdn.com.br/img/img_prod/995386/mini_melissa_street_minnie_255_variacao_627_2_9a3af60f10532b6dff1c49ae710ff280.jpg | U92: https://images.tcdn.com.br/img/img_prod/995386/mini_melissa_street_minnie_255_variacao_627_2_9a3af60f10532b6dff1c49ae710ff280.jpg, https://images.tcdn.com.br/img/img_prod/995386/mini_melissa_street_minnie_255_variacao_627_3_7fb7cdf454e99ec62cc7168c482464ae.jpg, https://images.tcdn.com.br/img/img_prod/995386/mini_melissa_street_minnie_255_variacao_627_4_9347a1e436b20039668f7156eed2f4a5.jpg, https://images.tcdn.com.br/img/img_prod/995386/mini_melissa_street_minnie_255_variacao_627_5_c2f0f6f1e54622b315d6598e56b94f1b.jpg, https://images.tcdn.com.br/img/img_prod/995386/mini_melissa_street_minnie_255_variacao_627_6_aaf2e0d4256c7a73a79046dc4e7efa9d.jpg
A93: 629 | B93: 275 | C93: 7894443800944 | D93: COR | E93: Preto | F93: Tamanho | G93: 26/27 | H93: 100 | I93: 68 | J93: 0 | K93: 3 | L93: 40 | O93: 0 | P93: § | Q93: https://images.tcdn.com.br/img/img_prod/995386/mini_melissa_m40_com_pochete_275_variacao_629_2_e96031851dd0e6925b2c9955dff6fbe7.jpeg | R93: 25 | S93: 15 | T93: 10 | U93: https://images.tcdn.com.br/img/img_prod/995386/mini_melissa_m40_com_pochete_275_variacao_629_2_e96031851dd0e6925b2c9955dff6fbe7.jpeg, https://images.tcdn.com.br/img/img_prod/995386/mini_melissa_m40_com_pochete_275_variacao_629_3_7515a7500891d6d11fb9d4ccce8179c3.jpeg, https://images.tcdn.com.br/img/img_prod/995386/mini_melissa_m40_com_pochete_275_variacao_629_4_5b4a8a0bbf4bfa4a3e66b2137fb17b5b.jpeg, https://images.tcdn.com.br/img/img_prod/995386/mini_melissa_m40_com_pochete_275_variacao_629_5_b2d5f8a1d90c33a8a7b0348968dc0f87.jpeg, https://images.tcdn.com.br/img/img_prod/995386/mini_melissa_m40_com_pochete_275_variacao_629_6_d06f03d6b2a1230693551de2b5193570.jpeg
A94: 639 | B94: 139 | C94: 7894443800951 | D94: COR | E94: marrom | F94: Tamanho | G94: 22 | H94: 100 | I94: 65 | J94: 0 | K94: 3 | L94: 40 | O94: 0 | P94: § | Q94: https://images.tcdn.com.br/img/img_prod/995386/mini_melissa_maggie_bear_139_variacao_639_2_4c9ecd1a440621ed6a22ee7a5b29356a.jpeg | R94: 25 | S94: 15 | T94: 10 | U94: https://images.tcdn.com.br/img/img_prod/995386/mini_melissa_maggie_bear_139_variacao_639_2_4c9ecd1a440621ed6a22ee7a5b29356a.jpeg, https://images.tcdn.com.br/img/img_prod/995386/mini_melissa_maggie_bear_139_variacao_639_3_be0223e7bb62da70a7a985eeda31bf6b.jpeg, https://images.tcdn.com.br/img/img_prod/995386/mini_melissa_maggie_bear_139_variacao_639_4_e2f75eef8cbef4a5b9f67fc682dd15d9.jpeg
A95: 641 | B95: 277 | C95: 7894443800968 | D95: COR | E95: Preto | F95: Tamanho | G95: 22 | I95: 55 | J95: 0 | K95: 0 | L95: 35 | O95: 0 | P95: § | Q95: https://images.tcdn.com.br/img/img_prod/995386/mini_melissa_furadinha_babouche_foguete_277_variacao_641_2_c2e4713ac89670a8555b5632605fa52f.png | U95: https://images.tcdn.com.br/img/img_prod/995386/mini_melissa_furadinha_babouche_foguete_277_variacao_641_2_c2e4713ac89670a8555b5632605fa52f.png
A96: 647 | B96: 127 | C96: 7894443800975 | D96: COR | E96: Verde | F96: Tamanho | G96: 20/21 | H96: 100 | I96: 50 | J96: 0 | K96: 5 | L96: 35 | O96: 0 | P96: § | Q96: https://images.tcdn.com.br/img/img_prod/995386/mini_melissa_ultragirl_baby_shark_127_variacao_647_2_70555c329da8c7b8ba88276912f357c8.jpeg | R96: 25 | S96: 15 | T96: 10 | U96: https://images.tcdn.com.br/img/img_prod/995386/mini_melissa_ultragirl_baby_shark_127_variacao_647_2_70555c329da8c7b8ba88276912f357c8.jpeg, https://images.tcdn.com.br/img/img_prod/995386/mini_melissa_ultragirl_baby_shark_127_variacao_647_3_e2bdde1adcd53a30f68870bfb9ef2389.jpeg, https://images.tcdn.com.br/img/img_prod/995386/mini_melissa_ultragirl_baby_shark_127_variacao_647_4_aaabd7454e5ab5a53d059e2c58973e40.jpeg, https://images.tcdn.com.br/img/img_prod/995386/mini_melissa_ultragirl_baby_shark_127_variacao_647_5_8baa75787d2a3d631291622bc6a8a49d.jpeg
A97: 651 | B97: 149 | C97: 7894443800982 | D97: COR | E97: Vermelho | F97: Tamanho | G97: 22 | I97: 45 | J97: 0 | K97: 3 | L97: 25 | O97: 0 | P97: § | Q97: https://images.tcdn.com.br/img/img_prod/995386/mini_melissa_furadinha_fabula_149_variacao_651_2_9f2755e0646fde4c58028acabdafc95e.jpeg | U97: https://images.tcdn.com.br/img/img_prod/995386/mini_melissa_furadinha_fabula_149_variacao_651_2_9f2755e0646fde4c58028acabdafc95e.jpeg, https://images.tcdn.com.br/img/img_prod/995386/mini_melissa_furadinha_fabula_149_variacao_651_3_a5dcf6eb53e8a01493667b8c305d5af0.jpeg, https://images.tcdn.com.br/img/img_prod/995386/mini_melissa_furadinha_fabula_149_variacao_651_4_64300b7d81d80865c2854bcf005c4d27.jpeg, https://images.tcdn.com.br/img/img_prod/995386/mini_melissa_furadinha_fabula_149_variacao_651_5_bcc7f3880d71f26773d6b49c6cc3451b.jpeg, https://images.tcdn.com.br/img/img_prod/995386/mini_melissa_furadinha_fabula_149_variacao_651_6_74d92b76b8250dae341536ce4fd7e09c.jpeg
A98: 655 | B98: 87 | C98: 7894443800999 | D98: COR | E98: Azul | F98: Tamanho | G98: 22 | H98: 100 | I98: 55 | J98: 0 | K98: 6 | L98: 30.15 | O98: 0 | P98: § | Q98: https://images.tcdn.com.br/img/img_prod/995386/mini_melissa_possession_87_variacao_655_3_ff1ef3de4577c6f4372f4d1e8c1e17e9.jpeg | R98: 25 | S98: 15 | T98: 10 | U98: https://images.tcdn.com.br/img/img_prod/995386/mini_melissa_possession_87_variacao_655_3_ff1ef3de4577c6f4372f4d1e8c1e17e9.jpeg, https://images.tcdn.com.br/img/img_prod/995386/mini_melissa_possession_87_variacao_655_4_ba7b5774b1a123654cf501b83339387d.jpeg, https://images.tcdn.com.br/img/img_prod/995386/mini_melissa_possession_87_variacao_655_5_7320923200d8f6651882df72239f48e1.jpeg, https://images.tcdn.com.br/img/img_prod/995386/mini_melissa_possession_87_variacao_655_6_18a4d5917ac3a105c0a9782fa640a801.jpeg
A99: 661 | B99: 279 | C99: 7894443801002 | D99: COR | E99: Preto | F99: Tamanho | G99: 22 | I99: 55 | J99: 0 | K99: 2 | L99: 0 | O99: 0 | P99: § | Q99: https://images.tcdn.com.br/img/img_prod/995386/mini_melissa_ultragirl_gatinho_279_variacao_661_2_862feb00f368821ee303ee804f9fa128.jpeg | U99: https://images.tcdn.com.br/img/img_prod/995386/mini_melissa_ultragirl_gatinho_279_variacao_661_2_862feb00f368821ee303ee804f9fa128.jpeg, https://images.tcdn.com.br/img/img_prod/995386/mini_melissa_ultragirl_gatinho_279_variacao_661_3_4f7fe1acd3cf8b991f44d51210422e40.jpeg, https://images.tcdn.com.br/img/img_prod/995386/mini_melissa_ultragirl_gatinho_279_variacao_661_4_8b5256a713c53547db22881624e14326.jpeg, https://images.tcdn.com.br/img/img_prod/995386/mini_melissa_ultragirl_gatinho_279_variacao_661_5_48c695225814a4238f79fc457e0e7ed2.jpeg, https://images.tcdn.com.br/img/img_prod/995386/mini_melissa_ultragirl_gatinho_279_variacao_661_6_be899dbbffd794d17c1b2e2c2b756196.jpeg
A100: 673 | B100: 283 | C100: 7894443801019 | D100: COR | E100: Laranja | F100: Tamanho | G100: 17/18 | I100: 50 | J100: 0 | K100: 4 | L100: 25 | O100: 0 | P100: 51 usada | Q100: https://images.tcdn.com.br/img/img_prod/995386/mini_melissa_mia_fabula_283_variacao_673_2_789831a919fae8310c670346c0d4a039.jpeg | U100: https://images.tcdn.com.br/img/img_prod/995386/mini_melissa_mia_fabula_283_variacao_673_2_789831a919fae8310c670346c0d4a039.jpeg, https://images.tcdn.com.br/img/img_prod/995386/mini_melissa_mia_fabula_283_variacao_673_3_8b91b41c79c6a710c354ad0536bebbb9.jpeg, https://images.tcdn.com.br/img/img_prod/995386/mini_melissa_mia_fabula_283_variacao_673_4_567682918a8539f4b941300462962668.jpeg, https://images.tcdn.com.br/img/img_prod/995386/mini_melissa_mia_fabula_283_variacao_673_5_50efe5eb8b78c64f3713d73a2d64314b.jpeg, https://images.tcdn.com.br/img/img_prod/995386/mini_melissa_mia_fabula_283_variacao_673_6_3b3ce6b8e8993e515bdf39c9b02a907a.jpg
...

Sheet Produtos
B1: Código loja | C1: Código categoria | D1: Data cadastro | E1: Nome produto | F1: Código produto | G1: Imagem principal | H1: Imagem 2 | I1: Imagem 3 | J1: Imagem 4 | K1: Preço venda | L1: Peso | M1: Frete | N1: Estoque atual | O1: Estoque mínimo | P1: Disponível | Q1: Inicio promoção | R1: Fim promoção | S1: Preço promoção | T1: Selo destaque | U1: Selo lançamento | V1: Selo adicional | W1: Quantidade vendida | X1: Marca | Y1: Modelo | Z1: Referência | AA1: EAN | AB1: Garantia | AC1: Tamanho | AD1: Cor | AE1: Preço de custo | AF1: Preço de custo em dólar | AG1: Disponibilidade | AH1: Itens inclusos | AI1: Mensagem adicional | AJ1: Comprimento | AK1: Largura | AL1: Altura | AM1: Data de ativação | AN1: Data de desativação | AO1: SEO Título | AP1: SEO descrição simplificada | AQ1: SEO palavra chave | AR1: Características | AS1: Endereço do Produto (URL Tray) | AT1: Imagens adicionais | AU1: Nome categoria
B2: 995386 | C2: 161 | D2: 44502 | E2: Mini Melissa Aranha Minnie | F2: 21 | G2: https://images.tcdn.com.br/img/img_prod/995386/mini_melissa_aranha_minnie_21_1_55ce6e102664f8e1284917e27e071023.jpeg | H2: https://images.tcdn.com.br/img/img_prod/995386/mini_melissa_aranha_minnie_21_2_48aa7c1f52c28c25734077cd130b3deb.jpg | I2: https://images.tcdn.com.br/img/img_prod/995386/mini_melissa_aranha_minnie_21_3_1680907f4c52ef26163a7003238e5e1b.jpg | K2: 0.00 | L2: 100 | M2: 0.00 | N2: -1 | O2: 0 | P2: Não | S2: 0.00 | T2: Não | U2: Não | V2: Não | W2: 7 | X2: Melissa | Y2: ARANHA | Z2: V21P104 | AA2: 21 | AB2: 7 dias após o recebimento do produto | AE2: 0.00 | AF2: 0.00 | AG2: Imediata | AJ2: 25 | AK2: 15 | AL2: 10 | AM2: 45201 | AN2: 45205 | AP2: Melissas novas, seminovas e usadas. Em ótimas condições de conservação. Todas higienizadas.Moda circular sustentável!Porque uma melissa bem cuidada é para sempre!? | AS2: https://www.minhamania.net/mini-melissa-aranha-minnie | AU2: Infantil
B3: 995386 | C3: 161 | D3: 44310 | E3: My First Mini Melissa Tricot | F3: 37 | G3: https://images.tcdn.com.br/img/img_prod/995386/my_first_mini_melissa_tricot_37_2_f6400ccfc718e2a01776ad5a31dba06f.jpeg | H3: https://images.tcdn.com.br/img/img_prod/995386/my_first_mini_melissa_tricot_37_2_20046460b02dc4e6c316db6b87a51b3c.jpeg | I3: https://images.tcdn.com.br/img/img_prod/995386/my_first_mini_melissa_tricot_37_1_219c3c171b931444319cb9ddf4124758.jpeg | K3: 65.00 | L3: 83 | M3: 0.00 | N3: 0 | O3: 0 | P3: Não | S3: 0.00 | T3: Não | U3: Não | V3: Não | W3: 7 | X3: Melissa | Y3: MY FIRST | AA3: 37 | AB3: 7 dias após o recebimento do produto | AE3: 45.00 | AF3: 0.00 | AG3: Imediata | AJ3: 10 | AK3: 5 | AL3: 3 | AM3: 44695 | AN3: 44902 | AP3: Melissas novas, seminovas e usadas. Em ótimas condições de conservação. Todas higienizadas.Moda circular sustentável!Porque uma melissa bem cuidada é para sempre!? | AS3: https://www.minhamania.net/mini-melissa/the-first-minha-primeira-melissa-tricot | AU3: Infantil
B4: 995386 | C4: 161 | D4: 44311 | E4: Galocha Mini Melissa Sugar Rain Fabula | F4: 39 | G4: https://images.tcdn.com.br/img/img_prod/995386/galocha_mini_melissa_sugar_rain_fabula_39_1_e95fd447cdd4fc6ef05167d635ac0b2e.png | K4: 50.00 | L4: 500 | M4: 0.00 | N4: 0 | O4: 0 | P4: Não | S4: 0.00 | T4: Não | U4: Não | V4: Não | W4: 2 | X4: Melissa | Z4: P39 | AA4: 39 | AB4: 7 dias após o recebimento do produto | AE4: 50.00 | AF4: 0.00 | AG4: Imediata | AJ4: 15 | AK4: 10 | AL4: 8 | AM4: 44618 | AN4: 44618 | AP4: Melissas novas, seminovas e usadas. Em ótimas condições de conservação. Todas higienizadas.Moda circular sustentável!Porque uma melissa bem cuidada é para sempre!? | AS4: https://www.minhamania.net/mini-melissa/galocha-mini-melissa-sugar-rain-fabula | AU4: Infantil
B5: 995386 | C5: 161 | D5: 44311 | E5: Mini Melissa Furadinha Babouche | F5: 41 | G5: https://images.tcdn.com.br/img/img_prod/995386/mini_melissa_furadinha_babouche_41_1_9a0685cdfaff42b43393106861b15cb8.jpeg | H5: https://images.tcdn.com.br/img/img_prod/995386/mini_melissa_furadinha_babouche_41_2_db44246f1d529264a804c205f9a502f0.jpeg | I5: https://images.tcdn.com.br/img/img_prod/995386/mini_melissa_furadinha_babouche_41_3_dbe01477538dd92f7f63f5967159d186.jpeg | K5: 55.00 | L5: 500 | M5: 0.00 | N5: 0 | O5: 0 | P5: Não | S5: 0.00 | T5: Não | U5: Não | V5: Não | W5: 25 | X5: Melissa | Y5: BABOUCHE | Z5: P41 | AA5: 41 | AE5: 0.00 | AF5: 0.00 | AJ5: 0 | AK5: 0 | AL5: 0 | AM5: 44850 | AN5: 44887 | AP5: Melissas novas, seminovas e usadas. Em ótimas condições de conservação. Todas higienizadas.Moda circular sustentável!Porque uma melissa bem cuidada é para sempre!? | AS5: https://www.minhamania.net/mini-melissa/mini-melissa-furadinha-babouche | AU5: Infantil
B6: 995386 | C6: 161 | D6: 44311 | E6: Mini Melissa Aranha + Fabula | F6: 43 | G6: https://images.tcdn.com.br/img/img_prod/995386/mini_melissa_aranha_fabula_43_1_e13b4cd0ec9fb053f93bfef668661a68.jpeg | K6: 45.00 | L6: 500 | M6: 0.00 | N6: 0 | O6: 0 | P6: Não | S6: 0.00 | T6: Não | U6: Não | V6: Não | W6: 2 | X6: Melissa | Z6: V43P37 | AA6: 43 | AB6: 7 dias após o recebimento do produto | AE6: 0.00 | AF6: 0.00 | AG6: Imediata | AJ6: 25 | AK6: 15 | AL6: 10 | AM6: 44727 | AN6: 44900 | AP6: Melissas novas, seminovas e usadas. Em ótimas condições de conservação. Todas higienizadas.Moda circular sustentável!Porque uma melissa bem cuidada é para sempre!? | AS6: https://www.minhamania.net/mini-melissa/mini-melissa-aranha-fabula | AU6: Infantil
B7: 995386 | C7: 161 | D7: 44316 | E7: Mini Melissa Furadinha Frutas | F7: 47 | G7: https://images.tcdn.com.br/img/img_prod/995386/mini_melissa_furadinha_frutas_47_1_1dca43ce9a507d4c1fee1cc570f1a4cc.jpeg | H7: https://images.tcdn.com.br/img/img_prod/995386/mini_melissa_furadinha_frutas_47_1_b168026b5d0e04f36f58e0f02fa70a5c.jpeg | I7: https://images.tcdn.com.br/img/img_prod/995386/mini_melissa_furadinha_frutas_47_2_701380c25c0d8f02b02f094e194df760.jpeg | J7: https://images.tcdn.com.br/img/img_prod/995386/mini_melissa_furadinha_frutas_47_5_dc28e296e8155415f04dc2e1d1b2dc2e.jpeg | K7: 40.00 | L7: 500 | M7: 0.00 | N7: 0 | O7: 0 | P7: Não | S7: 0.00 | T7: Não | U7: Não | V7: Não | W7: 17 | X7: Melissa | Z7: P47 | AA7: 47 | AE7: 29.77 | AF7: 0.00 | AG7: Imediata | AJ7: 20 | AK7: 15 | AL7: 10 | AM7: 45159 | AN7: 45355 | AP7: Melissas novas, seminovas e usadas. Em ótimas condições de conservação. Todas higienizadas.Moda circular sustentável!Porque uma melissa bem cuidada é para sempre!? | AS7: https://www.minhamania.net/mini-melissa/mini-melissa-furadinha-cereja | AT7: https://images.tcdn.com.br/img/img_prod/995386/mini_melissa_furadinha_frutas_47_5_0eb12176f57643579a0fac59c0bfa254.jpg, https://images.tcdn.com.br/img/img_prod/995386/mini_melissa_furadinha_frutas_47_6_611036c36dde990f73879a93084e9636.jpg | AU7: Infantil
B8: 995386 | C8: 161 | D8: 44316 | E8: Mini Melissa Sneaker Ulitsa | F8: 51 | G8: https://images.tcdn.com.br/img/img_prod/995386/mini_melissa_sneaker_ulitsa_51_1_5e5f7609830a0799200b29b8bf3ff639.jpeg | H8: https://images.tcdn.com.br/img/img_prod/995386/mini_melissa_sneaker_ulitsa_51_2_9bddb004e771ff5a8f461747956cc594.jpeg | I8: https://images.tcdn.com.br/img/img_prod/995386/mini_melissa_sneaker_ulitsa_51_4_ffc8b53376c8b1bbc0a2642e3542246b.jpeg | J8: https://images.tcdn.com.br/img/img_prod/995386/mini_melissa_sneaker_ulitsa_51_4_42b10670ae1aef66a526d131101386fc.jpg | K8: 65.00 | L8: 500 | M8: 0.00 | N8: 0 | O8: 0 | P8: Não | S8: 0.00 | T8: Não | U8: Não | V8: Não | W8: 72 | X8: Melissa | Y8: ULITSA | Z8: P51 | AA8: 51 | AB8: 7 dias após o recebimento do produto | AE8: 33.67 | AF8: 0.00 | AG8: Imediata | AJ8: 20 | AK8: 15 | AL8: 10 | AM8: 45322 | AN8: 45411 | AP8: Melissas novas, seminovas e usadas. Em ótimas condições de conservação. Todas higienizadas.Moda circular sustentável!Porque uma melissa bem cuidada é para sempre!? | AS8: https://www.minhamania.net/mini-melissa/mini-melissa-sneaker-ulitsa | AT8: https://images.tcdn.com.br/img/img_prod/995386/mini_melissa_sneaker_ulitsa_51_5_48c06e8e2d4daa3c6722be83110b6e80.jpg | AU8: Infantil
B9: 995386 | C9: 161 | D9: 44316 | E9: Melissa Mel Sneaker Ulitsa | F9: 52 | G9: https://images.tcdn.com.br/img/img_prod/995386/melissa_mel_sneaker_ulitsa_52_4_af8a092531e98f4cfdaea3146d0220d2.jpeg | H9: https://images.tcdn.com.br/img/img_prod/995386/melissa_mel_sneaker_ulitsa_52_2_8e36ad665727bcb293e9052230180248.jpg | I9: https://images.tcdn.com.br/img/img_prod/995386/melissa_mel_sneaker_ulitsa_52_1_bf3981daa91a6fc7c00aefe446de3aa7.png | J9: https://images.tcdn.com.br/img/img_prod/995386/melissa_mel_sneaker_ulitsa_52_4_0094154ef977e93aafa6fbbc61d68f48.jpg | K9: 65.00 | L9: 500 | M9: 0.00 | N9: 0 | O9: 0 | P9: Não | S9: 0.00 | T9: Não | U9: Não | V9: Não | W9: 37 | X9: Melissa | Y9: ULITSA | Z9: P52 | AA9: 52 | AB9: 7 dias após o recebimento do produto | AE9: 43.13 | AF9: 0.00 | AG9: Imediata | AJ9: 20 | AK9: 15 | AL9: 10 | AM9: 45456 | AN9: 45456 | AP9: Melissas novas, seminovas e usadas. Em ótimas condições de conservação. Todas higienizadas.Moda circular sustentável!Porque uma melissa bem cuidada é para sempre!? | AS9: https://www.minhamania.net/mini-melissa/mini-melissa-aranha-fabula- | AT9: https://images.tcdn.com.br/img/img_prod/995386/melissa_mel_sneaker_ulitsa_52_5_bcfb793bc015f03252fb8482710732f0.jpg, https://images.tcdn.com.br/img/img_prod/995386/melissa_mel_sneaker_ulitsa_52_6_1ffe214b439157f1eb81f98afd521d98.jpg, https://images.tcdn.com.br/img/img_prod/995386/melissa_mel_sneaker_ulitsa_52_7_3cf42c6d9e049055ddad630ceb065809.jpg | AU9: Infantil
B10: 995386 | C10: 161 | D10: 44316 | E10: Mini Melissa Campana Zig Zag | F10: 53 | G10: https://images.tcdn.com.br/img/img_prod/995386/mini_melissa_campana_zig_zag_53_1_b28b67cc661ea286195852b9e2bbf1f3.jpeg | H10: https://images.tcdn.com.br/img/img_prod/995386/mini_melissa_campana_zig_zag_53_5_19df4c1eef4deebad31a921b0130157a.jpg | I10: https://images.tcdn.com.br/img/img_prod/995386/mini_melissa_campana_zig_zag_53_4_a4240f3bebe37d95db3c608fcd7456cb.jpg | J10: https://images.tcdn.com.br/img/img_prod/995386/mini_melissa_campana_zig_zag_53_5_ed82bcd3329fd43863f08facc82bdaa8.jpg | K10: 40.00 | L10: 500 | M10: 0.00 | N10: 0 | O10: 0 | P10: Não | S10: 0.00 | T10: Não | U10: Não | V10: Não | W10: 62 | X10: Melissa | Y10: campana | Z10: V53P47 | AA10: 53 | AB10: 7 dias após o recebimento do produto | AE10: 34.00 | AF10: 0.00 | AG10: Imediata | AJ10: 20 | AK10: 15 | AL10: 10 | AM10: 45396 | AN10: 45470 | AP10: Melissas novas, seminovas e usadas. Em ótimas condições de conservação. Todas higienizadas.Moda circular sustentável!Porque uma melissa bem cuidada é para sempre!? | AS10: https://www.minhamania.net/mini-melissa/mini-melissa-campana-zig-zag | AU10: Infantil
B11: 995386 | C11: 161 | D11: 44316 | E11: Melissa Mel Harmonic Flower | F11: 54 | G11: https://images.tcdn.com.br/img/img_prod/995386/melissa_mel_rasteirinha_54_1_ca23c37fd89a96467d5f6a511e68bcfc.png | K11: 55.00 | L11: 500 | M11: 0.00 | N11: 0 | O11: 0 | P11: Não | S11: 0.00 | T11: Não | U11: Não | V11: Não | W11: 1 | X11: Melissa | Z11: P54 | AA11: 54 | AB11: 7 dias após o recebimento do produto | AE11: 34.00 | AF11: 0.00 | AG11: Imediata | AJ11: 20 | AK11: 15 | AL11: 10 | AM11: 44992 | AN11: 45197 | AP11: Melissas novas, seminovas e usadas. Em ótimas condições de conservação. Todas higienizadas.Moda circular sustentável!Porque uma melissa bem cuidada é para sempre!? | AS11: https://www.minhamania.net/mini-melissa/mini-melissa-posseissom-turma-do-pudim | AU11: Infantil
B12: 995386 | C12: 161 | D12: 44316 | E12: Mini Melissa Ultragirl Swett iii | F12: 55 | G12: https://images.tcdn.com.br/img/img_prod/995386/mini_melissa_ultragirl_laco_triplo_55_1_a3e08308e33445e27bf43a0df3d46c80.png | H12: https://images.tcdn.com.br/img/img_prod/995386/mini_melissa_ultragirl_swett_iii_55_2_ad68dd3a71e6ef7b667968ad1fa708c7.jpg | K12: 55.00 | L12: 500 | M12: 0.00 | N12: 0 | O12: 0 | P12: Não | S12: 0.00 | T12: Não | U12: Não | V12: Não | W12: 9 | X12: Melissa | Y12: ULTRAGIRL | Z12: V55P139 | AA12: 55 | AB12: 7 dias após o recebimento do produto | AE12: 38.25 | AF12: 0.00 | AG12: Imediata | AJ12: 20 | AK12: 15 | AL12: 10 | AM12: 45091 | AN12: 45030 | AP12: Melissas novas, seminovas e usadas. Em ótimas condições de conservação. Todas higienizadas.Moda circular sustentável!Porque uma melissa bem cuidada é para sempre!? | AS12: https://www.minhamania.net/mini-melissa/mini-melissa-ultragirl-laco | AU12: Infantil
B13: 995386 | C13: 161 | D13: 44316 | E13: Mini Melissa Rain Boot | F13: 56 | G13: https://images.tcdn.com.br/img/img_prod/995386/mini_melissa_rain_boot_56_1_003c1f32f466501fbe85b0c660c506b7.jpeg | H13: https://images.tcdn.com.br/img/img_prod/995386/mini_melissa_rain_boot_56_1_577361e7c86cb7eff60e6070e9108577.jpeg | I13: https://images.tcdn.com.br/img/img_prod/995386/mini_melissa_rain_boot_56_2_fcbdb44849e83936d01202cf7d6c7663.jpeg | J13: https://images.tcdn.com.br/img/img_prod/995386/mini_melissa_rain_boot_56_4_37c9d68154bcd86f02618fe92136d9e4.jpeg | K13: 80.00 | L13: 500 | M13: 0.00 | N13: 0 | O13: 0 | P13: Não | S13: 0.00 | T13: Não | U13: Não | V13: Não | W13: 29 | X13: Melissa | Y13: RAIN Boot | Z13: P56 | AA13: 56 | AB13: 7 dias após o recebimento do produto | AE13: 38.25 | AF13: 0.00 | AG13: Imediata | AJ13: 20 | AK13: 15 | AL13: 10 | AM13: 45190 | AN13: 45373 | AP13: Melissas novas, seminovas e usadas. Em ótimas condições de conservação. Todas higienizadas.Moda circular sustentável!Porque uma melissa bem cuidada é para sempre!? | AS13: https://www.minhamania.net/mini-melissa/mini-melissa-sugar-boot | AT13: https://images.tcdn.com.br/img/img_prod/995386/mini_melissa_rain_boot_56_5_c6627fbbb8eaeeccec104379820c2a88.jpg | AU13: Infantil
B14: 995386 | C14: 161 | D14: 44316 | E14: Mini Melissa Sugar Boot Winter | F14: 58 | G14: https://images.tcdn.com.br/img/img_prod/995386/mini_melissa_sugar_boot_winter_58_2_d49161fb22748bb9b4bf0f802a6b0429.jpeg | H14: https://images.tcdn.com.br/img/img_prod/995386/mini_melissa_sugar_boot_winter_58_2_e6a32acdca94e5b9566e4cabaa1f6b60.jpg | I14: https://images.tcdn.com.br/img/img_prod/995386/mini_melissa_sugar_boot_winter_58_3_92eb58c8801594a9721e46e19a9870a7.jpg | K14: 80.00 | L14: 500 | M14: 0.00 | N14: 0 | O14: 0 | P14: Não | S14: 0.00 | T14: Não | U14: Não | V14: Não | W14: 15 | X14: Melissa | Y14: SUGAR WINTER | Z14: P58 | AA14: 58 | AB14: 7 dias após o recebimento do produto | AE14: 58.07 | AF14: 0.00 | AG14: Imediata | AJ14: 20 | AK14: 15 | AL14: 10 | AM14: 45386 | AN14: 45357 | AP14: Melissas novas, seminovas e usadas. Em ótimas condições de conservação. Todas higienizadas.Moda circular sustentável!Porque uma melissa bem cuidada é para sempre!? | AS14: https://www.minhamania.net/mini-melissa/mini-melissa-sugar-boot-winter | AU14: Infantil
B15: 995386 | C15: 161 | D15: 44316 | E15: Mini Melissa Beach Line Friends Cachorro | F15: 62 | G15: https://images.tcdn.com.br/img/img_prod/995386/mini_melissa_beach_line_friends_cachorro_62_2_a0a6c77f30ce560bbac9d1aac8943a3e.jpg | H15: https://images.tcdn.com.br/img/img_prod/995386/mini_melissa_beach_line_friends_cachorro_62_2_3b5c4f203bc4ede42ca8debb911c7229.jpg | I15: https://images.tcdn.com.br/img/img_prod/995386/mini_melissa_beach_line_friends_cachorro_62_3_ae98d0b92ee8d1d36c805e659fee9569.jpg | K15: 65.00 | L15: 500 | M15: 0.00 | N15: 0 | O15: 0 | P15: Não | S15: 0.00 | T15: Não | U15: Não | V15: Não | W15: 11 | X15: Melissa | Y15: beach slide | Z15: P62 | AA15: 62 | AB15: 7 dias após o recebimento do produto | AE15: 42.50 | AF15: 0.00 | AG15: Imediata | AJ15: 20 | AK15: 15 | AL15: 10 | AM15: 45396 | AN15: 45308 | AP15: Melissas novas, seminovas e usadas. Em ótimas condições de conservação. Todas higienizadas.Moda circular sustentável!Porque uma melissa bem cuidada é para sempre!? | AS15: https://www.minhamania.net/mini-melissa/mini-melissa-beach-slide-line-friends | AU15: Infantil
B16: 995386 | C16: 161 | D16: 44316 | E16: Mini Melissa Aranha Smurfs | F16: 64 | G16: https://images.tcdn.com.br/img/img_prod/995386/mini_melissa_aranha_smurfs_64_1_003f447866b6f55b535ea36351ba405d.jpg | K16: 40.00 | L16: 500 | M16: 0.00 | N16: 0 | O16: 0 | P16: Não | S16: 0.00 | T16: Não | U16: Não | V16: Não | W16: 0 | X16: Melissa | Z16: P64 | AA16: 64 | AE16: 28.60 | AF16: 0.00 | AG16: Imediata | AJ16: 20 | AK16: 15 | AL16: 10 | AM16: 44327 | AN16: 44421 | AP16: Melissas novas, seminovas e usadas. Em ótimas condições de conservação. Todas higienizadas.Moda circular sustentável!Porque uma melissa bem cuidada é para sempre!? | AS16: https://www.minhamania.net/mini-melissa/mini-melissa-aranha-smurfs | AU16: Infantil
B17: 995386 | C17: 161 | D17: 44316 | E17: Mini Melissa Street + Mickey And Friends | F17: 65 | G17: https://images.tcdn.com.br/img/img_prod/995386/mini_melissa_street_mickey_and_friends_65_1_5b017b5da7a4ff3482a512688d6a9129.jpeg | H17: https://images.tcdn.com.br/img/img_prod/995386/mini_melissa_street_mickey_and_friends_65_2_4a41569a4969d7cf36435f3925b2aebd.jpeg | K17: 100.00 | L17: 500 | M17: 0.00 | N17: 0 | O17: 0 | P17: Não | S17: 0.00 | T17: Não | U17: Não | V17: Não | W17: 15 | X17: Melissa | Y17: STRETT | Z17: V65P84 | AA17: 65 | AB17: 7 dias após o recebimento do produto | AE17: 134.00 | AF17: 0.00 | AG17: Imediata | AJ17: 20 | AK17: 15 | AL17: 10 | AM17: 45305 | AN17: 45357 | AP17: Melissas novas, seminovas e usadas. Em ótimas condições de conservação. Todas higienizadas.Moda circular sustentável!Porque uma melissa bem cuidada é para sempre!? | AS17: https://www.minhamania.net/mini-melissa/mini-melissa-street-mickey-and-friends-minnie | AU17: Infantil
B18: 995386 | C18: 161 | D18: 44316 | E18: Mini Melissa Mar Sandal Pirulito | F18: 67 | G18: https://images.tcdn.com.br/img/img_prod/995386/mini_melissa_mar_sandal_pirulito_67_1_b73f9857ed0d088bb1a3e85c59faf149.jpeg | H18: https://images.tcdn.com.br/img/img_prod/995386/mini_melissa_mar_sandal_pirulito_67_2_108279f2237edf78b00c9c35d35c95fb.jpg | K18: 55.00 | L18: 500 | M18: 0.00 | N18: 1 | O18: 0 | P18: Sim | S18: 0.00 | T18: Não | U18: Não | V18: Não | W18: 12 | X18: Melissa | Z18: P67 | AA18: 67 | AE18: 36.65 | AF18: 0.00 | AG18: Imediata | AJ18: 20 | AK18: 15 | AL18: 10 | AM18: 45386 | AN18: 45411 | AP18: Melissas novas, seminovas e usadas. Em ótimas condições de conservação. Todas higienizadas.Moda circular sustentável!Porque uma melissa bem cuidada é para sempre!? | AS18: https://www.minhamania.net/mini-melissa/mini-melissa-mar-sandal-pirulito | AU18: Infantil
B19: 995386 | C19: 161 | D19: 44316 | E19: Mini Melissa Ultragirl Frozen | F19: 68 | G19: https://images.tcdn.com.br/img/img_prod/995386/mini_melissa_ultragirl_frozen_68_1_4993b5a4f17d0a5d46a7e583acd700d8.jpeg | H19: https://images.tcdn.com.br/img/img_prod/995386/mini_melissa_ultragirl_frozen_68_2_708ac81b0be7284de9f114f2791eca69.jpeg | I19: https://images.tcdn.com.br/img/img_prod/995386/mini_melissa_ultragirl_frozen_68_3_775555883ec27d37c4ea8c23a6902657.jpg | K19: 55.00 | L19: 500 | M19: 0.00 | N19: -2 | O19: 0 | P19: Não | S19: 0.00 | T19: Não | U19: Não | V19: Não | W19: 19 | X19: Melissa | Y19: Ultragirl | Z19: P68 | AA19: 68 | AE19: 36.65 | AF19: 0.00 | AG19: Imediata | AJ19: 20 | AK19: 15 | AL19: 10 | AM19: 45322 | AN19: 45495 | AP19: Melissas novas, seminovas e usadas. Em ótimas condições de conservação. Todas higienizadas.Moda circular sustentável!Porque uma melissa bem cuidada é para sempre!? | AS19: https://www.minhamania.net/mini-melissa/mini-melissa-ultragirl-frozen | AU19: Infantil
B20: 995386 | C20: 161 | D20: 44316 | E20: Melissa Mel Flox | F20: 69 | G20: https://images.tcdn.com.br/img/img_prod/995386/melissa_mel_flox_69_2_b965bdc395682a88b0d3ccdd912ca30f.jpeg | H20: https://images.tcdn.com.br/img/img_prod/995386/melissa_mel_flox_69_3_c4c1b02a3c012d0e1b417acdc8997765.jpg | I20: https://images.tcdn.com.br/img/img_prod/995386/melissa_mel_flox_69_4_9681fd3d72113078343d3178643c8a3f.jpg | J20: https://images.tcdn.com.br/img/img_prod/995386/melissa_mel_flox_69_4_c705c4ddf2a0d553bcaee1b910e75e65.jpg | K20: 50.00 | L20: 500 | M20: 0.00 | N20: 0 | O20: 0 | P20: Não | S20: 0.00 | T20: Não | U20: Não | V20: Não | W20: 48 | X20: Melissa | Y20: FLOX | Z20: P69 | AA20: 69 | AB20: 7 dias após o recebimento do produto | AE20: 37.99 | AF20: 0.00 | AG20: Imediata | AJ20: 20 | AK20: 15 | AL20: 10 | AM20: 44998 | AN20: 45163 | AP20: Melissas novas, seminovas e usadas. Em ótimas condições de conservação. Todas higienizadas.Moda circular sustentável!Porque uma melissa bem cuidada é para sempre!? | AS20: https://www.minhamania.net/mini-melissa/mini-melissa-posseissom | AT20: https://images.tcdn.com.br/img/img_prod/995386/melissa_mel_flox_69_5_d31bc93f7babcb81c92db5d782bc27eb.jpg, https://images.tcdn.com.br/img/img_prod/995386/melissa_mel_flox_69_6_2e6524507b4dddbb44168d9b4caa6e42.jpg | AU20: Infantil
B21: 995386 | C21: 161 | D21: 44316 | E21: Mini Melissa Possession Turma Do Pudim | F21: 72 | G21: https://images.tcdn.com.br/img/img_prod/995386/mini_melissa_posseissom_turma_do_pudim_72_1_982966ae01c3eac82ea316a6bf53793e.png | H21: https://images.tcdn.com.br/img/img_prod/995386/mini_melissa_posseissom_turma_do_pudim_72_2_c99bf6d47e4540587d54bff3732881a4.jpeg | K21: 50.00 | L21: 500 | M21: 0.00 | N21: 0 | O21: 0 | P21: Não | S21: 0.00 | T21: Não | U21: Não | V21: Não | W21: 11 | X21: Melissa | Y21: Turma do Pudim | Z21: P72 | AA21: 72 | AE21: 25.00 | AF21: 0.00 | AG21: Imediata | AJ21: 20 | AK21: 15 | AL21: 10 | AM21: 45127 | AN21: 45400 | AP21: Melissas novas, seminovas e usadas. Em ótimas condições de conservação. Todas higienizadas.Moda circular sustentável!Porque uma melissa bem cuidada é para sempre!? | AS21: https://www.minhamania.net/mini-melissa/mini-melissa-posseissom-turma-do-pudim- | AU21: Infantil
B22: 995386 | C22: 161 | D22: 44316 | E22: Mini Melissa Sneaker Polibolha | F22: 77 | G22: https://images.tcdn.com.br/img/img_prod/995386/mini_melissa_sneaker_polibolha_77_1_735479f88435f4eb06f645ae85d8ab20.jpg | H22: https://images.tcdn.com.br/img/img_prod/995386/mini_melissa_sneaker_polibolha_77_1_9cc47eb08855d81a33cb9781bf0f8843.jpg | I22: https://images.tcdn.com.br/img/img_prod/995386/mini_melissa_sneaker_polibolha_77_2_05466fd7a78a766537832864c1641f72.jpeg | J22: https://images.tcdn.com.br/img/img_prod/995386/mini_melissa_sneaker_polibolha_77_8_45526233fe28b4eb6b246e661d24464d.jpg | K22: 60.00 | L22: 100 | M22: 0.00 | N22: 0 | O22: 0 | P22: Não | S22: 0.00 | T22: Não | U22: Não | V22: Não | W22: 33 | X22: Melissa | Y22: Polibolha | Z22: V77P139 | AA22: 77 | AB22: 7 dias após o recebimento do produto | AE22: 32.86 | AF22: 0.00 | AG22: Imediata | AJ22: 25 | AK22: 15 | AL22: 10 | AM22: 45299 | AN22: 45447 | AP22: Melissas novas, seminovas e usadas. Em ótimas condições de conservação. Todas higienizadas.Moda circular sustentável!Porque uma melissa bem cuidada é para sempre!? | AS22: https://www.minhamania.net/mini-melissa/tenis-polibolha-turma-do-pudim | AU22: Infantil
B23: 995386 | C23: 161 | D23: 44316 | E23: Mini Melissa Ultragirl Pequena Sereia | F23: 83 | G23: https://images.tcdn.com.br/img/img_prod/995386/mini_melissa_ultragirl_pequena_sereia_83_1_6ba81f2236b43a14a7c0be07a372349f.jpg | H23: https://images.tcdn.com.br/img/img_prod/995386/mini_melissa_ultragirl_pequena_sereia_83_1_b111f32791193752693b2cdf44d1e027.jpeg | I23: https://images.tcdn.com.br/img/img_prod/995386/mini_melissa_ultragirl_pequena_sereia_83_1_2465d4ac564a6f8cf11c31694ee9f5d4.jpeg | K23: 55.00 | L23: 500 | M23: 0.00 | N23: 0 | O23: 0 | P23: Não | S23: 0.00 | T23: Não | U23: Não | V23: Não | W23: 14 | X23: Melissa | Z23: V83P51 | AA23: 83 | AB23: 7 dias após o recebimento do produto | AE23: 34.00 | AF23: 0.00 | AG23: Imediata | AJ23: 20 | AK23: 15 | AL23: 10 | AM23: 45159 | AN23: 45231 | AP23: Melissas novas, seminovas e usadas. Em ótimas condições de conservação. Todas higienizadas.Moda circular sustentável!Porque uma melissa bem cuidada é para sempre!? | AS23: https://www.minhamania.net/mini-melissa/mini-melissa-ultragirl-pequena-sereia | AU23: Infantil
B24: 995386 | C24: 161 | D24: 44316 | E24: Mini Melissa Balet Quadrada | F24: 84 | G24: https://images.tcdn.com.br/img/img_prod/995386/mini_melissa_ultragirl_bale_quadrada_84_1_7c4db8f989b6d6077bc3fc5ee89329c7.jpeg | H24: https://images.tcdn.com.br/img/img_prod/995386/mini_melissa_ultragirl_bale_quadrada_84_1_e49576164309458c286501884c41cf14.png | I24: https://images.tcdn.com.br/img/img_prod/995386/mini_melissa_ultragirl_bale_quadrada_84_3_85bf6966b0b0833c967281365cabd974.jpeg | K24: 50.00 | L24: 500 | M24: 0.00 | N24: 0 | O24: 0 | P24: Não | S24: 0.00 | T24: Não | U24: Não | V24: Não | W24: 8 | X24: Melissa | Z24: P84 | AA24: 84 | AE24: 34.00 | AF24: 0.00 | AG24: Imediata | AJ24: 20 | AK24: 15 | AL24: 10 | AM24: 44711 | AN24: 45396 | AP24: Melissas novas, seminovas e usadas. Em ótimas condições de conservação. Todas higienizadas.Moda circular sustentável!Porque uma melissa bem cuidada é para sempre!? | AS24: https://www.minhamania.net/mini-melissa/mini-melissa-ultragirl-bailarina | AU24: Infantil
B25: 995386 | C25: 161 | D25: 44316 | E25: Mini Melissa M40 Sem Pochete | F25: 86 | G25: https://images.tcdn.com.br/img/img_prod/995386/mini_melissa_m40_sem_pochete_86_1_8bb86f03e20097902fb5c385228efb3c.jpeg | H25: https://images.tcdn.com.br/img/img_prod/995386/mini_melissa_m40_sem_pochete_86_2_bce5d6a14e4ccdad3af271c59af40789.jpeg | I25: https://images.tcdn.com.br/img/img_prod/995386/mini_melissa_m40_sem_pochete_86_4_bcbb9664ea7366009fa579bbf8a750d9.jpg | J25: https://images.tcdn.com.br/img/img_prod/995386/mini_melissa_m40_sem_pochete_86_4_ac3848307f2427402626bfd9f87586d1.jpg | K25: 50.00 | L25: 100 | M25: 0.00 | N25: 1 | O25: 0 | P25: Sim | S25: 0.00 | T25: Não | U25: Não | V25: Não | W25: 26 | X25: Melissa | Y25: M40 | Z25: P86 | AA25: 86 | AE25: 30.00 | AF25: 0.00 | AG25: Imediata | AJ25: 25 | AK25: 15 | AL25: 10 | AM25: 45461 | AN25: 45461 | AP25: Melissas novas, seminovas e usadas. Em ótimas condições de conservação. Todas higienizadas.Moda circular sustentável!Porque uma melissa bem cuidada é para sempre!? | AS25: https://www.minhamania.net/mini-melissa/mini-melissa-vintage-sem-ponchete | AT25: https://images.tcdn.com.br/img/img_prod/995386/mini_melissa_m40_sem_pochete_86_5_8e85c30c026ca3f4f8991eb346bce46d.jpg, https://images.tcdn.com.br/img/img_prod/995386/mini_melissa_m40_sem_pochete_86_6_4f5fc12d7fa507e66e7044de7781d307.jpg, https://images.tcdn.com.br/img/img_prod/995386/mini_melissa_m40_sem_pochete_86_7_b9a18d8976fb40f7ee167257b42d6ee6.jpg | AU25: Infantil
B26: 995386 | C26: 161 | D26: 44316 | E26: Mini Melissa Possession | F26: 87 | G26: https://images.tcdn.com.br/img/img_prod/995386/mini_melissa_possession_87_1_9a98138e6c1a36926a7a321f53279f16.jpeg | H26: https://images.tcdn.com.br/img/img_prod/995386/mini_melissa_possession_87_1_756d82fbcd067b4c1c9b0b55b9da6e54.jpg | I26: https://images.tcdn.com.br/img/img_prod/995386/mini_melissa_possession_87_1_94b82b30165f7ca4a9205d726d4cac0f.jpeg | J26: https://images.tcdn.com.br/img/img_prod/995386/mini_melissa_possession_87_4_bda4939a3a42ed42c71f52a73065ebcc.jpg | K26: 55.00 | L26: 500 | M26: 0.00 | N26: 5 | O26: 0 | P26: Sim | S26: 0.00 | T26: Não | U26: Não | V26: Não | W26: 146 | X26: Melissa | Y26: Possession | Z26: V87P159 | AA26: 87 | AB26: 7 dias após o recebimento do produto | AE26: 38.25 | AF26: 0.00 | AG26: Imediata | AJ26: 20 | AK26: 15 | AL26: 10 | AM26: 45443 | AN26: 45359 | AP26: Melissas novas, seminovas e usadas. Em ótimas condições de conservação. Todas higienizadas.Moda circular sustentável!Porque uma melissa bem cuidada é para sempre!? | AS26: https://www.minhamania.net/mini-melissa/mini-melissa-posseissom- | AT26: https://images.tcdn.com.br/img/img_prod/995386/mini_melissa_possession_87_5_6e3bda8d1d2dd60db2e8cc1df190b05e.jpg, https://images.tcdn.com.br/img/img_prod/995386/mini_melissa_possession_87_6_d0f3f9688d73647a473ca685777639de.jpg, https://images.tcdn.com.br/img/img_prod/995386/mini_melissa_possession_87_7_f673ac7d400105f796c2e093da09ff96.jpg, https://images.tcdn.com.br/img/img_prod/995386/mini_melissa_possession_87_8_cd03f328826e5d5f89c28c9896907aef.jpg, https://images.tcdn.com.br/img/img_prod/995386/mini_melissa_possession_87_9_78f510c10cbe27b0ff2532825dd194af.jpg, https://images.tcdn.com.br/img/img_prod/995386/mini_melissa_possession_87_10_4c2e73fe1110a9e9121c7166825b15a8.jpg | AU26: Infantil
B27: 995386 | C27: 161 | D27: 44316 | E27: Mini Melissa Beach Sandal | F27: 93 | G27: https://images.tcdn.com.br/img/img_prod/995386/mini_melissa_beach_sandal_93_1_7304f70c8fe5b49474e142ce23e014c5.jpeg | H27: https://images.tcdn.com.br/img/img_prod/995386/mini_melissa_beach_sandal_93_2_bf47cca8eb382e0b5c3f2e3f006835fb.jpeg | I27: https://images.tcdn.com.br/img/img_prod/995386/mini_melissa_beach_sandal_93_3_1c9b9adff2b6b60c505736008a75259c.jpeg | K27: 55.00 | L27: 500 | M27: 0.00 | N27: 0 | O27: 0 | P27: Não | S27: 0.00 | T27: Não | U27: Não | V27: Não | W27: 9 | X27: Melissa | Z27: V93P121 | AA27: 93 | AE27: 44.00 | AF27: 0.00 | AG27: Imediata | AJ27: 20 | AK27: 15 | AL27: 10 | AM27: 44711 | AN27: 44670 | AP27: Melissas novas, seminovas e usadas. Em ótimas condições de conservação. Todas higienizadas.Moda circular sustentável!Porque uma melissa bem cuidada é para sempre!? | AS27: https://www.minhamania.net/mini-melissa/mini-melissa-beach-sandal | AU27: Infantil
B28: 995386 | C28: 161 | D28: 44316 | E28: Mini Melissa Sneaker Be Disney | F28: 94 | G28: https://images.tcdn.com.br/img/img_prod/995386/mini_melissa_sneaker_be_ad_disney_94_2_4aba0f6d902f8c7c4e08ca75af9076dd.jpg | H28: https://images.tcdn.com.br/img/img_prod/995386/mini_melissa_sneaker_be_disney_94_2_b9393edffcc7c18c893a285821cb186f.jpg | I28: https://images.tcdn.com.br/img/img_prod/995386/mini_melissa_sneaker_be_disney_94_3_9717f72bcbb44a1ac53c0df6c654e95e.jpg | K28: 65.00 | L28: 500 | M28: 0.00 | N28: 0 | O28: 0 | P28: Não | S28: 0.00 | T28: Não | U28: Não | V28: Não | W28: 15 | X28: Melissa | Y28: be | Z28: P94 | AA28: 94 | AB28: 7 dias após o recebimento do produto | AE28: 51.09 | AF28: 0.00 | AG28: Imediata | AJ28: 20 | AK28: 15 | AL28: 10 | AM28: 45158 | AN28: 45396 | AP28: Melissas novas, seminovas e usadas. Em ótimas condições de conservação. Todas higienizadas.Moda circular sustentável!Porque uma melissa bem cuidada é para sempre!? | AS28: https://www.minhamania.net/mini-melissa/mini-melissa-sneaker-be-ad-disney | AU28: Infantil
B29: 995386 | C29: 161 | D29: 44316 | E29: Mini Melissa Campana Crochet | F29: 96 | G29: https://images.tcdn.com.br/img/img_prod/995386/mini_melissa_campana_crochet_96_1_b40ea18dac3a8577ed8ac4fbfe593ade.png | H29: https://images.tcdn.com.br/img/img_prod/995386/mini_melissa_campana_crochet_96_2_c00d9c0308e1589bdf27e510006526e5.jpeg | I29: https://images.tcdn.com.br/img/img_prod/995386/mini_melissa_campana_crochet_96_3_c921939d6f3989f47c95f76df62c08f6.jpg | K29: 55.00 | L29: 500 | M29: 0.00 | N29: 0 | O29: 0 | P29: Não | S29: 0.00 | T29: Não | U29: Não | V29: Não | W29: 7 | X29: Melissa | Z29: P96 | AA29: 96 | AB29: 7 dias após o recebimento do produto | AE29: 41.60 | AF29: 0.00 | AG29: Imediata | AJ29: 20 | AK29: 15 | AL29: 10 | AM29: 44797 | AN29: 45470 | AP29: Melissas novas, seminovas e usadas. Em ótimas condições de conservação. Todas higienizadas.Moda circular sustentável!Porque uma melissa bem cuidada é para sempre!? | AS29: https://www.minhamania.net/mini-melissa/mini-melissa-campana-chochet | AU29: Infantil
B30: 995386 | C30: 161 | D30: 44316 | E30: Mini Melissa Beach Slide Zoo | F30: 102 | G30: https://images.tcdn.com.br/img/img_prod/995386/mini_melissa_beach_slide_zoo_102_4_972a9e4b4c2c3e1ec286d2a4432ae012.jpeg | H30: https://images.tcdn.com.br/img/img_prod/995386/mini_melissa_beach_slide_zoo_102_1_40e5e166450ec9e85817566c948cc5c3.jpeg | I30: https://images.tcdn.com.br/img/img_prod/995386/mini_melissa_beach_slide_zoo_102_4_bb0af83e7439ae9ea2046acaaa63b1ee.jpg | J30: https://images.tcdn.com.br/img/img_prod/995386/mini_melissa_beach_slide_zoo_102_4_eed96c97dd1fb31273267aee8ec80133.jpeg | K30: 100.00 | L30: 500 | M30: 0.00 | N30: -3 | O30: 0 | P30: Não | S30: 0.00 | T30: Não | U30: Não | V30: Não | W30: 32 | X30: Melissa | Y30: beach slide | Z30: P102 | AA30: 102 | AB30: 7 dias após o recebimento do produto | AE30: 35.00 | AF30: 0.00 | AG30: Imediata | AJ30: 20 | AK30: 15 | AL30: 10 | AM30: 45205 | AN30: 45476 | AP30: Melissas novas, seminovas e usadas. Em ótimas condições de conservação. Todas higienizadas.Moda circular sustentável!Porque uma melissa bem cuidada é para sempre!? | AS30: https://www.minhamania.net/mini-melissa/mini-melissa-beach-slide-zoo | AT30: https://images.tcdn.com.br/img/img_prod/995386/mini_melissa_beach_slide_zoo_102_5_7cb07010cec7c536345387fd09bc10a1.jpg, https://images.tcdn.com.br/img/img_prod/995386/mini_melissa_beach_slide_zoo_102_6_07192538655f5ed6366a0337f468ef47.jpg | AU30: Infantil
B31: 995386 | C31: 161 | D31: 44316 | E31: Mini Melissa Jump Frutland Abacaxi Morango Melancia Abacate Laranja | F31: 103 | G31: https://images.tcdn.com.br/img/img_prod/995386/mini_melissa_jump_frutland_abacaxi_morango_melancia_abacate_103_1_c612fc06bf8a2fa0e38b43d5794ca0ce.jpeg | H31: https://images.tcdn.com.br/img/img_prod/995386/mini_melissa_jump_frutland_abacaxi_morango_melancia_abacate_103_2_c2881899e917d89252771475929ad769.jpeg | I31: https://images.tcdn.com.br/img/img_prod/995386/mini_melissa_jump_frutland_abacaxi_morango_melancia_abacate_103_3_8524c1efb585bd472ef5436600e737cb.jpeg | J31: https://images.tcdn.com.br/img/img_prod/995386/mini_melissa_jump_frutland_abacaxi_morango_melancia_abacate_103_4_5c97f4d47678cb4e8a7f77b38869b779.jpeg | K31: 65.00 | L31: 100 | M31: 0.00 | N31: 0 | O31: 0 | P31: Não | S31: 0.00 | T31: Não | U31: Não | V31: Não | W31: 84 | X31: Melissa | Y31: JUMP FRUTLAND | Z31: V103P165 | AA31: 103 | AB31: 7 dias após o recebimento do produto | AE31: 65.00 | AF31: 0.00 | AG31: Imediata | AJ31: 25 | AK31: 15 | AL31: 10 | AM31: 45448 | AN31: 45369 | AP31: Melissas novas, seminovas e usadas. Em ótimas condições de conservação. Todas higienizadas.Moda circular sustentável!Porque uma melissa bem cuidada é para sempre!? | AS31: https://www.minhamania.net/mini-melissa/mini-melissa-basic-frutland-melancia | AT31: https://images.tcdn.com.br/img/img_prod/995386/mini_melissa_jump_frutland_abacaxi_morango_melancia_abacate_103_5_23b8ba58c0322ba3cb4bdfe579b402c2.jpg, https://images.tcdn.com.br/img/img_prod/995386/mini_melissa_jump_frutland_abacaxi_morango_melancia_abacate_103_6_8420a8780d49def9870454b83374a079.jpg, https://images.tcdn.com.br/img/img_prod/995386/mini_melissa_jump_frutland_abacaxi_morango_melancia_abacate_103_7_1467808949933216a6fb0744ec29004a.jpg, https://images.tcdn.com.br/img/img_prod/995386/mini_melissa_jump_frutland_abacaxi_morango_melancia_abacate_laranja_103_8_0febbd76f71839f7647237688027f014.jpg | AU31: Infantil
B32: 995386 | C32: 161 | D32: 44316 | E32: Mini Melissa Francks | F32: 105 | G32: https://images.tcdn.com.br/img/img_prod/995386/mini_melissa_francks_105_1_4d00882ef4907c38e2d4664e174d4416.jpeg | H32: https://images.tcdn.com.br/img/img_prod/995386/mini_melissa_francks_105_3_ce56408290165b667be32dcbde3b8d01.jpeg | I32: https://images.tcdn.com.br/img/img_prod/995386/mini_melissa_francks_105_4_8b74fd1ea1480006ac09adf8da697c9e.jpg | J32: https://images.tcdn.com.br/img/img_prod/995386/mini_melissa_francks_105_4_48b36d09700956f89247539783a7fb19.jpg | K32: 55.00 | L32: 500 | M32: 0.00 | N32: -1 | O32: 0 | P32: Não | S32: 0.00 | T32: Não | U32: Não | V32: Não | W32: 53 | X32: Melissa | Y32: FRANCX | Z32: V105P55 | AA32: 105 | AB32: 7 dias após o recebimento do produto | AE32: 34.00 | AF32: 0.00 | AG32: Imediata | AJ32: 20 | AK32: 15 | AL32: 10 | AM32: 44951 | AN32: 45329 | AP32: Melissas novas, seminovas e usadas. Em ótimas condições de conservação. Todas higienizadas.Moda circular sustentável!Porque uma melissa bem cuidada é para sempre!? | AS32: https://www.minhamania.net/mini-melissa/mini-melissa-francks | AU32: Infantil
B33: 995386 | C33: 161 | D33: 44316 | E33: Galocha Mini Melissa Sugar Rain | F33: 107 | G33: https://images.tcdn.com.br/img/img_prod/995386/galocha_mini_melissa_sugar_rain_107_1_7cdb6f1263a620758fc3cbee6e0c6218.jpeg | H33: https://images.tcdn.com.br/img/img_prod/995386/galocha_mini_melissa_sugar_rain_107_1_44c4b49cfdf350b3c328b0c481c3fdd0.jpeg | I33: https://images.tcdn.com.br/img/img_prod/995386/galocha_mini_melissa_sugar_rain_107_3_b7d682c9d5bb86859b1d135d7d517b66.jpeg | K33: 65.00 | L33: 500 | M33: 0.00 | N33: 0 | O33: 0 | P33: Não | S33: 0.00 | T33: Não | U33: Não | V33: Não | W33: 11 | X33: Melissa | Y33: sugar rain | Z33: V107P55 | AA33: 107 | AB33: 7 dias após o recebimento do produto | AE33: 23.75 | AF33: 0.00 | AG33: Imediata | AJ33: 20 | AK33: 15 | AL33: 10 | AM33: 45386 | AN33: 45321 | AP33: Melissas novas, seminovas e usadas. Em ótimas condições de conservação. Todas higienizadas.Moda circular sustentável!Porque uma melissa bem cuidada é para sempre!? | AS33: https://www.minhamania.net/mini-melissa/galocha-mini-melissa-sugar-rain | AU33: Infantil
B34: 995386 | C34: 161 | D34: 44316 | E34: Mini Melissa Aranha Xiii | F34: 109 | G34: https://images.tcdn.com.br/img/img_prod/995386/mini_melissa_aranha_laco_109_2_7ba1105cdb4572cc686ba10b49472b0c.jpeg | H34: https://images.tcdn.com.br/img/img_prod/995386/mini_melissa_aranha_laco_109_1_3e54f1fb03138aa09868420e3d991be3.jpeg | I34: https://images.tcdn.com.br/img/img_prod/995386/mini_melissa_aranha_xiii_109_3_0281816ffe99c2d3fe8a774aea994da8.jpg | K34: 55.00 | L34: 500 | M34: 0.00 | N34: 0 | O34: 0 | P34: Não | S34: 0.00 | T34: Não | U34: Não | V34: Não | W34: 6 | X34: Melissa | Y34: aranha | Z34: P109 | AA34: 109 | AB34: 7 dias após o recebimento do produto | AE34: 38.25 | AF34: 0.00 | AG34: Imediata | AJ34: 20 | AK34: 15 | AL34: 10 | AM34: 44998 | AN34: 45036 | AP34: Melissas novas, seminovas e usadas. Em ótimas condições de conservação. Todas higienizadas.Moda circular sustentável!Porque uma melissa bem cuidada é para sempre!? | AS34: https://www.minhamania.net/mini-melissa/mini-melissa-aranha-laco- | AU34: Infantil
B35: 995386 | C35: 161 | D35: 44316 | E35: Mini Melissa Ultragirl Unicornio | F35: 111 | G35: https://images.tcdn.com.br/img/img_prod/995386/mini_melissa_ultragil_unicornio_111_1_571b3f81db8201ff82d32bfb7c9bb28d.png | H35: https://images.tcdn.com.br/img/img_prod/995386/mini_melissa_ultragirl_unicornio_111_2_9e790b16ec329803fa87c0de310d89c1.jpeg | I35: https://images.tcdn.com.br/img/img_prod/995386/mini_melissa_ultragirl_unicornio_111_4_c443a859fb71549e74a2d694ba48c838.jpeg | J35: https://images.tcdn.com.br/img/img_prod/995386/mini_melissa_ultragirl_unicornio_111_4_aa69c92c694dc99f398db18c7384e0a9.jpg | K35: 55.00 | L35: 500 | M35: 0.00 | N35: -1 | O35: 0 | P35: Não | S35: 0.00 | T35: Não | U35: Não | V35: Não | W35: 18 | X35: Melissa | Z35: P111 | AA35: 111 | AE35: 25.00 | AF35: 0.00 | AG35: Imediata | AJ35: 20 | AK35: 15 | AL35: 10 | AM35: 45125 | AN35: 45396 | AP35: Melissas novas, seminovas e usadas. Em ótimas condições de conservação. Todas higienizadas.Moda circular sustentável!Porque uma melissa bem cuidada é para sempre!? | AS35: https://www.minhamania.net/mini-melissa/mini-melissa-ultragil-trick-or-treat | AU35: Infantil
B36: 995386 | C36: 161 | D36: 44316 | E36: Mini Melissa Ultragirl Trick Or Treat (Bala) | F36: 112 | G36: https://images.tcdn.com.br/img/img_prod/995386/mini_melissa_ultragirl_trick_or_treat_bala_112_1_fbff021095ec2d27b9b57f4a367a9465.jpeg | H36: https://images.tcdn.com.br/img/img_prod/995386/mini_melissa_ultragirl_trick_or_treat_bala_112_1_17729624a78e4e59c380a94b0896877e.jpeg | I36: https://images.tcdn.com.br/img/img_prod/995386/mini_melissa_ultragirl_trick_or_treat_bala_112_3_6f3334d4a24487bef8c5140bf605ff62.jpeg | J36: https://images.tcdn.com.br/img/img_prod/995386/mini_melissa_ultragirl_trick_or_treat_bala_112_4_2534a4ac7e800a5de43dd392c79b3447.jpg | K36: 55.00 | L36: 500 | M36: 0.00 | N36: 0 | O36: 0 | P36: Não | S36: 0.00 | T36: Não | U36: Não | V36: Não | W36: 17 | X36: Melissa | Z36: P112 | AA36: 112 | AB36: 7 dias após o recebimento do produto | AE36: 30.95 | AF36: 0.00 | AG36: Imediata | AJ36: 20 | AK36: 15 | AL36: 10 | AM36: 45233 | AN36: 45334 | AP36: Melissas novas, seminovas e usadas. Em ótimas condições de conservação. Todas higienizadas.Moda circular sustentável!Porque uma melissa bem cuidada é para sempre!? | AS36: https://www.minhamania.net/mini-melissa/mini-melissa-ultragirl-bala | AU36: Infantil
B37: 995386 | C37: 161 | D37: 44316 | E37: Mini Melissa Possession Unicornio | F37: 113 | G37: https://images.tcdn.com.br/img/img_prod/995386/mini_melissa_posseissom_unicornio_113_1_f7dcc28ccbb4b9b6bccb425744264593.jpeg | H37: https://images.tcdn.com.br/img/img_prod/995386/mini_melissa_possession_unicornio_113_2_a81be642f91f9371331db35ac4cbca96.jpeg | K37: 55.00 | L37: 500 | M37: 0.00 | N37: 0 | O37: 0 | P37: Não | S37: 0.00 | T37: Não | U37: Não | V37: Não | W37: 10 | X37: Melissa | Y37: possession | Z37: V113P147 | AA37: 113 | AB37: 7 dias após o recebimento do produto | AE37: 36.80 | AF37: 0.00 | AG37: Imediata | AJ37: 20 | AK37: 15 | AL37: 10 | AM37: 44914 | AN37: 44784 | AP37: Melissas novas, seminovas e usadas. Em ótimas condições de conservação. Todas higienizadas.Moda circular sustentável!Porque uma melissa bem cuidada é para sempre!? | AS37: https://www.minhamania.net/mini-melissa/mini-melissa-posseissom-unicornio | AU37: Infantil
B38: 995386 | C38: 161 | D38: 44316 | E38: Mini Melissa Beach Slide Mickey And Friends | F38: 116 | G38: https://images.tcdn.com.br/img/img_prod/995386/mini_melissa_beach_slide_mickey_and_friends_116_1_a3c0f7e6c2f8326d6ef98561e4cc6d04.jpg | H38: https://images.tcdn.com.br/img/img_prod/995386/mini_melissa_beach_slide_mickey_and_friends_116_3_84de2c9e598d79e7814d424ac6057f0a.jpeg | I38: https://images.tcdn.com.br/img/img_prod/995386/mini_melissa_beach_slide_mickey_and_friends_116_3_f361a25540d9138c4052cfc6e516ffef.jpg | K38: 100.00 | L38: 500 | M38: 0.00 | N38: -2 | O38: 0 | P38: Não | S38: 0.00 | T38: Não | U38: Não | V38: Não | W38: 36 | X38: Melissa | Y38: BEACH SLIDE | Z38: P116 | AA38: 116 | AE38: 70.00 | AF38: 0.00 | AG38: Imediata | AJ38: 20 | AK38: 15 | AL38: 10 | AM38: 45386 | AN38: 45462 | AP38: Melissas novas, seminovas e usadas. Em ótimas condições de conservação. Todas higienizadas.Moda circular sustentável!Porque uma melissa bem cuidada é para sempre!? | AS38: https://www.minhamania.net/mini-melissa/mini-melisse-beach-slide-mickey-e-minnie | AU38: Infantil
B39: 995386 | C39: 161 | D39: 44316 | E39: Mini Melissa Ultragirl Bamby | F39: 118 | G39: https://images.tcdn.com.br/img/img_prod/995386/mini_melissa_ultragirl_bamby_118_1_13482de8ee756c1ee45a7897e61b2800.jpeg | H39: https://images.tcdn.com.br/img/img_prod/995386/mini_melissa_ultragirl_bamby_118_2_cb3f460500a45947796d562e645be88e.jpeg | I39: https://images.tcdn.com.br/img/img_prod/995386/mini_melissa_ultragirl_bamby_118_3_d4a60935139c1a8e1fa733fa7bd47932.jpg | K39: 50.00 | L39: 500 | M39: 0.00 | N39: 0 | O39: 0 | P39: Não | S39: 0.00 | T39: Não | U39: Não | V39: Não | W39: 4 | X39: Melissa | Z39: P118 | AA39: 118 | AB39: 7 dias após o recebimento do produto | AE39: 31.55 | AF39: 0.00 | AG39: Imediata | AJ39: 20 | AK39: 15 | AL39: 10 | AM39: 45107 | AN39: 45396 | AP39: Melissas novas, seminovas e usadas. Em ótimas condições de conservação. Todas higienizadas.Moda circular sustentável!Porque uma melissa bem cuidada é para sempre!? | AS39: https://www.minhamania.net/mini-melissa/mini-melissa-ultragirl-bamby | AU39: Infantil
B40: 995386 | C40: 161 | D40: 44316 | E40: Mini Melissa Sneaker Love System | F40: 121 | G40: https://images.tcdn.com.br/img/img_prod/995386/mini_melissa_sneaker_love_system_121_1_a7d6c67366dd8654e262462022f214e8.jpeg | H40: https://images.tcdn.com.br/img/img_prod/995386/mini_melissa_sneaker_love_system_121_2_ee4a77024b60537d2c3cc55b64b23772.jpeg | I40: https://images.tcdn.com.br/img/img_prod/995386/mini_melissa_sneaker_love_system_121_3_b984acc0cda6f8c06da1e1a95d77bb74.jpeg | J40: https://images.tcdn.com.br/img/img_prod/995386/mini_melissa_sneaker_love_system_121_4_59d2900fa0915bc8e87ab0e5b5ee26b4.jpeg | K40: 65.00 | L40: 500 | M40: 0.00 | N40: 0 | O40: 0 | P40: Não | S40: 0.00 | T40: Não | U40: Não | V40: Não | W40: 18 | X40: Melissa | Z40: P121 | AA40: 121 | AE40: 40.00 | AF40: 0.00 | AG40: Imediata | AJ40: 20 | AK40: 15 | AL40: 10 | AM40: 45049 | AN40: 45396 | AP40: Melissas novas, seminovas e usadas. Em ótimas condições de conservação. Todas higienizadas.Moda circular sustentável!Porque uma melissa bem cuidada é para sempre!? | AS40: https://www.minhamania.net/mini-melissa/mini-melissa-sneaker-swett-love- | AU40: Infantil
B41: 995386 | C41: 161 | D41: 44316 | E41: Mini Melissa Ultragirl Anglomania + Vivienne Westwood | F41: 123 | G41: https://images.tcdn.com.br/img/img_prod/995386/mini_melissa_ultragirl_vivienne_westwood_123_1_a6a6417f133b3ae2918ddb7e85a53b53.jpeg | H41: https://images.tcdn.com.br/img/img_prod/995386/mini_melissa_ultragirl_vivienne_westwood_123_2_a57b144856b459655a92a5f4f2ecdcea.jpeg | I41: https://images.tcdn.com.br/img/img_prod/995386/mini_melissa_ultragirl_vivienne_westwood_123_3_a0baec34cbcac10fa417e0ec992d9105.jpeg | J41: https://images.tcdn.com.br/img/img_prod/995386/mini_melissa_ultragirl_anglomania_vivienne_westwood_123_4_651196ac5d09a357b9a653ad3f9376d6.jpg | K41: 40.00 | L41: 500 | M41: 0.00 | N41: 0 | O41: 0 | P41: Não | S41: 0.00 | T41: Não | U41: Não | V41: Não | W41: 12 | X41: Melissa | Y41: Ultragirl | Z41: V123P169 | AA41: 123 | AE41: 0.00 | AF41: 0.00 | AG41: Imediata | AJ41: 20 | AK41: 15 | AL41: 10 | AM41: 45294 | AN41: 45323 | AP41: Melissas novas, seminovas e usadas. Em ótimas condições de conservação. Todas higienizadas.Moda circular sustentável!Porque uma melissa bem cuidada é para sempre!? | AS41: https://www.minhamania.net/mini-melissa/mini-melissa-ultragirl-a-dama-e-o-vagabundo | AU41: Infantil
B42: 995386 | C42: 161 | D42: 44316 | E42: Mini Melissa Cosmic Sandal | F42: 124 | G42: https://images.tcdn.com.br/img/img_prod/995386/mini_melissa_cosmic_sandal_124_2_a9ac3806b3d30728f2b7f4090b17a444.jpeg | H42: https://images.tcdn.com.br/img/img_prod/995386/mini_melissa_cosmic_sandal_124_2_975471a7178b4cad1dc376d014d200ed.jpeg | I42: https://images.tcdn.com.br/img/img_prod/995386/mini_melissa_cosmic_sandal_124_3_7a085a4f4f351c94df86f1c99bd75cb0.jpg | J42: https://images.tcdn.com.br/img/img_prod/995386/mini_melissa_cosmic_sandal_124_4_ef7e48a7803436a23582ed5036293831.jpg | K42: 55.00 | L42: 500 | M42: 0.00 | N42: 0 | O42: 0 | P42: Não | S42: 0.00 | T42: Não | U42: Não | V42: Não | W42: 16 | X42: Melissa | Y42: cosmic | Z42: P124 | AA42: 124 | AB42: 7 dias após o recebimento do produto | AE42: 31.38 | AF42: 0.00 | AG42: Imediata | AJ42: 20 | AK42: 15 | AL42: 10 | AM42: 45030 | AN42: 45482 | AP42: Melissas novas, seminovas e usadas. Em ótimas condições de conservação. Todas higienizadas.Moda circular sustentável!Porque uma melissa bem cuidada é para sempre!? | AS42: https://www.minhamania.net/mini-melissa/mini-melissa-flox | AU42: Infantil
B43: 995386 | C43: 161 | D43: 44316 | E43: Mini Melissa Papete Rider | F43: 125 | G43: https://images.tcdn.com.br/img/img_prod/995386/mini_melissa_papete_rider_125_1_f771d1d3707adfe26d540517937060f2.jpeg | H43: https://images.tcdn.com.br/img/img_prod/995386/mini_melissa_papete_rider_125_1_2e65fe53af5796a2cc679c9135939ecf.jpeg | I43: https://images.tcdn.com.br/img/img_prod/995386/mini_melissa_papete_rider_125_4_22dedcb91a4ae08258a4843edf082a33.jpg | J43: https://images.tcdn.com.br/img/img_prod/995386/mini_melissa_papete_rider_125_4_f7d0f649f26fff2a58aa5d6a3d032116.jpg | K43: 100.00 | L43: 500 | M43: 0.00 | N43: 3 | O43: 0 | P43: Sim | Q43: 45041 | R43: 45169 | S43: 70.00 | T43: Não | U43: Não | V43: Não | W43: 83 | X43: Melissa | Y43: PAPETE | Z43: V125P171 | AA43: 125 | AB43: 7 dias após o recebimento do produto | AE43: 0.00 | AF43: 0.00 | AG43: Imediata | AJ43: 20 | AK43: 15 | AL43: 10 | AM43: 45439 | AN43: 45438 | AP43: Melissas novas, seminovas e usadas. Em ótimas condições de conservação. Todas higienizadas.Moda circular sustentável!Porque uma melissa bem cuidada é para sempre!? | AS43: https://www.minhamania.net/mini-melissa/mini-melissa-papete-rider-baby | AT43: https://images.tcdn.com.br/img/img_prod/995386/mini_melissa_papete_rider_125_5_73633cead81d8f41fe38b1072534a40a.jpg, https://images.tcdn.com.br/img/img_prod/995386/mini_melissa_papete_rider_125_6_0e4ddeecae3fc6424e889f9b1701682a.jpg, https://images.tcdn.com.br/img/img_prod/995386/mini_melissa_papete_rider_125_7_d8f218f8e9f8f0042aefe0c371972b7d.jpg | AU43: Infantil
B44: 995386 | C44: 161 | D44: 44316 | E44: Mini Melissa Possession Estrela] | F44: 126 | G44: https://images.tcdn.com.br/img/img_prod/995386/mini_melissa_possession_estrela_126_2_784830dc25efba4db04cb75a0500b969.jpeg | H44: https://images.tcdn.com.br/img/img_prod/995386/mini_melissa_posseissom_estrela_126_1_c6c58bed39805b940790e7c5baeb0248.jpeg | K44: 55.00 | L44: 500 | M44: 0.00 | N44: 0 | O44: 0 | P44: Não | S44: 0.00 | T44: Não | U44: Não | V44: Não | W44: 6 | X44: Melissa | Y44: Possession | Z44: P126 | AA44: 126 | AB44: 7 dias após o recebimento do produto | AE44: 28.57 | AF44: 0.00 | AG44: Imediata | AJ44: 20 | AK44: 15 | AL44: 10 | AM44: 44695 | AN44: 44758 | AP44: Melissas novas, seminovas e usadas. Em ótimas condições de conservação. Todas higienizadas.Moda circular sustentável!Porque uma melissa bem cuidada é para sempre!? | AS44: https://www.minhamania.net/mini-melissa/mini-melissa-posseissom-estrela | AU44: Infantil
B45: 995386 | C45: 161 | D45: 44316 | E45: Mini Melissa Ultragirl Baby Shark | F45: 127 | G45: https://images.tcdn.com.br/img/img_prod/995386/mini_melissa_ultragirl_baby_shark_127_1_72dbb6ae92e82d19a7f93c340aeca2a9.jpg | H45: https://images.tcdn.com.br/img/img_prod/995386/mini_melissa_ultragirl_baby_shark_127_2_3886d0f76dba5418133624227e6cdf7f.jpeg | I45: https://images.tcdn.com.br/img/img_prod/995386/mini_melissa_ultragirl_baby_shark_127_2_c2d49056f143baec64f0c0d04af0ce92.jpeg | J45: https://images.tcdn.com.br/img/img_prod/995386/mini_melissa_ultragirl_baby_shark_127_4_86311dc7851b77a77db70d4aaf3ab5a1.jpg | K45: 55.00 | L45: 500 | M45: 0.00 | N45: 0 | O45: 0 | P45: Não | S45: 0.00 | T45: Não | U45: Não | V45: Não | W45: 13 | X45: Melissa | Y45: ultragirl | Z45: V127P125 | AA45: 127 | AB45: 7 dias após o recebimento do produto | AE45: 28.57 | AF45: 0.00 | AG45: Imediata | AJ45: 20 | AK45: 15 | AL45: 10 | AM45: 44695 | AN45: 45477 | AP45: Melissas novas, seminovas e usadas. Em ótimas condições de conservação. Todas higienizadas.Moda circular sustentável!Porque uma melissa bem cuidada é para sempre!? | AS45: https://www.minhamania.net/mini-melissa/mini-melissa-baby-skark | AU45: Infantil
B46: 995386 | C46: 161 | D46: 44316 | E46: Mini Melissa Furadinha Pic Nic | F46: 128 | G46: https://images.tcdn.com.br/img/img_prod/995386/mini_melissa_furadinha_pic_nic_128_1_f6ae2786699fcd9b06fc2888edbb33c7.jpeg | H46: https://images.tcdn.com.br/img/img_prod/995386/mini_melissa_furadinha_pic_nic_128_2_846fc6b8f156f0ff4e3271e9b3778e15.jpeg | K46: 40.00 | L46: 500 | M46: 0.00 | N46: 0 | O46: 0 | P46: Não | S46: 0.00 | T46: Não | U46: Não | V46: Não | W46: 3 | X46: Melissa | Y46: FURADINHA | Z46: P128 | AA46: 128 | AB46: 7 dias após o recebimento do produto | AE46: 36.50 | AF46: 0.00 | AG46: Imediata | AJ46: 20 | AK46: 15 | AL46: 10 | AM46: 45040 | AN46: 45396 | AP46: Melissas novas, seminovas e usadas. Em ótimas condições de conservação. Todas higienizadas.Moda circular sustentável!Porque uma melissa bem cuidada é para sempre!? | AS46: https://www.minhamania.net/mini-melissa/mini-melissa-furadinha-laco | AU46: Infantil
B47: 995386 | C47: 161 | D47: 44316 | E47: Mini Melissa Ultragirl Swett chrome | F47: 130 | G47: https://images.tcdn.com.br/img/img_prod/995386/mini_melissa_ultragirl_swett_130_2_548644b3fbf8346506e640db3c83c99f.jpeg | K47: 55.00 | L47: 500 | M47: 0.00 | N47: 0 | O47: 0 | P47: Não | S47: 0.00 | T47: Não | U47: Não | V47: Não | W47: 10 | X47: Melissa | Z47: P130 | AA47: 130 | AE47: 30.00 | AF47: 0.00 | AG47: Imediata | AJ47: 20 | AK47: 15 | AL47: 10 | AM47: 44711 | AN47: 45396 | AP47: Melissas novas, seminovas e usadas. Em ótimas condições de conservação. Todas higienizadas.Moda circular sustentável!Porque uma melissa bem cuidada é para sempre!? | AS47: https://www.minhamania.net/mini-melissa/mini-melissa-ultragirl-swett | AU47: Infantil
B48: 995386 | C48: 161 | D48: 44316 | E48: Mini Melissa Animal Lovers Esquilo | F48: 131 | G48: https://images.tcdn.com.br/img/img_prod/995386/mini_melissa_animal_lovers_esquilo_131_1_4154fcc84c3c75aa579624e6bd174ba5.jpeg | H48: https://images.tcdn.com.br/img/img_prod/995386/mini_melissa_animal_lovers_esquilo_131_1_3495259851600a17b696c74137e101d6.jpeg | K48: 45.00 | L48: 500 | M48: 0.00 | N48: 0 | O48: 0 | P48: Não | S48: 0.00 | T48: Não | U48: Não | V48: Não | W48: 3 | X48: Melissa | Z48: V131P51 | AA48: 131 | AE48: 30.00 | AF48: 0.00 | AG48: Imediata | AJ48: 20 | AK48: 15 | AL48: 10 | AM48: 44695 | AN48: 44758 | AP48: Melissas novas, seminovas e usadas. Em ótimas condições de conservação. Todas higienizadas.Moda circular sustentável!Porque uma melissa bem cuidada é para sempre!? | AS48: https://www.minhamania.net/mini-melissa/mini-melissa-campana-zig-zag---- | AU48: Infantil
B49: 995386 | C49: 161 | D49: 44316 | E49: Mini Melissa Maggie Bear | F49: 139 | G49: https://images.tcdn.com.br/img/img_prod/995386/mini_melissa_maggie_bear_139_1_14f1403516609d631fb6a02cecf61964.jpeg | H49: https://images.tcdn.com.br/img/img_prod/995386/mini_melissa_maggie_bear_139_2_db5f280b5d2d6b892d066b239713e84b.jpeg | I49: https://images.tcdn.com.br/img/img_prod/995386/mini_melissa_maggie_bear_139_3_756446da5dfa949609c7f57f03f2be5f.jpg | K49: 65.00 | L49: 500 | M49: 0.00 | N49: -1 | O49: 0 | P49: Não | S49: 0.00 | T49: Não | U49: Não | V49: Não | W49: 33 | X49: Melissa | Y49: maggic bear | Z49: V139P65 | AA49: 139 | AE49: 33.00 | AF49: 0.00 | AG49: Imediata | AJ49: 20 | AK49: 15 | AL49: 10 | AM49: 45230 | AN49: 45477 | AP49: Melissas novas, seminovas e usadas. Em ótimas condições de conservação. Todas higienizadas.Moda circular sustentável!Porque uma melissa bem cuidada é para sempre!? | AS49: https://www.minhamania.net/mini-melissa/mini-melissa-campana | AU49: Infantil
B50: 995386 | C50: 161 | D50: 44319 | E50: Mini Melissa Boot Baby | F50: 143 | G50: https://images.tcdn.com.br/img/img_prod/995386/mini_melissa_boot_baby_143_1_c5fc736d193670df27730e1b4f931365.png | K50: 60.00 | L50: 500 | M50: 0.00 | N50: 0 | O50: 0 | P50: Não | S50: 0.00 | T50: Não | U50: Não | V50: Não | W50: 1 | Z50: V143P65 | AA50: 143 | AB50: 7 dias após o recebimento do produto | AE50: 43.20 | AF50: 0.00 | AG50: Imediata | AJ50: 15 | AK50: 12 | AL50: 10 | AM50: 44403 | AN50: 44429 | AP50: Melissas novas, seminovas e usadas. Em ótimas condições de conservação. Todas higienizadas.Moda circular sustentável!Porque uma melissa bem cuidada é para sempre!? | AS50: https://www.minhamania.net/mini-melissa/mini-melissa-boot-baby | AU50: Infantil
B51: 995386 | C51: 161 | D51: 44319 | E51: Mini Melissa Aranha Picolé | F51: 145 | G51: https://images.tcdn.com.br/img/img_prod/995386/mini_melissa_aranha_picole_145_1_1891d8d3e8a50666f0b91535c63e0640.jpg | H51: https://images.tcdn.com.br/img/img_prod/995386/mini_melissa_aranha_picole_145_1_04243fc63e3211743fe630195e885030.png | I51: https://images.tcdn.com.br/img/img_prod/995386/mini_melissa_aranha_picole_145_1_f52fd13182df53356161e9b955d8caab.jpeg | K51: 45.00 | L51: 500 | M51: 0.00 | N51: 0 | O51: 0 | P51: Não | S51: 0.00 | T51: Não | U51: Não | V51: Não | W51: 15 | X51: Melissa | Y51: Aranha | Z51: V145P65 | AA51: 145 | AB51: 7 dias após o recebimento do produto | AE51: 28.60 | AF51: 0.00 | AG51: Imediata | AJ51: 20 | AK51: 15 | AL51: 10 | AM51: 44695 | AN51: 44684 | AP51: Melissas novas, seminovas e usadas. Em ótimas condições de conservação. Todas higienizadas.Moda circular sustentável!Porque uma melissa bem cuidada é para sempre!? | AS51: https://www.minhamania.net/mini-melissa/mini-melissa-aranha-picole | AU51: Infantil
B52: 995386 | C52: 161 | D52: 44319 | E52: Mini Melissa Ultragirl + Minnie (Laço Lateral) | F52: 147 | G52: https://images.tcdn.com.br/img/img_prod/995386/mini_melissa_ultragirl_minnie_laco_lateral_147_1_a4f13f67377247c85019530ece38ca86.jpeg | H52: https://images.tcdn.com.br/img/img_prod/995386/mini_melissa_ultragirl_minnie_laco_lateral_147_2_a73acbadf4919a05f9c5b419394c33e5.jpg | I52: https://images.tcdn.com.br/img/img_prod/995386/mini_melissa_ultragirl_minnie_laco_lateral_147_3_f8b3ae5f8b3d88b3110db06b08db18b5.jpg | J52: https://images.tcdn.com.br/img/img_prod/995386/mini_melissa_ultragirl_minnie_laco_lateral_147_4_271cb309e740efbb9b5dfa99bff483c5.jpg | K52: 55.00 | L52: 500 | M52: 0.00 | N52: 0 | O52: 0 | P52: Não | S52: 0.00 | T52: Não | U52: Não | V52: Não | W52: 5 | X52: Melissa | Z52: V147P65 | AA52: 147 | AE52: 39.27 | AF52: 0.00 | AJ52: 30 | AK52: 12 | AL52: 10 | AM52: 45030 | AN52: 44914 | AP52: Melissas novas, seminovas e usadas. Em ótimas condições de conservação. Todas higienizadas.Moda circular sustentável!Porque uma melissa bem cuidada é para sempre!? | AS52: https://www.minhamania.net/mini-melissa/mini-melissa-ultragirl-minnie | AU52: Infantil
B53: 995386 | C53: 161 | D53: 44319 | E53: Mini Melissa Furadinha Fabula | F53: 149 | G53: https://images.tcdn.com.br/img/img_prod/995386/mini_melissa_furadinha_fabula_149_1_9f2755e0646fde4c58028acabdafc95e.jpeg | H53: https://images.tcdn.com.br/img/img_prod/995386/mini_melissa_furadinha_fabula_149_1_b5b665854fa03206410c6c51d480df3d.jpeg | K53: 45.00 | L53: 500 | M53: 0.00 | N53: 0 | O53: 0 | P53: Não | S53: 0.00 | T53: Não | U53: Não | V53: Não | W53: 4 | X53: Melissa | Y53: ARANHA | Z53: V149P173 | AA53: 149 | AB53: 7 dias após o recebimento do produto | AE53: 34.99 | AF53: 0.00 | AG53: Imediata | AJ53: 20 | AK53: 12 | AL53: 10 | AM53: 44812 | AN53: 44812 | AP53: Melissas novas, seminovas e usadas. Em ótimas condições de conservação. Todas higienizadas.Moda circular sustentável!Porque uma melissa bem cuidada é para sempre!? | AS53: https://www.minhamania.net/mini-melissa/mini-melissa-aranha-fabula-- | AU53: Infantil
B54: 995386 | C54: 161 | D54: 44319 | E54: Mini Melissa Swett + Minnie | F54: 151 | G54: https://images.tcdn.com.br/img/img_prod/995386/mini_melissa_swett_disney_151_1_8caf8bd3a2b50b90a601a324db5a41cd.png | K54: 55.00 | L54: 500 | M54: 0.00 | N54: 0 | O54: 0 | P54: Não | Q54: 44405 | R54: 44408 | S54: 40.00 | T54: Não | U54: Não | V54: Não | W54: 5 | X54: Melissa | Y54: SWETT LOVE | Z54: V151P175 | AA54: 151 | AB54: 7 dias após o recebimento do produto | AE54: 38.99 | AF54: 0.00 | AG54: Imediata | AJ54: 25 | AK54: 12 | AL54: 10 | AM54: 44532 | AN54: 44532 | AP54: Melissas novas, seminovas e usadas. Em ótimas condições de conservação. Todas higienizadas.Moda circular sustentável!Porque uma melissa bem cuidada é para sempre!? | AS54: https://www.minhamania.net/mini-melissa/mini-melissa-swett-love-minnie | AU54: Infantil
B55: 995386 | C55: 161 | D55: 44319 | E55: Mini Melissa Play Step Cachorro | F55: 153 | G55: https://images.tcdn.com.br/img/img_prod/995386/mini_melissa_play_step_cachorro_153_1_53d1643374367e2a8e608d39a550b9a4.jpeg | H55: https://images.tcdn.com.br/img/img_prod/995386/mini_melissa_play_step_cachorro_153_2_7c221432c4957710e6e62d73c88a2d70.jpeg | K55: 65.00 | L55: 500 | M55: 0.00 | N55: 0 | O55: 0 | P55: Não | S55: 0.00 | T55: Não | U55: Não | V55: Não | W55: 12 | X55: Melissa | Y55: MAGGIE | Z55: V153P53 | AA55: 153 | AB55: 7 dias após o recebimento do produto | AE55: 38.49 | AF55: 0.00 | AG55: Imediata | AJ55: 25 | AK55: 12 | AL55: 10 | AM55: 44963 | AN55: 45055 | AP55: Melissas novas, seminovas e usadas. Em ótimas condições de conservação. Todas higienizadas.Moda circular sustentável!Porque uma melissa bem cuidada é para sempre!? | AS55: https://www.minhamania.net/mini-melissa/mini-melissa-maggie-cachorro | AU55: Infantil
B56: 995386 | C56: 161 | D56: 44319 | E56: Mini Melissa Jump Sunny Day | F56: 155 | G56: https://images.tcdn.com.br/img/img_prod/995386/mini_melissa_jump_sunny_day_155_1_9687d2ccfff407c20de94c56764d4ce4.jpeg | H56: https://images.tcdn.com.br/img/img_prod/995386/mini_melissa_jump_sunny_day_155_2_335905b42a21354b65d10ce4bb17d2ca.jpeg | I56: https://images.tcdn.com.br/img/img_prod/995386/mini_melissa_jump_sunny_day_155_3_38d8d6de7665e18ba59a98b340af006b.jpg | J56: https://images.tcdn.com.br/img/img_prod/995386/mini_melissa_jump_sunny_day_155_4_81e3dc909ce5f06d4a4511214964c3ce.jpg | K56: 65.00 | L56: 500 | M56: 0.00 | N56: 0 | O56: 0 | P56: Não | S56: 0.00 | T56: Não | U56: Não | V56: Não | W56: 31 | X56: Melissa | Y56: JUMP | Z56: V155P37 | AA56: 155 | AB56: 7 dias após o recebimento do produto | AE56: 49.68 | AF56: 0.00 | AG56: Imediata | AJ56: 25 | AK56: 12 | AL56: 10 | AM56: 45490 | AN56: 45396 | AP56: Melissas novas, seminovas e usadas. Em ótimas condições de conservação. Todas higienizadas.Moda circular sustentável!Porque uma melissa bem cuidada é para sempre!? | AS56: https://www.minhamania.net/mini-melissa/mini-melissa-jump-sunny-day | AU56: Infantil
B57: 995386 | C57: 161 | D57: 44319 | E57: Mini Melissa Ultragirl Donnuts | F57: 157 | G57: https://images.tcdn.com.br/img/img_prod/995386/mini_melissa_ultragirl_donnuts_157_1_3b030a77c428dffb3e89061cb285b781.jpeg | H57: https://images.tcdn.com.br/img/img_prod/995386/mini_melissa_ultragirl_donnuts_157_2_35db0ca1895ba98f4bc80d461d2f3f98.jpg | I57: https://images.tcdn.com.br/img/img_prod/995386/mini_melissa_ultragirl_donnuts_157_3_3d27047956ba427d2c49f7a3f61ec1de.jpg | K57: 55.00 | L57: 500 | M57: 0.00 | N57: 0 | O57: 0 | P57: Não | S57: 0.00 | T57: Não | U57: Não | V57: Não | W57: 12 | X57: Melissa | Y57: ULTRAGIRL | Z57: V157P179 | AA57: 157 | AB57: 7 dias após o recebimento do produto | AE57: 33.49 | AF57: 0.00 | AJ57: 25 | AK57: 15 | AL57: 10 | AM57: 45259 | AN57: 45396 | AP57: Melissas novas, seminovas e usadas. Em ótimas condições de conservação. Todas higienizadas.Moda circular sustentável!Porque uma melissa bem cuidada é para sempre!? | AS57: https://www.minhamania.net/mini-melissa/mini-melissa-ultragirl-donnuts | AU57: Infantil
B58: 995386 | C58: 161 | D58: 44321 | E58: Mini Melissa Ultragirl A Bela E A Fera | F58: 159 | G58: https://images.tcdn.com.br/img/img_prod/995386/mini_melissa_ultragirl_a_bela_e_a_fera_159_1_3a7423dfc45750e7cd98b34326994149.jpeg | K58: 55.00 | L58: 500 | M58: 0.00 | N58: 0 | O58: 0 | P58: Não | S58: 0.00 | T58: Não | U58: Não | V58: Não | W58: 4 | X58: Melissa | Y58: ULTRAGIRL | Z58: V159P87 | AA58: 159 | AB58: 7 dias após o recebimento do produto | AE58: 0.00 | AF58: 0.00 | AG58: Imediata | AJ58: 25 | AK58: 15 | AL58: 10 | AM58: 44797 | AN58: 44784 | AP58: Melissas novas, seminovas e usadas. Em ótimas condições de conservação. Todas higienizadas.Moda circular sustentável!Porque uma melissa bem cuidada é para sempre!? | AS58: https://www.minhamania.net/mini-melissa/mini-melissa-ultragil-a-bela-e-a-fera | AU58: Infantil
B59: 995386 | C59: 161 | D59: 44321 | E59: Mini Melissa Classic Baby | F59: 161 | G59: https://images.tcdn.com.br/img/img_prod/995386/mini_melissa_classic_baby_161_1_f966c7a0c405f520bcc3dd00c817b83e.jpeg | H59: https://images.tcdn.com.br/img/img_prod/995386/mini_melissa_classic_baby_161_1_139de18b37645056d4ba55da17e0788a.jpeg | I59: https://images.tcdn.com.br/img/img_prod/995386/mini_melissa_classic_baby_161_3_40d7ead24235977c1733f1992c52e294.jpg | J59: https://images.tcdn.com.br/img/img_prod/995386/mini_melissa_classic_baby_161_4_0a7562c127ea0df54d5add41b62535d8.jpeg | K59: 55.00 | L59: 5001 | M59: 0.00 | N59: 0 | O59: 0 | P59: Não | S59: 0.00 | T59: Não | U59: Não | V59: Não | W59: 11 | X59: Melissa | Y59: CLASSIC | Z59: P161 | AA59: 161 | AB59: 7 dias após o recebimento do produto | AE59: 0.00 | AF59: 0.00 | AG59: Imediata | AJ59: 25 | AK59: 15 | AL59: 10 | AM59: 44961 | AN59: 45396 | AP59: Melissas novas, seminovas e usadas. Em ótimas condições de conservação. Todas higienizadas.Moda circular sustentável!Porque uma melissa bem cuidada é para sempre!? | AS59: https://www.minhamania.net/mini-melissa/mini-melissa-classic-baby | AU59: Infantil
B60: 995386 | C60: 161 | D60: 44321 | E60: Mini Melissa Mar Sandal Swett Dreams | F60: 163 | G60: https://images.tcdn.com.br/img/img_prod/995386/mini_melissa_mar_sandal_swett_dreams_163_1_a7405532bed910b1441eb8df6322c758.jpeg | H60: https://images.tcdn.com.br/img/img_prod/995386/mini_melissa_mar_sandal_swett_dreams_163_2_bcec6d311710cc3f18582906e3917c6d.jpg | I60: https://images.tcdn.com.br/img/img_prod/995386/mini_melissa_mar_sandal_swett_dreams_163_3_377eb3cdad63833a24abaf1db818c1c6.jpg | K60: 55.00 | L60: 500 | M60: 0.00 | N60: 0 | O60: 0 | P60: Não | S60: 0.00 | T60: Não | U60: Não | V60: Não | W60: 19 | X60: Melissa | Y60: MAR SANDAL | Z60: V163P181 | AA60: 163 | AB60: 7 dias após o recebimento do produto | AE60: 0.00 | AF60: 0.00 | AG60: Imediata | AJ60: 20 | AK60: 15 | AL60: 10 | AM60: 45372 | AN60: 44684 | AP60: Melissas novas, seminovas e usadas. Em ótimas condições de conservação. Todas higienizadas.Moda circular sustentável!Porque uma melissa bem cuidada é para sempre!? | AS60: https://www.minhamania.net/mini-melissa/mini-melissa-mar-sandal-swett-dreams | AU60: Infantil
B61: 995386 | C61: 161 | D61: 44321 | E61: Melissa Mel Furadinha + Minnie Mouse | F61: 165 | G61: https://images.tcdn.com.br/img/img_prod/995386/melissa_mel_furadinha_minnie_mouse_165_1_89df43b79bc1fcbc11bd3392491b382d.jpg | H61: https://images.tcdn.com.br/img/img_prod/995386/melissa_mel_furadinha_minnie_mouse_165_1_90e5d9c5e0692cf747a5d6da3ceb52e1.jpeg | K61: 50.00 | L61: 500 | M61: 0.00 | N61: 0 | O61: 0 | P61: Não | S61: 0.00 | T61: Não | U61: Não | V61: Não | W61: 12 | X61: Melissa | Y61: FURADINHA | Z61: V165P183 | AA61: 165 | AB61: 7 dias após o recebimento do produto | AE61: 0.00 | AF61: 0.00 | AG61: Imediata | AJ61: 25 | AK61: 15 | AL61: 10 | AM61: 44963 | AN61: 44862 | AP61: Melissas novas, seminovas e usadas. Em ótimas condições de conservação. Todas higienizadas.Moda circular sustentável!Porque uma melissa bem cuidada é para sempre!? | AS61: https://www.minhamania.net/melissa-mell-teen/melissa-mel-furadinha-minnie-mouse | AU61: Infantil
B62: 995386 | C62: 161 | D62: 44321 | E62: Mini Melissa Furadinha Minnie | F62: 167 | G62: https://images.tcdn.com.br/img/img_prod/995386/mini_melissa_furadinha_minnie_167_1_8e2236d4f0fffc5f7f6ffeb171c755f3.jpeg | H62: https://images.tcdn.com.br/img/img_prod/995386/mini_melissa_furadinha_minnie_167_2_04b47252ea8ed4297671ec04ab251812.jpg | I62: https://images.tcdn.com.br/img/img_prod/995386/mini_melissa_furadinha_minnie_167_3_0743b5e98e575b777a5c51ac12251a51.jpg | K62: 55.00 | L62: 500 | M62: 0.00 | N62: 0 | O62: 0 | P62: Não | S62: 0.00 | T62: Não | U62: Não | V62: Não | W62: 9 | X62: Melissa | Y62: FURADINHA | Z62: P167 | AA62: 167 | AB62: 7 dias após o recebimento do produto | AE62: 0.00 | AF62: 0.00 | AG62: Imediata | AJ62: 25 | AK62: 15 | AL62: 10 | AM62: 45233 | AN62: 45307 | AP62: Melissas novas, seminovas e usadas. Em ótimas condições de conservação. Todas higienizadas.Moda circular sustentável!Porque uma melissa bem cuidada é para sempre!? | AS62: https://www.minhamania.net/mini-melissa/mini-melissa-furadinha-disney | AU62: Infantil
B63: 995386 | C63: 161 | D63: 44321 | E63: Mini Melissa Ultragirl Bailarina | F63: 169 | G63: https://images.tcdn.com.br/img/img_prod/995386/mini_melissa_ultragirl_bailarina_169_1_527148d06a4a592ce2a3d199841a2820.jpeg | H63: https://images.tcdn.com.br/img/img_prod/995386/mini_melissa_ultragirl_bailarina_169_1_a2b54b7ed8df7b86424d52a6efb84313.png | I63: https://images.tcdn.com.br/img/img_prod/995386/mini_melissa_ultragirl_bailarina_169_3_554c8ed956094ae8af626ef6cc278e50.jpg | J63: https://images.tcdn.com.br/img/img_prod/995386/mini_melissa_ultragirl_bailarina_169_4_e17fd686a1d48d315f1197a905336451.jpg | K63: 60.00 | L63: 500 | M63: 0.00 | N63: 0 | O63: 0 | P63: Não | S63: 0.00 | T63: Não | U63: Não | V63: Não | W63: 8 | X63: Melissa | Y63: ULTRAGIRL | Z63: V169P185 | AA63: 169 | AB63: 7 dias após o recebimento do produto | AE63: 0.00 | AF63: 0.00 | AG63: Imediata | AJ63: 25 | AK63: 15 | AL63: 10 | AM63: 45219 | AN63: 45447 | AP63: Melissas novas, seminovas e usadas. Em ótimas condições de conservação. Todas higienizadas.Moda circular sustentável!Porque uma melissa bem cuidada é para sempre!? | AS63: https://www.minhamania.net/mini-melissa/mini-melissa-ultragirl-bailarina- | AU63: Infantil
B64: 995386 | C64: 161 | D64: 44321 | E64: Mini Melissa Street Sneaker | F64: 171 | G64: https://images.tcdn.com.br/img/img_prod/995386/mini_melissa_street_sneaker_171_1_cafec9bc5992ea22599fa3d8ebff6877.jpeg | H64: https://images.tcdn.com.br/img/img_prod/995386/mini_melissa_street_sneaker_171_2_4705670cdf5d50738c380cd3f4376c3a.jpeg | I64: https://images.tcdn.com.br/img/img_prod/995386/mini_melissa_street_sneaker_171_4_40690f7835ba9f65c3d5da2024b232f4.jpeg | J64: https://images.tcdn.com.br/img/img_prod/995386/mini_melissa_street_sneaker_171_5_68ce4d622b7d6bda089c2dd7ba9f949d.jpeg | K64: 60.00 | L64: 500 | M64: 0.00 | N64: 1 | O64: 0 | P64: Sim | S64: 0.00 | T64: Não | U64: Não | V64: Não | W64: 71 | X64: Melissa | Y64: STRETT | Z64: V171P69 | AA64: 171 | AB64: 7 dias após o recebimento do produto | AE64: 0.00 | AF64: 0.00 | AG64: Imediata | AJ64: 25 | AK64: 15 | AL64: 10 | AM64: 45490 | AN64: 45480 | AP64: Melissas novas, seminovas e usadas. Em ótimas condições de conservação. Todas higienizadas.Moda circular sustentável!Porque uma melissa bem cuidada é para sempre!? | AS64: https://www.minhamania.net/mini-melissa/mini-melissa-street-sneaker | AT64: https://images.tcdn.com.br/img/img_prod/995386/mini_melissa_street_sneaker_171_5_3e1f9b8065a9d5d97569bf0a6021d5f4.jpg, https://images.tcdn.com.br/img/img_prod/995386/mini_melissa_street_sneaker_171_6_87c08ffa9b1185e5b3042c117f28116f.jpg, https://images.tcdn.com.br/img/img_prod/995386/mini_melissa_street_sneaker_171_7_ede8cc4483141fc3bbe418111cb290d4.jpg, https://images.tcdn.com.br/img/img_prod/995386/mini_melissa_street_sneaker_171_8_5ec0af0389439c1c4903148d63117d99.jpg, https://images.tcdn.com.br/img/img_prod/995386/mini_melissa_street_sneaker_171_9_30b43c1696a21b1744e5fef166eda2ae.jpg | AU64: Infantil
B65: 995386 | C65: 161 | D65: 44321 | E65: Mini Melissa Ultragirl Swett Dreams | F65: 173 | G65: https://images.tcdn.com.br/img/img_prod/995386/mini_melissa_ultragirl_swett_dreams_173_1_506e0ed8b072955068af2e0a6921c68c.jpeg | H65: https://images.tcdn.com.br/img/img_prod/995386/mini_melissa_ultragirl_swett_dreams_173_2_c4af13482e780d2e1333dfbd13517468.jpeg | K65: 55.00 | L65: 500 | M65: 0.00 | N65: 0 | O65: 0 | P65: Não | S65: 0.00 | T65: Não | U65: Não | V65: Não | W65: 10 | X65: Melissa | Y65: ULTRAGIRL | Z65: P173 | AA65: 173 | AB65: 7 dias após o recebimento do produto | AE65: 0.00 | AF65: 0.00 | AG65: Imediata | AJ65: 25 | AK65: 15 | AL65: 10 | AM65: 45294 | AN65: 45294 | AP65: Melissas novas, seminovas e usadas. Em ótimas condições de conservação. Todas higienizadas.Moda circular sustentável!Porque uma melissa bem cuidada é para sempre!? | AS65: https://www.minhamania.net/mini-melissa/mini-melissa-ultragirl-swett-dreams | AU65: Infantil
B66: 995386 | C66: 161 | D66: 44321 | E66: Mini Melissa Ultragirl Chic | F66: 175 | G66: https://images.tcdn.com.br/img/img_prod/995386/mini_melissa_ultragirl_chic_175_1_1f73624827c28498c47a90865ba8794e.jpeg | H66: https://images.tcdn.com.br/img/img_prod/995386/mini_melissa_ultragirl_chic_175_2_5b6fa2561d8b6bfc45c6c9b26d39d467.jpg | K66: 55.00 | L66: 500 | M66: 0.00 | N66: 0 | O66: 0 | P66: Não | S66: 0.00 | T66: Não | U66: Não | V66: Não | W66: 6 | X66: Melissa | Y66: ULTRAGIRL | Z66: V175P187 | AA66: 175 | AB66: 7 dias após o recebimento do produto | AE66: 0.00 | AF66: 0.00 | AG66: Imediata | AJ66: 25 | AK66: 15 | AL66: 10 | AM66: 45190 | AN66: 45189 | AP66: Melissas novas, seminovas e usadas. Em ótimas condições de conservação. Todas higienizadas.Moda circular sustentável!Porque uma melissa bem cuidada é para sempre!? | AS66: https://www.minhamania.net/mini-melissa/mini-melissa-ultragirl-chic | AU66: Infantil
B67: 995386 | C67: 161 | D67: 44323 | E67: Mini Melissa Aranha Pequeno Principe | F67: 179 | G67: https://images.tcdn.com.br/img/img_prod/995386/mini_melissa_aranha_pequeno_principe_179_1_52920fa7e6a84aee06ca504c859a5929.jpeg | H67: https://images.tcdn.com.br/img/img_prod/995386/mini_melissa_aranha_pequeno_principe_179_2_54c7dfec30817121b30b028914b214d4.jpeg | K67: 45.00 | L67: 500 | M67: 0.00 | N67: 0 | O67: 0 | P67: Não | S67: 0.00 | T67: Não | U67: Não | V67: Não | W67: 1 | X67: Melissa | Y67: Aranha | Z67: V179P189 | AA67: 179 | AE67: 0.00 | AF67: 0.00 | AJ67: 20 | AK67: 12 | AL67: 10 | AM67: 44695 | AN67: 44902 | AP67: Melissas novas, seminovas e usadas. Em ótimas condições de conservação. Todas higienizadas.Moda circular sustentável!Porque uma melissa bem cuidada é para sempre!? | AS67: https://www.minhamania.net/mini-melissa/mini-melissa-aranha-pequeno-principe | AU67: Infantil
B68: 995386 | C68: 161 | D68: 44323 | E68: Mini Melissa Maggie Boneca | F68: 181 | G68: https://images.tcdn.com.br/img/img_prod/995386/mini_melissa_maggie_boneca_181_1_825d05f478c28bea1edf8d6613811bc8.jpeg | H68: https://images.tcdn.com.br/img/img_prod/995386/mini_melissa_maggie_boneca_181_1_64b9b266839c9077d5841a981cfe0ccd.png | K68: 60.00 | L68: 500 | M68: 0.00 | N68: 0 | O68: 0 | P68: Não | S68: 0.00 | T68: Não | U68: Não | V68: Não | W68: 8 | X68: Melissa | Y68: MAGGIE | Z68: P181 | AA68: 181 | AB68: 7 dias após o recebimento do produto | AE68: 0.00 | AF68: 0.00 | AG68: Imediata | AJ68: 25 | AK68: 15 | AL68: 10 | AM68: 44850 | AN68: 44916 | AP68: Melissas novas, seminovas e usadas. Em ótimas condições de conservação. Todas higienizadas.Moda circular sustentável!Porque uma melissa bem cuidada é para sempre!? | AS68: https://www.minhamania.net/mini-melissa/mini-melissa-maggie-boneca | AU68: Infantil
B69: 995386 | C69: 161 | D69: 44323 | E69: Mini Melissa Aranha Vivienne Westwood | F69: 183 | G69: https://images.tcdn.com.br/img/img_prod/995386/mini_melissa_ultragirl_vivienne_westwood_183_1_e34d307351f2eef4c355a5862c5a4ce7.png | H69: https://images.tcdn.com.br/img/img_prod/995386/mini_melissa_aranha_vivienne_westwood_183_2_73d86f9c734f47a37a65754692eb30f5.jpeg | K69: 50.00 | L69: 500 | M69: 0.00 | N69: -1 | O69: 0 | P69: Não | S69: 0.00 | T69: Não | U69: Não | V69: Não | W69: 3 | Z69: P183 | AA69: 183 | AB69: 7 dias após o recebimento do produto | AE69: 0.00 | AF69: 0.00 | AG69: Imediata | AJ69: 20 | AK69: 12 | AL69: 10 | AM69: 44734 | AN69: 45462 | AP69: Melissas novas, seminovas e usadas. Em ótimas condições de conservação. Todas higienizadas.Moda circular sustentável!Porque uma melissa bem cuidada é para sempre!? | AS69: https://www.minhamania.net/mini-melissa/mini-melissa-ultragirl-vivienne-westwood | AU69: Infantil
B70: 995386 | C70: 159 | D70: 44323 | E70: Melissa Color Pop + Malevola | F70: 185 | G70: https://images.tcdn.com.br/img/img_prod/995386/melissa_color_pop_malevola_185_1_31f138d7ad0235bc6b5b0a03862daa90.png | K70: 55.00 | L70: 500 | M70: 0.00 | N70: 0 | O70: 0 | P70: Não | S70: 0.00 | T70: Não | U70: Não | V70: Não | W70: 1 | X70: Melissa | Y70: POP | Z70: V185P96 | AA70: 185 | AB70: 7 dias após o recebimento do produto | AE70: 0.00 | AF70: 0.00 | AG70: Imediata | AJ70: 25 | AK70: 15 | AL70: 10 | AM70: 44459 | AN70: 44474 | AP70: Melissas novas, seminovas e usadas. Em ótimas condições de conservação. Todas higienizadas.Moda circular sustentável!Porque uma melissa bem cuidada é para sempre!? | AS70: https://www.minhamania.net/melissa-mell-teen/melissa-color-pop-malevola | AU70: Adulto
B71: 995386 | C71: 161 | D71: 44323 | E71: Mini Melissa Sneaker Be | F71: 187 | G71: https://images.tcdn.com.br/img/img_prod/995386/mini_melissa_sneaker_be_ad_187_1_58dd1dcb13c06f0dedb70845b0a49895.jpeg | H71: https://images.tcdn.com.br/img/img_prod/995386/mini_melissa_sneaker_be_ad_187_2_4a0ce437a13cd5f10e06671a6fc22e2e.jpeg | I71: https://images.tcdn.com.br/img/img_prod/995386/mini_melissa_sneaker_be_ad_187_3_5514c5062c18a03cfe63a97c5f4350f2.jpeg | J71: https://images.tcdn.com.br/img/img_prod/995386/mini_melissa_sneaker_be_ad_187_5_eb75e71d4aedddbf654d7e1703a38d21.jpeg | K71: 55.00 | L71: 500 | M71: 0.00 | N71: 0 | O71: 0 | P71: Não | S71: 0.00 | T71: Não | U71: Não | V71: Não | W71: 17 | X71: Melissa | Y71: SN | Z71: V187P171 | AA71: 187 | AB71: 7 dias após o recebimento do produto | AE71: 40.00 | AF71: 0.00 | AG71: Imediata | AJ71: 20 | AK71: 12 | AL71: 10 | AM71: 45175 | AN71: 45175 | AP71: Melissas novas, seminovas e usadas. Em ótimas condições de conservação. Todas higienizadas.Moda circular sustentável!Porque uma melissa bem cuidada é para sempre!? | AS71: https://www.minhamania.net/mini-melissa/mini-melissa-sneaker-be-ad | AU71: Infantil
B72: 995386 | C72: 161 | D72: 44323 | E72: Mini Melissa Mar Sandal | F72: 189 | G72: https://images.tcdn.com.br/img/img_prod/995386/mini_melissa_mar_sandal_189_1_277507afc5405e3c86ee6affc081470b.jpg | H72: https://images.tcdn.com.br/img/img_prod/995386/mini_melissa_mar_sandal_189_3_6bcc3d519895de4cc7ed72eb411edbbe.jpeg | I72: https://images.tcdn.com.br/img/img_prod/995386/mini_melissa_mar_sandal_189_1_0844049483658a88fd5470c7127acf5d.jpeg | J72: https://images.tcdn.com.br/img/img_prod/995386/mini_melissa_mar_sandal_189_3_6baeb287e8e624fc0af61278ebb7d264.jpeg | K72: 55.00 | L72: 500 | M72: 0.00 | N72: 0 | O72: 0 | P72: Não | S72: 0.00 | T72: Não | U72: Não | V72: Não | W72: 47 | X72: Melissa | Y72: MAR SANDAL | Z72: P189 | AA72: 189 | AB72: 7 dias após o recebimento do produto | AE72: 0.00 | AF72: 0.00 | AG72: Imediata | AJ72: 25 | AK72: 15 | AL72: 10 | AM72: 44692 | AN72: 45307 | AP72: Melissas novas, seminovas e usadas. Em ótimas condições de conservação. Todas higienizadas.Moda circular sustentável!Porque uma melissa bem cuidada é para sempre!? | AS72: https://www.minhamania.net/mini-melissa/mini-melissa-mar-sandal | AT72: https://images.tcdn.com.br/img/img_prod/995386/mini_melissa_mar_sandal_189_5_fd6a3d00712d979b9409bb3d0e1c7009.jpg, https://images.tcdn.com.br/img/img_prod/995386/mini_melissa_mar_sandal_189_6_09a6395bdaec49f5153a086992b6b688.jpg | AU72: Infantil
B73: 995386 | C73: 161 | D73: 44323 | E73: Mini Melissa Campana Papel | F73: 191 | G73: https://images.tcdn.com.br/img/img_prod/995386/mini_melissa_campana_papel_191_1_343ef39ed5879c37d5f7abe59aab0669.jpg | H73: https://images.tcdn.com.br/img/img_prod/995386/mini_melissa_campana_papel_191_2_76a9040358ed65e918e5e5fc09185d0e.jpeg | I73: https://images.tcdn.com.br/img/img_prod/995386/mini_melissa_campana_papel_191_5_8af5f57a7606fc10ee4656f3c46cf2b2.jpg | J73: https://images.tcdn.com.br/img/img_prod/995386/mini_melissa_campana_papel_191_7_2b00ccf2dcfc44a9e04e89a6663173f8.jpg | K73: 50.00 | L73: 500 | M73: 0.00 | N73: 0 | O73: 0 | P73: Não | S73: 0.00 | T73: Não | U73: Não | V73: Não | W73: 60 | X73: Melissa | Y73: CAMPANA | Z73: V191P187 | AA73: 191 | AB73: 7 dias após o recebimento do produto | AE73: 0.00 | AF73: 0.00 | AG73: Imediata | AJ73: 25 | AK73: 15 | AL73: 10 | AM73: 45470 | AN73: 45477 | AP73: Melissas novas, seminovas e usadas. Em ótimas condições de conservação. Todas higienizadas.Moda circular sustentável!Porque uma melissa bem cuidada é para sempre!? | AS73: https://www.minhamania.net/mini-melissa/mini-melissa-campana-papel | AT73: https://images.tcdn.com.br/img/img_prod/995386/mini_melissa_campana_papel_191_5_a990ca67e29568c76b3fb3be5780b335.jpg, https://images.tcdn.com.br/img/img_prod/995386/mini_melissa_campana_papel_191_6_debeebfea80b730f4a594cfbabc15975.jpg | AU73: Infantil
B74: 995386 | C74: 161 | D74: 44323 | E74: Mini Melissa Wide Sandal | F74: 193 | G74: https://images.tcdn.com.br/img/img_prod/995386/mini_melissa_wide_sandal_193_1_ea5197dddc8167d70c9dd08eeb718425.jpg | H74: https://images.tcdn.com.br/img/img_prod/995386/mini_melissa_wide_sandal_193_1_47f5804a1dc2e70134d355ad5814e0dd.png | I74: https://images.tcdn.com.br/img/img_prod/995386/mini_melissa_wide_sandal_193_3_739560b4437dc1be67b653ea848eb8f1.jpg | J74: https://images.tcdn.com.br/img/img_prod/995386/mini_melissa_wide_sandal_193_8_48b659377fb5f3493ab935c56ab365bc.jpg | K74: 55.00 | L74: 500 | M74: 0.00 | N74: 1 | O74: 0 | P74: Sim | S74: 0.00 | T74: Não | U74: Não | V74: Não | W74: 39 | X74: Melissa | Y74: WIDE | Z74: P193 | AA74: 193 | AB74: 7 dias após o recebimento do produto | AE74: 0.00 | AF74: 0.00 | AG74: Imediata | AJ74: 25 | AK74: 15 | AL74: 10 | AM74: 45461 | AN74: 45418 | AP74: Melissas novas, seminovas e usadas. Em ótimas condições de conservação. Todas higienizadas.Moda circular sustentável!Porque uma melissa bem cuidada é para sempre!? | AS74: https://www.minhamania.net/mini-melissa/mini-melissa-wide-sandal | AU74: Infantil
B75: 995386 | C75: 161 | D75: 44323 | E75: Mini Melissa Ultragirl Girly | F75: 195 | G75: https://images.tcdn.com.br/img/img_prod/995386/mini_melissa_ultragirl_girly_195_1_9819acf8949dfb36440da6011d0dea8b.jpeg | K75: 55.00 | L75: 500 | M75: 0.00 | N75: 0 | O75: 0 | P75: Não | S75: 0.00 | T75: Não | U75: Não | V75: Não | W75: 8 | X75: Melissa | Y75: GIRLY | Z75: V195P191 | AA75: 195 | AB75: 7 dias após o recebimento do produto | AE75: 0.00 | AF75: 0.00 | AG75: Imediata | AJ75: 25 | AK75: 15 | AL75: 10 | AM75: 45190 | AN75: 45396 | AP75: Melissas novas, seminovas e usadas. Em ótimas condições de conservação. Todas higienizadas.Moda circular sustentável!Porque uma melissa bem cuidada é para sempre!? | AS75: https://www.minhamania.net/mini-melissa/mini-melissa-ultragirl-girly | AU75: Infantil
B76: 995386 | C76: 161 | D76: 44323 | E76: Mini Melissa Jean + Jason Wu | F76: 197 | G76: https://images.tcdn.com.br/img/img_prod/995386/mini_melissa_sapatilha_jason_wu_197_1_4bf553b7c3d6a2689ae425d99ff0f9cc.jpeg | H76: https://images.tcdn.com.br/img/img_prod/995386/mini_melissa_sapatilha_jason_wu_197_2_9ba7c19ec9f734fc3aa57e13744a8587.jpeg | I76: https://images.tcdn.com.br/img/img_prod/995386/mini_melissa_jean_jason_wu_197_3_10372d6c76e0b7b9932ae2976d6cb824.jpeg | K76: 40.00 | L76: 500 | M76: 0.00 | N76: 0 | O76: 0 | P76: Não | S76: 0.00 | T76: Não | U76: Não | V76: Não | W76: 13 | X76: Melissa | Y76: JASON WU | Z76: V197P87 | AA76: 197 | AB76: 7 dias após o recebimento do produto | AE76: 0.00 | AF76: 0.00 | AG76: Imediata | AJ76: 25 | AK76: 15 | AL76: 10 | AM76: 44932 | AN76: 45366 | AP76: Melissas novas, seminovas e usadas. Em ótimas condições de conservação. Todas higienizadas.Moda circular sustentável!Porque uma melissa bem cuidada é para sempre!? | AS76: https://www.minhamania.net/mini-melissa/mini-melissa-sapatilha-jason-wu | AU76: Infantil
